Workbook

Sheet Resumo
A1: Previdência privada - resumo
A2: Coleta de 24/09/2026 12:36
A4: Plataforma | B4: Renda Fixa | C4: Multimercado | D4: Ações | E4: Cambial | F4: Internacional | G4: Previdência | H4: Outros | I4: Total | J4: Com CNPJ | K4: Gestoras distintas
A5: XP Investimentos | B5: =COUNTIFS(Consolidado!$A$2:$A$486,$A5,Consolidado!$G$2:$G$486,B$4) | C5: =COUNTIFS(Consolidado!$A$2:$A$486,$A5,Consolidado!$G$2:$G$486,C$4) | D5: =COUNTIFS(Consolidado!$A$2:$A$486,$A5,Consolidado!$G$2:$G$486,D$4) | E5: =COUNTIFS(Consolidado!$A$2:$A$486,$A5,Consolidado!$G$2:$G$486,E$4) | F5: =COUNTIFS(Consolidado!$A$2:$A$486,$A5,Consolidado!$G$2:$G$486,F$4) | G5: =COUNTIFS(Consolidado!$A$2:$A$486,$A5,Consolidado!$G$2:$G$486,G$4) | H5: =COUNTIFS(Consolidado!$A$2:$A$486,$A5,Consolidado!$G$2:$G$486,H$4) | I5: =COUNTIF(Consolidado!$A$2:$A$486,$A5) | J5: =COUNTIFS(Consolidado!$A$2:$A$486,$A5,Consolidado!$C$2:$C$486,"<>") | K5: 70
A6: BTG Pactual | B6: =COUNTIFS(Consolidado!$A$2:$A$486,$A6,Consolidado!$G$2:$G$486,B$4) | C6: =COUNTIFS(Consolidado!$A$2:$A$486,$A6,Consolidado!$G$2:$G$486,C$4) | D6: =COUNTIFS(Consolidado!$A$2:$A$486,$A6,Consolidado!$G$2:$G$486,D$4) | E6: =COUNTIFS(Consolidado!$A$2:$A$486,$A6,Consolidado!$G$2:$G$486,E$4) | F6: =COUNTIFS(Consolidado!$A$2:$A$486,$A6,Consolidado!$G$2:$G$486,F$4) | G6: =COUNTIFS(Consolidado!$A$2:$A$486,$A6,Consolidado!$G$2:$G$486,G$4) | H6: =COUNTIFS(Consolidado!$A$2:$A$486,$A6,Consolidado!$G$2:$G$486,H$4) | I6: =COUNTIF(Consolidado!$A$2:$A$486,$A6) | J6: =COUNTIFS(Consolidado!$A$2:$A$486,$A6,Consolidado!$C$2:$C$486,"<>") | K6: 89
A7: Itaú Private | B7: =COUNTIFS(Consolidado!$A$2:$A$486,$A7,Consolidado!$G$2:$G$486,B$4) | C7: =COUNTIFS(Consolidado!$A$2:$A$486,$A7,Consolidado!$G$2:$G$486,C$4) | D7: =COUNTIFS(Consolidado!$A$2:$A$486,$A7,Consolidado!$G$2:$G$486,D$4) | E7: =COUNTIFS(Consolidado!$A$2:$A$486,$A7,Consolidado!$G$2:$G$486,E$4) | F7: =COUNTIFS(Consolidado!$A$2:$A$486,$A7,Consolidado!$G$2:$G$486,F$4) | G7: =COUNTIFS(Consolidado!$A$2:$A$486,$A7,Consolidado!$G$2:$G$486,G$4) | H7: =COUNTIFS(Consolidado!$A$2:$A$486,$A7,Consolidado!$G$2:$G$486,H$4) | I7: =COUNTIF(Consolidado!$A$2:$A$486,$A7) | J7: =COUNTIFS(Consolidado!$A$2:$A$486,$A7,Consolidado!$C$2:$C$486,"<>") | K7: 3
A9: Como ler esta planilha:
A10: As contagens por classe e os totais são fórmulas sobre a aba Consolidado (o catálogo);
A11: "Gestoras distintas" é um valor da coleta, não uma fórmula: contar valores únicos exigiria
A12: função de matriz, que nem todo leitor de planilha avalia da mesma forma.
A13: Uma plataforma com poucos fundos pode ser fonte parcial, não prateleira enxuta - confira a aba Coleta.

Sheet Consolidado
A1: Plataforma | B1: Fundo | C1: CNPJ | D1: Gestora | E1: CNPJ da gestora | F1: Administrador | G1: Classe | H1: Categoria na origem | I1: Aplicação mínima (R$) | J1: Taxa adm (%) | K1: Taxa perf (%) | L1: Benchmark | M1: Cotização resgate (D+) | N1: Líquidação resgate (D+) | O1: Carência (dias) | P1: Tributação | Q1: Fechado p/ captação | R1: Fontes | S1: Nº de fontes | T1: Open Finance | U1: Prateleira (site) | V1: Área logada | W1: Link
A2: XP Investimentos | B2: A1 Hedge Prev Xp Seg Prev Ficfim Rl | C2: 44.409.267/0001-02 | D2: XP VIDA E PREVIDÊNCIA S.A. | E2: 29.408.732/0001-05 | F2: XP Investimentos | G2: Multimercado | H2: Macro Alta Vol | I2: 100 | J2: 2.1 | M2: 22 | N2: 2 | Q2: Não | R2: Site (navegador) | S2: 1 | T2: Não | U2: Sim | V2: Não
A3: XP Investimentos | B3: A1 High Grade Prev XP Seg FIC FIRF CP RL | C3: 63.573.988/0001-06 | D3: ASSET1 INVESTIMENTOS S/A | E3: 35.185.577/0001-08 | F3: Intrag DTVM | G3: Renda Fixa | H3: Crédito Liquidez | I3: 100 | J3: 0.85 | M3: 0 | N3: 2 | Q3: Não | R3: Site (navegador) | S3: 1 | T3: Não | U3: Sim | V3: Não
A4: XP Investimentos | B4: A1 Renda Fixa Ativa Xp Seguros Firf | C4: 52.955.280/0001-95 | D4: ASSET1 INVESTIMENTOS S/A | E4: 35.185.577/0001-08 | F4: XP Investimentos | G4: Multimercado | H4: Renda Fixa Ativo | I4: 100 | J4: 0.9 | M4: 0 | N4: 1 | Q4: Não | R4: Site (navegador) | S4: 1 | T4: Não | U4: Sim | V4: Não
A5: XP Investimentos | B5: ARX Income 100 XP Seg Prev FIC FIA | C5: 34.461.754/0001-60 | D5: XP VIDA E PREVIDÊNCIA S.A. | E5: 29.408.732/0001-05 | F5: BNY Mellon DTVM | G5: Ações | H5: Renda Variável Dividendos | I5: 100 | J5: 2 | M5: 6 | N5: 2 | Q5: Não | R5: Site (navegador) | S5: 1 | T5: Não | U5: Sim | V5: Não
A6: XP Investimentos | B6: AZ Quest Inflação Ativo Prev FIE FIRF | C6: 34.442.059/0001-51 | D6: AZ Quest Prev Ltda. | E6: 59.312.965/0001-62 | F6: BNY Mellon DTVM | G6: Renda Fixa | H6: Renda Fixa Inflação | I6: 500 | J6: 1.1 | M6: 0 | N6: 1 | Q6: Sim | R6: Site (navegador) | S6: 1 | T6: Não | U6: Sim | V6: Não
A7: XP Investimentos | B7: AZ Quest Luce Advisory Prev XP Seg FICFIRF CP | C7: 32.847.001/0001-62 | D7: XP VIDA E PREVIDÊNCIA S.A. | E7: 29.408.732/0001-05 | F7: XPI Administradora - Modal | G7: Renda Fixa | H7: Crédito Liquidez | I7: 100 | J7: 1 | M7: 1 | N7: 2 | Q7: Não | R7: Site (navegador) | S7: 1 | T7: Não | U7: Sim | V7: Não
A8: XP Investimentos | B8: Absolute Atenas Xp Seg Prev Fie I Fic Firf Cp Rl | C8: 62.213.987/0001-80 | D8: ABSOLUTE CRÉDITO GESTÃO DE INVESTIMENTOS LTDA. | E8: 47.243.769/0001-02 | F8: BTG Pactual DTVM | G8: Renda Fixa | H8: Crédito Liquidez | I8: 100 | J8: 0.98 | M8: 6 | N8: 2 | Q8: Não | R8: Site (navegador) | S8: 1 | T8: Não | U8: Sim | V8: Não
A9: XP Investimentos | B9: Absolute Delfos Xp Seg Prev Fie I Fic Rf Cp Rl | C9: 61.904.092/0001-29 | D9: ABSOLUTE CRÉDITO GESTÃO DE INVESTIMENTOS LTDA. | E9: 47.243.769/0001-02 | F9: Intrag DTVM | G9: Renda Fixa | H9: Crédito High Grade | I9: 100 | J9: 0.88 | M9: 20 | N9: 2 | Q9: Não | R9: Site (navegador) | S9: 1 | T9: Não | U9: Sim | V9: Não
A10: XP Investimentos | B10: Absolute Endurance XP Seg FICFIA Prev | C10: 37.355.605/0001-05 | D10: ABSOLUTE GESTAO DE INVESTIMENTOS LTDA | E10: 17.285.755/0001-82 | F10: BNY Mellon DTVM | G10: Ações | H10: Renda Variável Long Only | I10: 100 | J10: 2 | M10: 21 | N10: 2 | Q10: Não | R10: Site (navegador) | S10: 1 | T10: Não | U10: Sim | V10: Não
A11: XP Investimentos | B11: Absolute Pace Xp Seg Prev Fif Em Ações Rl | C11: 61.201.512/0001-00 | D11: ABSOLUTE GESTAO DE INVESTIMENTOS LTDA | E11: 17.285.755/0001-82 | F11: BTG Pactual DTVM | G11: Ações | H11: Renda Variável Long Biased | I11: 100 | J11: 2 | M11: 22 | N11: 2 | Q11: Sim | R11: Site (navegador) | S11: 1 | T11: Não | U11: Sim | V11: Não
A12: XP Investimentos | B12: Absolute Vertex XP Seg Prev FIC FIM | C12: 40.882.496/0001-99 | D12: XP VIDA E PREVIDÊNCIA S.A. | E12: 29.408.732/0001-05 | F12: XPI Administradora - Modal | G12: Multimercado | H12: Macro Alta Vol | I12: 100 | J12: 2 | M12: 21 | N12: 1 | Q12: Não | R12: Site (navegador) | S12: 1 | T12: Não | U12: Sim | V12: Não
A13: XP Investimentos | B13: Ace Capital Prev Iq Xp Seg Fic Fim | C13: 37.541.379/0001-57 | D13: ACE CAPITAL GESTORA DE RECURSOS LTDA. | E13: 33.411.393/0001-85 | F13: Intrag DTVM | G13: Multimercado | H13: Macro Média Vol | I13: 100 | J13: 2 | M13: 6 | N13: 1 | Q13: Não | R13: Site (navegador) | S13: 1 | T13: Não | U13: Sim | V13: Não
... A39: XP Investimentos | B39: Capitânia Reit Prev Adv XP Seg FIE I FIC FIM CP | C39: 35.955.948/0001-85 | D39: CAPITANIA PREV S.A. | E39: 41.777.833/0001-40 | F39: BNY Mellon DTVM | G39: Multimercado | H39: Crédito Híbrido | I39: 100 | J39: 1.25 | M39: 59 | N39: 1 | Q39: Não | R39: Site (navegador) | S39: 1 | T39: Não | U39: Sim | V39: Não
A40: XP Investimentos | B40: Claritas Total Return XP Seg Prev FIE FIC FIM | C40: 37.396.828/0001-10 | D40: Claritas Investimentos (OLD) | F40: BNY Mellon DTVM | G40: Multimercado | H40: Macro Alta Vol | I40: 100 | J40: 2 | M40: 22 | N40: 2 | Q40: Sim | R40: Site (navegador) | S40: 1 | T40: Não | U40: Sim | V40: Não
A41: XP Investimentos | B41: Constellation XP Seg 100 Prev FIC FIM | C41: 35.651.477/0001-11 | D41: CONSTELLATION INVESTIMENTOS E PARTICIPAÇÕES LTDA | E41: 06.182.127/0001-55 | F41: XP Investimentos | G41: Multimercado | H41: Renda Variável Long Only | I41: 1000 | J41: 2 | M41: 40 | N41: 2 | Q41: Não | R41: Site (navegador) | S41: 1 | T41: Não | U41: Sim | V41: Não
A42: XP Investimentos | B42: DNA Energy Prev XP Seg FIM | C42: 35.420.731/0001-70 | D42: XP ADVISORY GESTAO DE RECURSOS LTDA | E42: 15.289.957/0001-77 | F42: XP Investimentos | G42: Multimercado | H42: Multiestratégia | I42: 100 | J42: 0.8 | M42: 6 | N42: 3 | Q42: Não | R42: Site (navegador) | S42: 1 | T42: Não | U42: Sim | V42: Não
A43: XP Investimentos | B43: Dahlia 100 Advisory XP Seg Prev FIC FIM | C43: 36.327.214/0001-14 | D43: DAHLIA CAPITAL GESTÃO DE RECURSOS LTDA. | E43: 09.551.766/0001-39 | F43: BNY Mellon DTVM | G43: Multimercado | H43: Renda Variável Long Only | I43: 100 | J43: 2 | M43: 10 | N43: 2 | Q43: Não | R43: Site (navegador) | S43: 1 | T43: Não | U43: Sim | V43: Não
A44: XP Investimentos | B44: Dahlia 70 Advisory Xp Seg Ii Prev Fic Fim | C44: 43.761.805/0001-60 | D44: XP VIDA E PREVIDÊNCIA S.A. | E44: 29.408.732/0001-05 | F44: XPI Administradora - Modal | G44: Multimercado | H44: Renda Variável Long Only | I44: 100 | J44: 1.5 | M44: 7 | N44: 2 | Q44: Não | R44: Site (navegador) | S44: 1 | T44: Não | U44: Sim | V44: Não
A45: XP Investimentos | B45: Dahlia Global 50 Advisory XP Seg Prev FIC FIM | C45: 37.645.515/0001-59 | D45: DAHLIA CAPITAL GESTÃO DE RECURSOS LTDA. | E45: 09.551.766/0001-39 | F45: BNY Mellon DTVM | G45: Multimercado | H45: Internacional Multimercado Não Hedgeado | I45: 100 | J45: 1.25 | M45: 7 | N45: 2 | Q45: Não | R45: Site (navegador) | S45: 1 | T45: Não | U45: Sim | V45: Não
A46: XP Investimentos | B46: Daycoval Classic Xp Seg Prev Fif Rf Cp Rl | C46: 61.941.773/0001-67 | D46: DAYCOVAL ASSET MANAGEMENT ADMINISTRACAO DE RECURSOS LTDA | E46: 72.027.832/0001-02 | F46: Banco Daycoval | G46: Renda Fixa | H46: Crédito Liquidez | I46: 100 | J46: 0.82 | M46: 0 | N46: 1 | Q46: Não | R46: Site (navegador) | S46: 1 | T46: Não | U46: Sim | V46: Não
A47: XP Investimentos | B47: Drys Shelter Prev XP FIRF CP RL | C47: 63.285.329/0001-66 | D47: DRYS CAPITAL LTDA | E47: 08.204.817/0001-93 | F47: BNY Mellon DTVM | G47: Renda Fixa | H47: Crédito Liquidez | I47: 100 | J47: 0.8 | M47: 5 | N47: 1 | Q47: Não | R47: Site (navegador) | S47: 1 | T47: Não | U47: Sim | V47: Não
A48: XP Investimentos | B48: Encore Long Biased 100 Xp Seg Prev Ficfim Rl | C48: 41.866.111/0001-62 | D48: XP VIDA E PREVIDÊNCIA S.A. | E48: 29.408.732/0001-05 | F48: XPI Administradora - Modal | G48: Multimercado | H48: Renda Variável Long Biased | I48: 100 | J48: 2 | M48: 20 | N48: 2 | Q48: Não | R48: Site (navegador) | S48: 1 | T48: Não | U48: Sim | V48: Não
A49: XP Investimentos | B49: Encore Long Biased 70 XP Seg Prev FIC FIM | C49: 41.802.178/0001-33 | D49: XP VIDA E PREVIDÊNCIA S.A. | E49: 29.408.732/0001-05 | F49: XPI Administradora - Modal | G49: Multimercado | H49: Renda Variável Long Biased | I49: 100 | J49: 1.5 | M49: 7 | N49: 2 | Q49: Não | R49: Site (navegador) | S49: 1 | T49: Não | U49: Sim | V49: Não
A50: XP Investimentos | B50: Forpus 100 XP Seg Prev FICFIA | C50: 40.212.923/0001-21 | D50: FORPUS CAPITAL GESTÃO DE RECURSOS LTDA. | E50: 21.018.289/0001-46 | F50: BNY Mellon DTVM | G50: Ações | H50: Renda Variável Long Only | I50: 100 | J50: 2 | M50: 8 | N50: 2 | Q50: Não | R50: Site (navegador) | S50: 1 | T50: Não | U50: Sim | V50: Não
A51: XP Investimentos | B51: Forpus 70 XP Seg Prev FIM | C51: 42.870.699/0001-90 | D51: FORPUS CAPITAL GESTÃO DE RECURSOS LTDA. | E51: 21.018.289/0001-46 | F51: BNY Mellon DTVM | G51: Multimercado | H51: Renda Variável Long Only | I51: 100 | J51: 2 | M51: 7 | N51: 2 | Q51: Não | R51: Site (navegador) | S51: 1 | T51: Não | U51: Sim | V51: Não
A52: XP Investimentos | B52: Franklin Valor e Liquidez 70 XP Seg FIM | C52: 32.319.047/0001-09 | D52: Franklin Templeton Brasil Ltda. | E52: 07.437.241/0001-41 | F52: BNY Mellon DTVM | G52: Multimercado | H52: Renda Variável Long Only | I52: 100 | J52: 2 | M52: 2 | N52: 2 | Q52: Não | R52: Site (navegador) | S52: 1 | T52: Não | U52: Sim | V52: Não
... A113: XP Investimentos | B113: Lis 100 Prev Xp Seguros Ficfim Rl | C113: 47.033.051/0001-83 | D113: XP VIDA E PREVIDÊNCIA S.A. | E113: 29.408.732/0001-05 | F113: XP Investimentos | G113: Multimercado | H113: Renda Variável Small/Mid Caps | I113: 100 | J113: 2 | M113: 30 | N113: 2 | Q113: Não | R113: Site (navegador) | S113: 1 | T113: Não | U113: Sim | V113: Não
A114: XP Investimentos | B114: Lis 70 Xp Seg Prev Ficfim Rl | C114: 43.860.692/0001-50 | D114: XP Vida e Previdência | F114: XP Investimentos | G114: Multimercado | H114: Renda Variável Small/Mid Caps | I114: 100 | J114: 2 | M114: 7 | N114: 2 | Q114: Sim | R114: Site (navegador) | S114: 1 | T114: Não | U114: Sim | V114: Não
A115: XP Investimentos | B115: M Global 40 Xp Seg Prev Fic Fim Rl | C115: 40.682.081/0001-71 | D115: XP ALLOCATION ASSET MANAGEMENT LTDA | E115: 37.918.829/0001-88 | F115: XP Investimentos | G115: Multimercado | H115: Internacional Ações Não Hedgeado | I115: 100 | J115: 0.94 | M115: 3 | N115: 3 | Q115: Não | R115: Site (navegador) | S115: 1 | T115: Não | U115: Sim | V115: Não
A116: XP Investimentos | B116: M8 Capital XP Seg Previdência FIC FIRF CP RL | C116: 61.539.506/0001-68 | D116: M8 PARTNERS GESTORA DE RECURSOS LTDA. | E116: 18.038.439/0001-79 | F116: BTG Pactual DTVM | G116: Renda Fixa | H116: Crédito High Yield | I116: 100 | J116: 1 | M116: 7 | N116: 2 | Q116: Não | R116: Site (navegador) | S116: 1 | T116: Não | U116: Sim | V116: Não
A117: XP Investimentos | B117: MAG Prev XP Seg Advisory FIRF CP | C117: 32.385.140/0001-11 | D117: MONGERAL AEGON INVESTIMENTOS LTDA | E117: 16.500.294/0001-50 | F117: BNY Mellon DTVM | G117: Renda Fixa | H117: Crédito High Grade | I117: 100 | J117: 0.95 | M117: 1 | N117: 1 | Q117: Não | R117: Site (navegador) | S117: 1 | T117: Não | U117: Sim | V117: Não
A118: XP Investimentos | B118: Mag Cash Xp Seg Prev Ficfirf Rl | C118: 58.543.779/0001-71 | D118: MONGERAL AEGON INVESTIMENTOS LTDA | E118: 16.500.294/0001-50 | F118: BNY Mellon DTVM | G118: Renda Fixa | H118: Crédito Liquidez | I118: 100 | J118: 0.8 | M118: 0 | N118: 1 | Q118: Sim | R118: Site (navegador) | S118: 1 | T118: Não | U118: Sim | V118: Não
A119: XP Investimentos | B119: Mag Prev Rf Fic Fim | C119: 45.645.112/0001-38 | D119: XP VIDA E PREVIDÊNCIA S.A. | E119: 29.408.732/0001-05 | F119: XPI Administradora - Modal | G119: Multimercado | H119: Renda Fixa Ativo | I119: 100 | J119: 0.7 | M119: 0 | N119: 1 | Q119: Não | R119: Site (navegador) | S119: 1 | T119: Não | U119: Sim | V119: Não
A120: XP Investimentos | B120: Mantaro LB Prev Advisory XP Seg FIC FIM | C120: 36.327.253/0001-11 | D120: MANTARO CAPITAL LTDA | E120: 43.353.050/0001-65 | F120: BTG Pactual DTVM | G120: Multimercado | H120: Renda Variável Long Biased | I120: 100 | J120: 2 | M120: 15 | N120: 2 | Q120: Não | R120: Site (navegador) | S120: 1 | T120: Não | U120: Sim | V120: Não
A121: XP Investimentos | B121: Mapfre Confianza XP Seg FIC FIF RF RL | C121: 56.385.272/0001-01 | D121: MAPFRE INVESTIMENTOS LTDA. | E121: 04.160.039/0001-27 | F121: BNY Mellon DTVM | G121: Renda Fixa | H121: Crédito Liquidez | I121: 100 | J121: 0.45 | M121: 0 | N121: 0 | Q121: Não | R121: Site (navegador) | S121: 1 | T121: Não | U121: Sim | V121: Não
A122: XP Investimentos | B122: Miles Virtus Advisory XP Seg Prev FIC FIA | C122: 34.475.121/0001-01 | D122: Miles Capital | F122: BNY Mellon DTVM | G122: Ações | H122: Renda Variável Long Only | I122: 100 | J122: 2 | M122: 2 | N122: 2 | Q122: Sim | R122: Site (navegador) | S122: 1 | T122: Não | U122: Sim | V122: Não
A123: XP Investimentos | B123: Moat Prev XP Seg FICFIA | C123: 37.037.432/0001-87 | D123: MOAT CAPITAL GESTÃO DE RECURSOS LTDA | E123: 18.730.786/0001-68 | F123: Intrag DTVM | G123: Ações | H123: Renda Variável Long Only | I123: 100 | J123: 2 | M123: 15 | N123: 2 | Q123: Não | R123: Site (navegador) | S123: 1 | T123: Não | U123: Sim | V123: Não
A124: XP Investimentos | B124: Neo Navitas Prev XP Seg FICFIA | C124: 41.081.187/0001-82 | D124: NEO Investimentos | F124: Intrag DTVM | G124: Ações | H124: Renda Variável Long Only | I124: 100 | J124: 2 | M124: 22 | N124: 2 | Q124: Sim | R124: Site (navegador) | S124: 1 | T124: Não | U124: Sim | V124: Não
A125: XP Investimentos | B125: Novus Bolsa Macro Global Prev Xp Seg Ficfia | C125: 38.035.023/0001-04 | D125: NOVUS CAPITAL GESTORA DE RECURSOS LTDA. | E125: 15.388.425/0001-97 | F125: Intrag DTVM | G125: Ações | H125: Renda Variável Long Biased | I125: 100 | J125: 2 | M125: 21 | N125: 2 | Q125: Sim | R125: Site (navegador) | S125: 1 | T125: Não | U125: Sim | V125: Não
A126: XP Investimentos | B126: Novus Crédito Previdência Xp Fif Em Cotas Fim Cp Rl | C126: 60.818.157/0001-50 | D126: NOVUS CREDITO GESTAO DE RECURSOS LTDA | E126: 42.524.344/0001-40 | F126: BTG Pactual DTVM | G126: Multimercado | H126: Crédito High Grade | I126: 100 | J126: 0.9 | M126: 22 | N126: 1 | Q126: Sim | R126: Site (navegador) | S126: 1 | T126: Não | U126: Sim | V126: Não
A127: XP Investimentos | B127: Occam Liquidez Prev Xp Seg Fic Fim | C127: 40.780.979/0001-82 | D127: XP VIDA E PREVIDÊNCIA S.A. | E127: 29.408.732/0001-05 | F127: XPI Administradora | G127: Multimercado | H127: Macro Baixa Vol | I127: 100 | J127: 1.15 | M127: 0 | N127: 1 | Q127: Não | R127: Site (navegador) | S127: 1 | T127: Não | U127: Sim | V127: Não
A128: XP Investimentos | B128: Occam Liquidez XP Seg Prev FIC FIRF CP RL | C128: 63.799.359/0001-90 | D128: NOVA OCCAM BRASIL GESTAO DE RECURSOS LTDA. | E128: 43.228.545/0001-62 | F128: BNY Mellon DTVM | G128: Renda Fixa | H128: Crédito Liquidez | I128: 100 | J128: 0.8 | M128: 6 | N128: 1 | Q128: Não | R128: Site (navegador) | S128: 1 | T128: Não | U128: Sim | V128: Não
A129: XP Investimentos | B129: Occam Xp Seg Prev Fic Fim Rl | C129: 32.312.361/0001-60 | D129: XP VIDA E PREVIDÊNCIA S.A. | E129: 29.408.732/0001-05 | F129: XPI Administradora - Modal | G129: Multimercado | H129: Long Short Direcional | I129: 100 | J129: 2 | M129: 1 | N129: 2 | Q129: Não | R129: Site (navegador) | S129: 1 | T129: Não | U129: Sim | V129: Não
A130: XP Investimentos | B130: Oceana Long Biased Advisory XP Seg Prev FIC FIM | C130: 38.236.291/0001-94 | D130: OCEANA INVESTIMENTOS ADMINISTRADORA DE CARTEIRA DE VALORES MOBILIÁRIOS LTDA | E130: 09.326.542/0001-23 | F130: BNY Mellon DTVM | G130: Multimercado | H130: Renda Variável Long Biased | I130: 100 | J130: 2 | M130: 21 | N130: 2 | Q130: Não | R130: Site (navegador) | S130: 1 | T130: Não | U130: Sim | V130: Não
A131: XP Investimentos | B131: Oceana Valor Advisory XP Seg Prev FICFIA | C131: 39.958.567/0001-00 | D131: XP VIDA E PREVIDÊNCIA S.A. | E131: 29.408.732/0001-05 | F131: BNY Mellon DTVM | G131: Ações | H131: Renda Variável Long Only | I131: 100 | J131: 2 | M131: 21 | N131: 2 | Q131: Não | R131: Site (navegador) | S131: 1 | T131: Não | U131: Sim | V131: Não
A132: XP Investimentos | B132: Pacifico Macro Prev Advisory Xp Seg Fic Fim | C132: 33.755.685/0001-35 | D132: BTG PACTUAL ASSET MANAGEMENT S/A DTVM | E132: 29.650.082/0001-00 | F132: BTG Pactual DTVM | G132: Multimercado | H132: Macro Alta Vol | I132: 100 | J132: 2 | M132: 1 | N132: 2 | Q132: Sim | R132: Site (navegador) | S132: 1 | T132: Não | U132: Sim | V132: Não
A133: XP Investimentos | B133: Patria Previdenciário XP Seg FIC MM CP RL | C133: 53.990.084/0001-14 | D133: PÁTRIA INVESTIMENTOS LTDA. | E133: 12.461.756/0001-17 | F133: XP Investimentos | G133: Multimercado | H133: Crédito High Yield | I133: 100 | J133: 1.59 | M133: 90 | N133: 2 | Q133: Não | R133: Site (navegador) | S133: 1 | T133: Não | U133: Sim | V133: Não
A134: XP Investimentos | B134: Persevera Prospera Xp Seg Prev Firf Cp | C134: 53.856.982/0001-84 | D134: PERSEVERA GESTÃO DE RECURSOS LTDA. | E134: 29.608.120/0001-58 | F134: Daycoval Asset | G134: Renda Fixa | H134: Renda Fixa Ativo | I134: 500 | J134: 0.9 | M134: 4 | N134: 2 | Q134: Não | R134: Site (navegador) | S134: 1 | T134: Não | U134: Sim | V134: Não
A135: XP Investimentos | B135: Polo Crédito Corporativo Prev Xp Seg Fic Rf Cp Rl | C135: 52.955.528/0001-18 | D135: POLO CAPITAL GESTÃO DE RECURSOS LTDA | E135: 05.451.668/0001-79 | F135: XP Investimentos | G135: Renda Fixa | H135: Crédito High Grade | I135: 100 | J135: 0.9 | M135: 7 | N135: 2 | Q135: Não | R135: Site (navegador) | S135: 1 | T135: Não | U135: Sim | V135: Não
A136: XP Investimentos | B136: Porto CP Prev XP Seg FICFIM RL | C136: 45.089.750/0001-10 | D136: XP VIDA E PREVIDÊNCIA S.A. | E136: 29.408.732/0001-05 | F136: XP Serviços Financeiros DTVM LTDA | G136: Multimercado | H136: Crédito High Grade | I136: 100 | J136: 0.9 | M136: 8 | N136: 1 | Q136: Sim | R136: Site (navegador) | S136: 1 | T136: Não | U136: Sim | V136: Não
... A146: XP Investimentos | B146: Root Capital Crédito HG PREV XP SEG FIC FIRF CP | C146: 48.940.997/0001-96 | D146: ROOT CAPITAL - GESTÃO DE RECURSOS LTDA | E146: 11.397.040/0001-35 | F146: BNY Mellon DTVM | G146: Renda Fixa | H146: Crédito High Yield | I146: 100 | J146: 0.9 | M146: 7 | N146: 2 | Q146: Sim | R146: Site (navegador) | S146: 1 | T146: Não | U146: Sim | V146: Não
A147: XP Investimentos | B147: Root Capital Hg Prev Plus Xp Seg Fic De Fif Multi Cp Rl | C147: 62.669.471/0001-44 | D147: ROOT CAPITAL - GESTÃO DE RECURSOS LTDA | E147: 11.397.040/0001-35 | F147: BNY Mellon DTVM | G147: Renda Fixa | I147: 100 | J147: 1.1 | M147: 23 | N147: 1 | Q147: Não | R147: Site (navegador) | S147: 1 | T147: Não | U147: Sim | V147: Não
A148: XP Investimentos | B148: Root Hy Xp Seg Prev Ficfirf Cp | C148: 52.955.482/0001-37 | D148: ROOT CAPITAL - GESTÃO DE RECURSOS LTDA | E148: 11.397.040/0001-35 | F148: XP Investimentos | G148: Renda Fixa | H148: Crédito High Yield | I148: 100 | J148: 1.45 | M148: 131 | N148: 1 | Q148: Não | R148: Site (navegador) | S148: 1 | T148: Não | U148: Sim | V148: Não
A149: XP Investimentos | B149: SPX Lancer Plus XP Seg Prev FIC FIM | C149: 41.802.098/0001-88 | D149: XP VIDA E PREVIDÊNCIA S.A. | E149: 29.408.732/0001-05 | F149: XP Investimentos | G149: Multimercado | H149: Macro Alta Vol | I149: 100 | J149: 2 | M149: 2 | N149: 3 | Q149: Não | R149: Site (navegador) | S149: 1 | T149: Não | U149: Sim | V149: Não
A150: XP Investimentos | B150: Safari Prev 100 XP Seg FIM FIE | C150: 33.378.232/0001-37 | D150: SAFARI CAPITAL GESTÃO DE RECURSOS LTDA. | E150: 21.850.329/0001-11 | F150: BNY Mellon DTVM | G150: Multimercado | H150: Renda Variável Long Biased | I150: 100 | J150: 2 | M150: 33 | N150: 2 | Q150: Sim | R150: Site (navegador) | S150: 1 | T150: Não | U150: Sim | V150: Não
A151: XP Investimentos | B151: Safra Prev Vitesse Plus Advisory FIC RF CP Prev RL | C151: 57.850.204/0001-39 | D151: TURMALINA GESTÃO E ADMINISTRAÇÃO DE RECURSOS S.A. | E151: 43.826.833/0001-19 | F151: SAFRA SERVIÇOS DE ADMINISTRAÇÃO FIDUCIÁRIA | G151: Renda Fixa | H151: Crédito High Grade | I151: 100 | J151: 0.8 | M151: 9 | N151: 1 | Q151: Não | R151: Site (navegador) | S151: 1 | T151: Não | U151: Sim | V151: Não
A152: XP Investimentos | B152: Selection Multimercado XP Seg FIC FIM | C152: 35.386.842/0001-08 | D152: XP ADVISORY GESTAO DE RECURSOS LTDA | E152: 15.289.957/0001-77 | F152: XP Investimentos | G152: Multimercado | H152: Multiestratégia | I152: 100 | J152: 0.8 | M152: 7 | N152: 2 | Q152: Não | R152: Site (navegador) | S152: 1 | T152: Não | U152: Sim | V152: Não
A153: XP Investimentos | B153: Sharp Equity Value 100 XP Seg Prev FIC FIM | C153: 35.957.156/0001-40 | D153: XP VIDA E PREVIDÊNCIA S.A. | E153: 29.408.732/0001-05 | F153: BNY Mellon DTVM | G153: Multimercado | H153: Renda Variável Long Biased | I153: 100 | J153: 2 | M153: 22 | N153: 2 | Q153: Não | R153: Site (navegador) | S153: 1 | T153: Não | U153: Sim | V153: Não
A154: XP Investimentos | B154: Solis Antares XP Seg Prev FIC FIRF CP | C154: 41.866.372/0001-82 | D154: XP VIDA E PREVIDÊNCIA S.A. | E154: 29.408.732/0001-05 | F154: XP Serviços Financeiros DTVM LTDA | G154: Renda Fixa | H154: Crédito High Yield | I154: 100 | J154: 0.9 | M154: 21 | N154: 1 | Q154: Sim | R154: Site (navegador) | S154: 1 | T154: Não | U154: Sim | V154: Não
A155: XP Investimentos | B155: Sparta Inflação Prev Advisory XP Seg FIC FIRF CP | C155: 44.843.813/0001-19 | D155: XP VIDA E PREVIDÊNCIA S.A. | E155: 29.408.732/0001-05 | F155: XP Investimentos | G155: Renda Fixa | H155: Renda Fixa Inflação | I155: 100 | J155: 1.1 | M155: 5 | N155: 1 | Q155: Não | R155: Site (navegador) | S155: 1 | T155: Não | U155: Sim | V155: Não
A156: XP Investimentos | B156: Sparta Prev Advisory Xp Seg Fic Rf Cp Rl | C156: 32.239.012/0001-60 | D156: XP VIDA E PREVIDÊNCIA S.A. | E156: 29.408.732/0001-05 | F156: XPI Administradora - Modal | G156: Renda Fixa | H156: Crédito High Grade | I156: 100 | J156: 0.8 | M156: 5 | N156: 1 | Q156: Não | R156: Site (navegador) | S156: 1 | T156: Não | U156: Sim | V156: Não
A157: XP Investimentos | B157: Spx Lancer Xp Seg Prev I Fic Fim Rl | C157: 31.569.954/0001-43 | D157: XP VIDA E PREVIDÊNCIA S.A. | E157: 29.408.732/0001-05 | F157: XP Investimentos | G157: Multimercado | H157: Macro Alta Vol | I157: 100 | J157: 2 | M157: 2 | N157: 3 | Q157: Não | R157: Site (navegador) | S157: 1 | T157: Não | U157: Sim | V157: Não
A158: XP Investimentos | B158: Spx Long Bias Xp Seguros Prev Fic Fim Rl | C158: 40.526.764/0001-30 | D158: XP VIDA E PREVIDÊNCIA S.A. | E158: 29.408.732/0001-05 | F158: XP Investimentos | G158: Multimercado | H158: Renda Variável Long Biased | I158: 100 | J158: 2 | M158: 30 | N158: 2 | Q158: Sim | R158: Site (navegador) | S158: 1 | T158: Não | U158: Sim | V158: Não
A159: XP Investimentos | B159: Spx Seahawk Plus XP Seg Prev FIC FIM CP | C159: 43.636.185/0001-38 | D159: XP VIDA E PREVIDÊNCIA S.A. | E159: 29.408.732/0001-05 | F159: XP Investimentos | G159: Multimercado | H159: Crédito Híbrido | I159: 100 | J159: 0.8 | M159: 8 | N159: 1 | Q159: Não | R159: Site (navegador) | S159: 1 | T159: Não | U159: Sim | V159: Não
... A163: XP Investimentos | B163: Suno Ações Xp Seg Prev Fic Fim Rl | C163: 44.814.968/0001-27 | D163: XP VIDA E PREVIDÊNCIA S.A. | E163: 29.408.732/0001-05 | F163: XP Investimentos | G163: Multimercado | H163: Renda Variável Long Only | I163: 100 | J163: 2 | M163: 7 | N163: 2 | Q163: Não | R163: Site (navegador) | S163: 1 | T163: Não | U163: Sim | V163: Não
A164: XP Investimentos | B164: Tivio Alt Light XP Seg Prev FI FIM CP RL | C164: 53.991.177/0001-63 | D164: TIVIO CAPITAL DISTRIBUIDORA DE TITULOS E VALORES MOBILIARIOS S.A. | E164: 03.384.738/0001-98 | F164: XP Investimentos | G164: Multimercado | I164: 100 | J164: 1.15 | M164: 50 | N164: 2 | Q164: Sim | R164: Site (navegador) | S164: 1 | T164: Não | U164: Sim | V164: Não
A165: XP Investimentos | B165: Tork Long Only XP Seg Prev FIC FIA FIE | C165: 34.432.014/0001-04 | D165: XP GESTÃO DE RECURSOS LTDA | E165: 07.625.200/0001-89 | F165: BTG Pactual DTVM | G165: Multimercado | H165: Renda Variável Long Biased | I165: 100 | J165: 2 | M165: 30 | N165: 2 | Q165: Sim | R165: Site (navegador) | S165: 1 | T165: Não | U165: Sim | V165: Não
A166: XP Investimentos | B166: Trend B26 Prev XP Seg FIC FIRF RL | C166: 24.714.864/0001-33 | D166: XP VIDA E PREVIDÊNCIA S.A. | E166: 29.408.732/0001-05 | F166: XPI Administradora | G166: Renda Fixa | H166: Renda Fixa Inflação | I166: 100 | J166: 0.3 | M166: 2 | N166: 1 | Q166: Sim | R166: Site (navegador) | S166: 1 | T166: Não | U166: Sim | V166: Não
A167: XP Investimentos | B167: Trend B29 Xp Seguros Prev Firf Rl | C167: 49.228.354/0001-87 | D167: XP ALLOCATION ASSET MANAGEMENT LTDA | E167: 37.918.829/0001-88 | F167: XP Investimentos | G167: Renda Fixa | H167: Renda Fixa Inflação | I167: 100 | J167: 0.3 | M167: 0 | N167: 1 | Q167: Não | R167: Site (navegador) | S167: 1 | T167: Não | U167: Sim | V167: Não
A168: XP Investimentos | B168: Trend B35 Prev XP Seg FIC FIRF RL | C168: 27.077.318/0001-27 | D168: XP ALLOCATION ASSET MANAGEMENT LTDA | E168: 37.918.829/0001-88 | F168: XPI Administradora - Modal | G168: Renda Fixa | H168: Renda Fixa Inflação | I168: 100 | J168: 0.3 | M168: 2 | N168: 1 | Q168: Não | R168: Site (navegador) | S168: 1 | T168: Não | U168: Sim | V168: Não
A169: XP Investimentos | B169: Trend B50 Prev Xp Seg Fic Firf | C169: 47.033.019/0001-06 | D169: XP ALLOCATION ASSET MANAGEMENT LTDA | E169: 37.918.829/0001-88 | F169: XPI Administradora - Modal | G169: Renda Fixa | H169: Renda Fixa Inflação | I169: 100 | J169: 0.3 | M169: 0 | N169: 1 | Q169: Não | R169: Site (navegador) | S169: 1 | T169: Não | U169: Sim | V169: Não
A170: XP Investimentos | B170: Trend B60 XP Seg Prev RF RL | C170: 65.912.212/0001-90 | D170: XP ALLOCATION ASSET MANAGEMENT LTDA | E170: 37.918.829/0001-88 | F170: BNP Paribas | G170: Renda Fixa | H170: Renda Fixa Inflação | I170: 100 | J170: 0.3 | M170: 0 | N170: 1 | Q170: Não | R170: Site (navegador) | S170: 1 | T170: Não | U170: Sim | V170: Não
A171: XP Investimentos | B171: Trend Bolsa Americana 40 Prev XP FIM RL | C171: 41.610.532/0001-28 | D171: XP ALLOCATION ASSET MANAGEMENT LTDA | E171: 37.918.829/0001-88 | F171: XP Investimentos | G171: Multimercado | H171: Internacional Ações Hedgeado | I171: 100 | J171: 0.33 | M171: 0 | N171: 1 | Q171: Não | R171: Site (navegador) | S171: 1 | T171: Não | U171: Sim | V171: Não
A172: XP Investimentos | B172: Trend Ibovespa 100 XP Seg Prev FIC FIA RL | C172: 33.795.343/0001-49 | D172: XP ALLOCATION ASSET MANAGEMENT LTDA | E172: 37.918.829/0001-88 | F172: BNY Mellon DTVM | G172: Ações | H172: Renda Variável Indexado | I172: 100 | J172: 0.4 | M172: 0 | N172: 2 | Q172: Não | R172: Site (navegador) | S172: 1 | T172: Não | U172: Sim | V172: Não
A173: XP Investimentos | B173: Trend Ibovespa 70 XP Seg Prev FIC FIM RL | C173: 33.784.183/0001-32 | D173: XP ALLOCATION ASSET MANAGEMENT LTDA | E173: 37.918.829/0001-88 | F173: BNY Mellon DTVM | G173: Multimercado | H173: Renda Variável Indexado | I173: 100 | J173: 0.35 | M173: 0 | N173: 2 | Q173: Não | R173: Site (navegador) | S173: 1 | T173: Não | U173: Sim | V173: Não
A174: XP Investimentos | B174: Trend Imab5+ & Bolsa Americana Dólar Xp Seg Prev Fim Rl | C174: 52.840.043/0001-89 | D174: XP ALLOCATION ASSET MANAGEMENT LTDA | E174: 37.918.829/0001-88 | F174: XP Investimentos | G174: Multimercado | H174: Multiestratégia | I174: 100 | J174: 0.5 | M174: 0 | N174: 2 | Q174: Não | R174: Site (navegador) | S174: 1 | T174: Não | U174: Sim | V174: Não
A175: XP Investimentos | B175: Trend Inflação Curta XP Seg Prev FICFI RF | C175: 32.065.041/0001-52 | D175: XP ALLOCATION ASSET MANAGEMENT LTDA | E175: 37.918.829/0001-88 | F175: XPI Administradora | G175: Renda Fixa | H175: Renda Fixa Inflação | I175: 100 | J175: 0.4 | M175: 0 | N175: 1 | Q175: Não | R175: Site (navegador) | S175: 1 | T175: Não | U175: Sim | V175: Não
A176: XP Investimentos | B176: Trend Pré-Fixado XP Seg Prev FIC FIRF RL | C176: 33.755.733/0001-95 | D176: XP ALLOCATION ASSET MANAGEMENT LTDA | E176: 37.918.829/0001-88 | F176: XP Investimentos | G176: Renda Fixa | H176: Renda Fixa Pré | I176: 100 | J176: 0.4 | M176: 0 | N176: 1 | Q176: Não | R176: Site (navegador) | S176: 1 | T176: Não | U176: Sim | V176: Não
... A219: XP Investimentos | B219: Xp Termo Xp Seg Prev Ficfim Cp | C219: 47.032.813/0001-27 | D219: XP VIDA E PREVIDÊNCIA S.A. | E219: 29.408.732/0001-05 | F219: XPI Administradora | G219: Multimercado | H219: Crédito Liquidez | I219: 100 | J219: 0.5 | M219: 5 | N219: 1 | Q219: Não | R219: Site (navegador) | S219: 1 | T219: Não | U219: Sim | V219: Não
A220: BTG Pactual | B220: 3R Genus Hedge Prev FIM RL | C220: 51.694.298/0001-18 | D220: 3R GESTORA DE RECURSOS LTDA | E220: 13.641.353/0001-12 | F220: BTG PACTUAL SERVICOS FINANCEIROS S.A. DISTRIBUIDOR | G220: Multimercado | H220: Renda Variável | I220: 1000 | K220: 20 | L220: - | M220: 3 | N220: 4 | P220: Curto Prazo | Q220: Sim | R220: API interna | S220: 1 | T220: Não | U220: Sim | V220: Não
A221: BTG Pactual | B221: A1 High Grade FIE I Prev BP FIC FIRF | C221: 67.124.600/0001-32 | D221: ASSET1 INVESTIMENTOS S/A | E221: 35.185.577/0001-08 | F221: BTG PACTUAL SERVICOS FINANCEIROS S.A. DISTRIBUIDOR | G221: Renda Fixa | H221: Outros | I221: 1000 | J221: 0.85 | M221: 0 | N221: 2 | P221: Longo Prazo | Q221: Não | R221: API interna | S221: 1 | T221: Não | U221: Sim | V221: Não
A222: BTG Pactual | B222: A1 RF Ativa Prev FICFIRF RL | C222: 60.356.190/0001-06 | D222: ASSET1 INVESTIMENTOS S/A | E222: 35.185.577/0001-08 | F222: BTG PACTUAL SERVICOS FINANCEIROS S.A. DISTRIBUIDOR | G222: Renda Fixa | H222: Renda Fixa | I222: 1000 | K222: 20 | L222: - | M222: 0 | N222: 1 | P222: Curto Prazo | Q222: Não | R222: API interna | S222: 1 | T222: Não | U222: Sim | V222: Não
A223: BTG Pactual | B223: ACE Capital Prev Icatu FICFIM RL | C223: 48.212.959/0001-17 | D223: ACE CAPITAL GESTORA DE RECURSOS LTDA. | E223: 33.411.393/0001-85 | F223: INTRAG DISTR DE TITULOS EVALORES MOBILIARIOS LTDA | G223: Multimercado | H223: Multimercado | I223: 1500 | J223: 2 | K223: 20 | L223: CDI | M223: 6 | N223: 7 | P223: Longo Prazo | Q223: Não | R223: API interna | S223: 1 | T223: Não | U223: Sim | V223: Não
A224: BTG Pactual | B224: ARX Denali Prev FIRF Access CrPr RL | C224: 47.564.808/0001-65 | D224: BTG PACTUAL GESTÃO E CONSULTORIA DE INVESTIMENTOS LTDA | E224: 12.695.840/0001-03 | F224: BTG PACTUAL SERVICOS FINANCEIROS S.A. DISTRIBUIDOR | G224: Renda Fixa | H224: Renda Fixa | I224: 1000 | M224: 2 | N224: 4 | P224: Curto Prazo | Q224: Não | R224: API interna | S224: 1 | T224: Não | U224: Sim | V224: Não
A225: BTG Pactual | B225: ARX Income Icatu Prev 100 FICFIA RL | C225: 37.355.672/0001-20 | D225: ARX INVESTIMENTOS LTDA | E225: 04.408.128/0001-40 | F225: BNY MELLON SERVICOS FINANCEIROS DTVM S/A | G225: Ações | H225: Renda Variável | I225: 5000 | J225: 2 | K225: 20 | L225: IBOVESPA | M225: 6 | N225: 8 | P225: Renda Variável | Q225: Não | R225: API interna | S225: 1 | T225: Não | U225: Sim | V225: Não
A226: BTG Pactual | B226: ARX Income Icatu Prev FIM RL | C226: 03.879.361/0001-48 | D226: ARX INVESTIMENTOS LTDA | E226: 04.408.128/0001-40 | F226: BNY MELLON SERVICOS FINANCEIROS DTVM S/A | G226: Multimercado | H226: Renda Variável | I226: 1000 | J226: 1.9 | M226: 1 | N226: 2 | P226: Não Aplicável | Q226: Não | R226: API interna | S226: 1 | T226: Não | U226: Sim | V226: Não
A227: BTG Pactual | B227: ARX K2 Prev FICFIM CrPr RL | C227: 33.165.244/0001-83 | D227: ARX INVESTIMENTOS LTDA | E227: 04.408.128/0001-40 | F227: BTG PACTUAL SERVICOS FINANCEIROS S.A. DISTRIBUIDOR | G227: Multimercado | H227: Renda Fixa | I227: 0 | J227: 1.1 | M227: 5 | N227: 7 | P227: Curto Prazo | Q227: Não | R227: API interna | S227: 1 | T227: Não | U227: Sim | V227: Não
A228: BTG Pactual | B228: ASA Hedge Icatu Prev FICFIM RL | C228: 26.343.792/0001-90 | D228: ASA ASSET MANAGEMENT LTDA. | E228: 19.807.960/0001-96 | F228: S3 CACEIS BRASIL DISTRIBUIDORA DE TITULOS E VALORE | G228: Multimercado | H228: Multimercado | I228: 1000 | J228: 0.95 | M228: 0 | N228: 3 | P228: Longo Prazo | Q228: Não | R228: API interna | S228: 1 | T228: Não | U228: Sim | V228: Não
A229: BTG Pactual | B229: AZ Quest Altro Prev FICFIM FIE Access CrPr RL | C229: 47.640.749/0001-67 | D229: BTG PACTUAL GESTÃO E CONSULTORIA DE INVESTIMENTOS LTDA | E229: 12.695.840/0001-03 | F229: BTG PACTUAL SERVICOS FINANCEIROS S.A. DISTRIBUIDOR | G229: Multimercado | H229: Renda Fixa | I229: 1000 | M229: 20 | N229: 21 | P229: Curto Prazo | Q229: Não | R229: API interna | S229: 1 | T229: Não | U229: Sim | V229: Não
A230: BTG Pactual | B230: AZ Quest Icatu Multi Prev FICFIM RL | C230: 18.534.967/0001-19 | D230: AZ Quest Prev Ltda. | E230: 59.312.965/0001-62 | F230: BNY MELLON SERVICOS FINANCEIROS DTVM S/A | G230: Multimercado | H230: Multimercado | I230: 1500 | J230: 2 | M230: 1 | N230: 3 | P230: Não Aplicável | Q230: Não | R230: API interna | S230: 1 | T230: Não | U230: Sim | V230: Não
A231: BTG Pactual | B231: AZ Quest Inflacao Ativo Prev FIE I FICFIRF RL | C231: 34.442.059/0001-51 | D231: AZ Quest Prev Ltda. | E231: 59.312.965/0001-62 | F231: BNY MELLON SERVICOS FINANCEIROS DTVM S/A | G231: Renda Fixa | H231: Renda Fixa | I231: 1500 | J231: 0.55 | M231: 0 | N231: 1 | P231: Longo Prazo | Q231: Não | R231: API interna | S231: 1 | T231: Não | U231: Sim | V231: Não
A232: BTG Pactual | B232: AZ Quest Prev Icatu Luce FICFIRF CrPr RL | C232: 23.883.385/0001-88 | D232: AZ Quest Prev Ltda. | E232: 59.312.965/0001-62 | F232: BNY MELLON SERVICOS FINANCEIROS DTVM S/A | G232: Renda Fixa | H232: Renda Fixa | I232: 3000 | J232: 0.55 | M232: 1 | N232: 3 | P232: Longo Prazo | Q232: Não | R232: API interna | S232: 1 | T232: Não | U232: Sim | V232: Não
A233: BTG Pactual | B233: Absolute Atenas Prev FIM Access CrPr RL | C233: 47.564.734/0001-67 | D233: BTG PACTUAL GESTÃO E CONSULTORIA DE INVESTIMENTOS LTDA | E233: 12.695.840/0001-03 | F233: BTG PACTUAL SERVICOS FINANCEIROS S.A. DISTRIBUIDOR | G233: Renda Fixa | H233: Renda Fixa | I233: 1000 | J233: 0.98 | M233: 6 | N233: 8 | P233: Curto Prazo | Q233: Não | R233: API interna | S233: 1 | T233: Não | U233: Sim | V233: Não
A234: BTG Pactual | B234: Absolute Delfos Prev FICFIRF Access CrPr RL | C234: 57.370.727/0001-88 | D234: BTG PACTUAL GESTÃO E CONSULTORIA DE INVESTIMENTOS LTDA | E234: 12.695.840/0001-03 | F234: BTG PACTUAL SERVICOS FINANCEIROS S.A. DISTRIBUIDOR | G234: Renda Fixa | H234: Renda Fixa | I234: 1000 | J234: 0.88 | M234: 20 | N234: 22 | P234: Curto Prazo | Q234: Não | R234: API interna | S234: 1 | T234: Não | U234: Sim | V234: Não
A235: BTG Pactual | B235: Absolute Hedge Prev FICFIM Access RL | C235: 61.861.454/0001-41 | D235: BTG PACTUAL GESTÃO E CONSULTORIA DE INVESTIMENTOS LTDA | E235: 12.695.840/0001-03 | F235: BTG PACTUAL SERVICOS FINANCEIROS S.A. DISTRIBUIDOR | G235: Multimercado | H235: Multimercado | I235: 1000 | J235: 2 | K235: 20 | L235: - | M235: 4 | N235: 5 | P235: Curto Prazo | Q235: Não | R235: API interna | S235: 1 | T235: Não | U235: Sim | V235: Não
A236: BTG Pactual | B236: Absolute Icatu I Prev FICFIM RL | C236: 29.242.441/0001-81 | D236: ABSOLUTE GESTAO DE INVESTIMENTOS LTDA | E236: 17.285.755/0001-82 | F236: BNY MELLON SERVICOS FINANCEIROS DTVM S/A | G236: Multimercado | H236: Multimercado | I236: 1500 | J236: 2 | K236: 20 | L236: CDI | M236: 0 | N236: 3 | P236: Longo Prazo | Q236: Não | R236: API interna | S236: 1 | T236: Não | U236: Sim | V236: Não
A237: BTG Pactual | B237: Absolute Pace Prev FICFIA Access RL | C237: 55.498.621/0001-39 | D237: BTG PACTUAL GESTÃO E CONSULTORIA DE INVESTIMENTOS LTDA | E237: 12.695.840/0001-03 | F237: BTG PACTUAL SERVICOS FINANCEIROS S.A. DISTRIBUIDOR | G237: Ações | H237: Renda Variável | I237: 0 | J237: 2 | K237: 20 | L237: - | M237: 22 | N237: 24 | P237: Curto Prazo | Q237: Sim | R237: API interna | S237: 1 | T237: Não | U237: Sim | V237: Não
A238: BTG Pactual | B238: Absolute Vertex Prev FIM Access RL | C238: 43.509.130/0001-67 | D238: BTG PACTUAL GESTÃO E CONSULTORIA DE INVESTIMENTOS LTDA | E238: 12.695.840/0001-03 | F238: BTG PACTUAL SERVICOS FINANCEIROS S.A. DISTRIBUIDOR | G238: Multimercado | H238: Multimercado | I238: 1000 | J238: 2 | K238: 20 | L238: CDI | M238: 21 | N238: 22 | P238: Curto Prazo | Q238: Não | R238: API interna | S238: 1 | T238: Não | U238: Sim | V238: Não
A239: BTG Pactual | B239: Adam BP Prev FICFIM RL | C239: 24.751.504/0001-01 | D239: ADAMCAPITAL GESTÃO DE RECURSOS LTDA. | E239: 17.905.206/0001-63 | F239: INTRAG DISTR DE TITULOS EVALORES MOBILIARIOS LTDA | G239: Multimercado | H239: Multimercado | I239: 1000 | J239: 2 | M239: 0 | N239: 2 | P239: Longo Prazo | Q239: Sim | R239: API interna | S239: 1 | T239: Não | U239: Sim | V239: Não
...

Sheet Vitrine varejo
A1: Plataforma | B1: Fundo | C1: CNPJ | D1: Classe oficial (ANBIMA ou CVM) | E1: Categoria na origem | F1: Gestora | G1: Produto | H1: Taxa adm (%) | I1: Aplicação mínima (R$) | J1: Líquidação resgate (D+) | K1: Situação CVM | L1: Fontes
A2: XP Investimentos | B2: XP Icatu Horizonte Prev FIC FIRF | C2: 18.897.562/0001-45 | D2: Previdência RF Duração Livre Grau de Inv | E2: Renda Fixa Ativo | F2: XP VISTA ASSET MANAGEMENT LTDA. | G2: Própria | H2: 0.8 | I2: 500 | J2: 3 | K2: Em Funcionamento Normal | L2: Site (navegador)
A3: XP Investimentos | B3: XP Icatu Horizonte Macro Prev FIM | C3: 18.927.174/0001-60 | D3: Previdência Multimercado Livre | E3: Macro Baixa Vol | F3: XP GESTÃO DE RECURSOS LTDA | G3: Própria | H3: 2 | I3: 500 | J3: 1 | K3: Em Funcionamento Normal | L3: Site (navegador)
A4: XP Investimentos | B4: Trend B26 Prev XP Seg FIC FIRF RL | C4: 24.714.864/0001-33 | D4: Previdência RF Indexados | E4: Renda Fixa Inflação | F4: XP VIDA E PREVIDÊNCIA S.A. | G4: Própria | H4: 0.3 | I4: 100 | J4: 1 | K4: Em Funcionamento Normal | L4: Site (navegador)
A5: XP Investimentos | B5: Trend B35 Prev XP Seg FIC FIRF RL | C5: 27.077.318/0001-27 | D5: Previdência RF Duração Livre Soberano | E5: Renda Fixa Inflação | F5: XP ALLOCATION ASSET MANAGEMENT LTDA | G5: Própria | H5: 0.3 | I5: 100 | J5: 1 | K5: Em Funcionamento Normal | L5: Site (navegador)
A6: XP Investimentos | B6: Leblon 70 XP Seg Prev FIM | C6: 27.793.095/0001-02 | D6: Previdência Multimercado Livre | E6: Renda Variável Long Only | F6: LEBLON EQUITIES GESTAO DE RECURSOS LTDA | G6: Terceiros | H6: 2 | I6: 100 | J6: 2 | K6: Em Funcionamento Normal | L6: Site (navegador)
A7: XP Investimentos | B7: Verde Am Lb 70 Advisory Xp Seg Prev Fic Fim Rl | C7: 30.830.240/0001-84 | D7: Previdência Multimercado Livre | E7: Renda Variável Long Biased | F7: XP VIDA E PREVIDÊNCIA S.A. | G7: Própria | H7: 2.2 | I7: 100 | J7: 3 | K7: Em Funcionamento Normal | L7: Site (navegador)
A8: XP Investimentos | B8: Kadima Xp Seg Prev Fie Fic Fim Rl | C8: 30.898.110/0001-83 | D8: Previdência Multimercado Livre | E8: Quantitativo | F8: XP VIDA E PREVIDÊNCIA S.A. | G8: Própria | H8: 2 | I8: 100 | J8: 1 | K8: Em Funcionamento Normal | L8: Site (navegador)
A9: XP Investimentos | B9: Xp Corporate Light Cp Xp Seg Fic Rf Rl | C9: 30.910.166/0001-06 | D9: Previdência RF Duração Livre Crédito Liv | E9: Crédito High Grade | F9: XP VISTA ASSET MANAGEMENT LTDA. | G9: Própria | H9: 0.5 | I9: 100 | J9: 1 | K9: Em Funcionamento Normal | L9: Site (navegador)
A10: XP Investimentos | B10: Verde Am Scena Advisory Xp Seg Fic Fim Rl | C10: 30.994.931/0001-13 | D10: Previdência Multimercado Livre | E10: Macro Alta Vol | F10: XP VIDA E PREVIDÊNCIA S.A. | G10: Própria | H10: 2 | I10: 100 | J10: 3 | K10: Em Funcionamento Normal | L10: Site (navegador)
A11: XP Investimentos | B11: Adam Xp Seg Prev I Fic Fim Rl | C11: 30.998.045/0001-68 | D11: Previdência Multimercado Livre | E11: Macro Alta Vol | F11: XP VIDA E PREVIDÊNCIA S.A. | G11: Própria | H11: 2 | I11: 100 | J11: 2 | K11: Em Funcionamento Normal | L11: Site (navegador)
A12: XP Investimentos | B12: RPS Prev Absoluto FIC FIM | C12: 31.340.875/0001-66 | D12: Previdência Multimercado Livre | E12: Long Short Direcional | F12: RPS CAPITAL ADMINISTRADORA DE RECURSOS LTDA | G12: Terceiros | H12: 2 | I12: 500 | J12: 3 | K12: Em Funcionamento Normal | L12: Site (navegador)
A13: XP Investimentos | B13: Spx Lancer Xp Seg Prev I Fic Fim Rl | C13: 31.569.954/0001-43 | D13: Previdência Multimercado Livre | E13: Macro Alta Vol | F13: XP VIDA E PREVIDÊNCIA S.A. | G13: Própria | H13: 2 | I13: 100 | J13: 3 | K13: Em Funcionamento Normal | L13: Site (navegador)
... A47: XP Investimentos | B47: JGP Multimercado Prev Advisory XP Seg FICFI | C47: 34.474.500/0001-87 | D47: Previdência Multimercado Livre | E47: Macro Média Vol | F47: JGP GESTÃO DE RECURSOS LTDA | G47: Terceiros | H47: 2 | I47: 100 | J47: 2 | K47: Em Funcionamento Normal | L47: Site (navegador)
A48: XP Investimentos | B48: Miles Virtus Advisory XP Seg Prev FIC FIA | C48: 34.475.121/0001-01 | E48: Renda Variável Long Only | F48: Miles Capital | G48: Terceiros | H48: 2 | I48: 100 | J48: 2 | L48: Site (navegador)
A49: XP Investimentos | B49: XP Advisory Portfolio Private II Prev FIM CP | C49: 34.475.199/0001-26 | D49: Previdência Multimercado Livre | E49: Multiestratégia | F49: XP ADVISORY GESTAO DE RECURSOS LTDA | G49: Própria | H49: 0.55 | I49: 300000 | J49: 2 | K49: Em Funcionamento Normal | L49: Site (navegador)
A50: XP Investimentos | B50: XP Advisory Portfolio Private III Prev FIM CP | C50: 34.475.378/0001-63 | D50: Previdência Multimercado Livre | E50: Multiestratégia | F50: XP ADVISORY GESTAO DE RECURSOS LTDA | G50: Própria | H50: 0.6 | I50: 300000 | J50: 2 | K50: Em Funcionamento Normal | L50: Site (navegador)
A51: XP Investimentos | B51: Vrb Advisory Prev Fundo De Investimento Multimercado | C51: 34.507.447/0001-73 | D51: Previdência Multimercado Livre | E51: Multiestratégia | F51: XP ADVISORY GESTAO DE RECURSOS LTDA | G51: Própria | H51: 1 | I51: 100 | J51: 3 | K51: Em Funcionamento Normal | L51: Site (navegador)
A52: XP Investimentos | B52: Kinea Apolo Advisory Xp Seg Prev Fic Fim Rl | C52: 35.162.484/0001-50 | D52: Previdência Multimercado Livre | E52: Macro Baixa Vol | F52: XP VIDA E PREVIDÊNCIA S.A. | G52: Própria | H52: 0.8 | I52: 100 | J52: 1 | K52: Em Funcionamento Normal | L52: Site (navegador)
A53: XP Investimentos | B53: Selection Multimercado XP Seg FIC FIM | C53: 35.386.842/0001-08 | D53: Previdência Multimercado Livre | E53: Multiestratégia | F53: XP ADVISORY GESTAO DE RECURSOS LTDA | G53: Própria | H53: 0.8 | I53: 100 | J53: 2 | K53: Em Funcionamento Normal | L53: Site (navegador)
A54: XP Investimentos | B54: XP Seg Superprev FIM | C54: 35.420.569/0001-90 | D54: Previdência Multimercado Livre | E54: Multiestratégia | F54: XP VIDA E PREVIDÊNCIA S.A. | G54: Própria | H54: 0.6 | I54: 100 | J54: 2 | K54: Em Funcionamento Normal | L54: Site (navegador)
A55: XP Investimentos | B55: DNA Energy Prev XP Seg FIM | C55: 35.420.731/0001-70 | D55: Previdência Multimercado Livre | E55: Multiestratégia | F55: XP ADVISORY GESTAO DE RECURSOS LTDA | G55: Própria | H55: 0.8 | I55: 100 | J55: 3 | K55: Em Funcionamento Normal | L55: Site (navegador)
A56: XP Investimentos | B56: Constellation XP Seg 100 Prev FIC FIM | C56: 35.651.477/0001-11 | D56: Previdência Multimercado Livre | E56: Renda Variável Long Only | F56: CONSTELLATION INVESTIMENTOS E PARTICIPAÇÕES LTDA | G56: Terceiros | H56: 2 | I56: 1000 | J56: 2 | K56: Em Funcionamento Normal | L56: Site (navegador)
A57: XP Investimentos | B57: JGP Ações 100 Prev XP Seg FIC FIA | C57: 35.704.530/0001-03 | D57: Previdência Ações Ativo | E57: Renda Variável Long Only | F57: JGP GESTÃO DE RECURSOS LTDA | G57: Terceiros | H57: 2 | I57: 100 | J57: 2 | K57: Em Funcionamento Normal | L57: Site (navegador)
A58: XP Investimentos | B58: Xp Long Biased Advisory Xp Seg Fic Fim | C58: 35.744.196/0001-03 | D58: Previdência Multimercado Livre | E58: Renda Variável Long Biased | F58: XP GESTÃO DE RECURSOS LTDA | G58: Própria | H58: 2 | I58: 100 | J58: 2 | K58: Em Funcionamento Normal | L58: Site (navegador)
A59: XP Investimentos | B59: Alaska Black 70 Advisory XP Seg Prev FIC FIM | C59: 35.939.700/0001-20 | D59: Previdência Multimercado Livre | E59: Renda Variável Long Only | F59: ALASKA INVESTIMENTOS LTDA. | G59: Terceiros | H59: 1.5 | I59: 100 | J59: 2 | K59: Em Funcionamento Normal | L59: Site (navegador)
A60: XP Investimentos | B60: Alaska Black 100 Advisory XP Seg Prev FIC FIM | C60: 35.939.857/0001-56 | D60: Previdência Multimercado Livre | E60: Renda Variável Long Only | F60: ALASKA INVESTIMENTOS LTDA. | G60: Terceiros | H60: 1.5 | I60: 100 | J60: 2 | K60: Em Funcionamento Normal | L60: Site (navegador)
... A75: XP Investimentos | B75: Absolute Endurance XP Seg FICFIA Prev | C75: 37.355.605/0001-05 | D75: Previdência Ações Ativo | E75: Renda Variável Long Only | F75: ABSOLUTE GESTAO DE INVESTIMENTOS LTDA | G75: Terceiros | H75: 2 | I75: 100 | J75: 2 | K75: Em Funcionamento Normal | L75: Site (navegador)
A76: XP Investimentos | B76: Claritas Total Return XP Seg Prev FIE FIC FIM | C76: 37.396.828/0001-10 | E76: Macro Alta Vol | F76: Claritas Investimentos (OLD) | G76: Terceiros | H76: 2 | I76: 100 | J76: 2 | L76: Site (navegador)
A77: XP Investimentos | B77: Ace Capital Prev Iq Xp Seg Fic Fim | C77: 37.541.379/0001-57 | D77: Previdência Multimercado Livre | E77: Macro Média Vol | F77: ACE CAPITAL GESTORA DE RECURSOS LTDA. | G77: Terceiros | H77: 2 | I77: 100 | J77: 1 | K77: Em Funcionamento Normal | L77: Site (navegador)
A78: XP Investimentos | B78: RPS Prev Ações XP Seg FICFI | C78: 37.567.399/0001-05 | D78: Previdência Ações Ativo | E78: Renda Variável Long Only | F78: RPS CAPITAL ADMINISTRADORA DE RECURSOS LTDA | G78: Terceiros | H78: 2 | I78: 100 | J78: 2 | K78: Em Funcionamento Normal | L78: Site (navegador)
A79: XP Investimentos | B79: Dahlia Global 50 Advisory XP Seg Prev FIC FIM | C79: 37.645.515/0001-59 | D79: Previdência Multimercado Livre | E79: Internacional Multimercado Não Hedgeado | F79: DAHLIA CAPITAL GESTÃO DE RECURSOS LTDA. | G79: Terceiros | H79: 1.25 | I79: 100 | J79: 2 | K79: Em Funcionamento Normal | L79: Site (navegador)
A80: XP Investimentos | B80: Kinea Prev Atlas XP Seg FIC FIM | C80: 37.728.799/0001-47 | D80: Previdência Multimercado Livre | E80: Macro Alta Vol | F80: XP VIDA E PREVIDÊNCIA S.A. | G80: Própria | H80: 2 | I80: 100 | J80: 1 | K80: Em Funcionamento Normal | L80: Site (navegador)
A81: XP Investimentos | B81: Truxt Valor XP Seguros Prev FICFIA | C81: 37.893.248/0001-39 | D81: Previdência Ações Ativo | E81: Renda Variável Long Only | F81: TRUXT INVESTIMENTOS LTDA. | G81: Terceiros | H81: 3 | I81: 100 | J81: 2 | K81: Em Funcionamento Normal | L81: Site (navegador)
A82: XP Investimentos | B82: Vista Long Biased Xp Seg Prev 1 Ficfim | C82: 37.900.124/0001-33 | D82: Previdência Multimercado Livre | E82: Renda Variável Long Biased | F82: XP GESTÃO DE RECURSOS LTDA | G82: Própria | H82: 2 | I82: 100 | J82: 2 | K82: Em Funcionamento Normal | L82: Site (navegador)
A83: XP Investimentos | B83: XP Seg Superprev 2 FIM | C83: 37.900.216/0001-13 | D83: Previdência Multimercado Livre | E83: Multiestratégia | F83: XP VIDA E PREVIDÊNCIA S.A. | G83: Própria | H83: 0.6 | I83: 100 | J83: 2 | K83: Em Funcionamento Normal | L83: Site (navegador)
A84: XP Investimentos | B84: Novus Bolsa Macro Global Prev Xp Seg Ficfia | C84: 38.035.023/0001-04 | D84: Previdência Ações Ativo | E84: Renda Variável Long Biased | F84: NOVUS CAPITAL GESTORA DE RECURSOS LTDA. | G84: Terceiros | H84: 2 | I84: 100 | J84: 2 | K84: Em Funcionamento Normal | L84: Site (navegador)
A85: XP Investimentos | B85: Oceana Long Biased Advisory XP Seg Prev FIC FIM | C85: 38.236.291/0001-94 | D85: Previdência Multimercado Livre | E85: Renda Variável Long Biased | F85: OCEANA INVESTIMENTOS ADMINISTRADORA DE CARTEIRA DE VALORES MOBILIÁRIOS LTDA | G85: Terceiros | H85: 2 | I85: 100 | J85: 2 | K85: Em Funcionamento Normal | L85: Site (navegador)
A86: XP Investimentos | B86: Oceana Valor Advisory XP Seg Prev FICFIA | C86: 39.958.567/0001-00 | D86: Previdência Ações Ativo | E86: Renda Variável Long Only | F86: XP VIDA E PREVIDÊNCIA S.A. | G86: Própria | H86: 2 | I86: 100 | J86: 2 | K86: Em Funcionamento Normal | L86: Site (navegador)
A87: XP Investimentos | B87: Hashdex 40 Nasdaq Crypto Index Xp Seg Prev Ficfim Rl | C87: 39.992.897/0001-12 | D87: Previdência Multimercado Livre | E87: Alternativo Líquido | F87: XP VIDA E PREVIDÊNCIA S.A. | G87: Própria | H87: 1.5 | I87: 100 | J87: 2 | K87: Em Funcionamento Normal | L87: Site (navegador)
A88: XP Investimentos | B88: Arx K2 XP Seg Prev Inflação Curta FIC FIM CP | C88: 40.212.715/0001-22 | D88: Previdência Multimercado Livre | E88: Renda Fixa Inflação | F88: XP VIDA E PREVIDÊNCIA S.A. | G88: Própria | H88: 1.1 | I88: 100 | J88: 2 | K88: Em Funcionamento Normal | L88: Site (navegador)
... A105: XP Investimentos | B105: Real Investor 100 Xp Seg Ad Ficfia | C105: 41.035.989/0001-56 | D105: Previdência Ações Ativo | E105: Renda Variável Long Only | F105: XP VIDA E PREVIDÊNCIA S.A. | G105: Própria | H105: 2 | I105: 100 | J105: 2 | K105: Em Funcionamento Normal | L105: Site (navegador)
A106: XP Investimentos | B106: Neo Navitas Prev XP Seg FICFIA | C106: 41.081.187/0001-82 | E106: Renda Variável Long Only | F106: NEO Investimentos | G106: Terceiros | H106: 2 | I106: 100 | J106: 2 | L106: Site (navegador)
A107: XP Investimentos | B107: Trend Bolsa Americana 40 Prev XP FIM RL | C107: 41.610.532/0001-28 | D107: Previdência Multimercado Livre | E107: Internacional Ações Hedgeado | F107: XP ALLOCATION ASSET MANAGEMENT LTDA | G107: Própria | H107: 0.33 | I107: 100 | J107: 1 | K107: Em Funcionamento Normal | L107: Site (navegador)
A108: XP Investimentos | B108: Verde Am Mundi Multimercado Globais Xp Seguros Fic Fim Rl | C108: 41.802.040/0001-34 | D108: Previdência Multimercado Livre | E108: Internacional Ações Não Hedgeado | F108: XP VIDA E PREVIDÊNCIA S.A. | G108: Própria | H108: 2 | I108: 100 | J108: 3 | K108: Em Funcionamento Normal | L108: Site (navegador)
A109: XP Investimentos | B109: SPX Lancer Plus XP Seg Prev FIC FIM | C109: 41.802.098/0001-88 | D109: Previdência Multimercado Livre | E109: Macro Alta Vol | F109: XP VIDA E PREVIDÊNCIA S.A. | G109: Própria | H109: 2 | I109: 100 | J109: 3 | K109: Em Funcionamento Normal | L109: Site (navegador)
A110: XP Investimentos | B110: Encore Long Biased 70 XP Seg Prev FIC FIM | C110: 41.802.178/0001-33 | D110: Previdência Multimercado Livre | E110: Renda Variável Long Biased | F110: XP VIDA E PREVIDÊNCIA S.A. | G110: Própria | H110: 1.5 | I110: 100 | J110: 2 | K110: Em Funcionamento Normal | L110: Site (navegador)
A111: XP Investimentos | B111: Encore Long Biased 100 Xp Seg Prev Ficfim Rl | C111: 41.866.111/0001-62 | D111: Previdência Multimercado Livre | E111: Renda Variável Long Biased | F111: XP VIDA E PREVIDÊNCIA S.A. | G111: Própria | H111: 2 | I111: 100 | J111: 2 | K111: Em Funcionamento Normal | L111: Site (navegador)
A112: XP Investimentos | B112: Vinland Renda Fixa Ativo Xp Seg Prev Ficfi | C112: 41.866.348/0001-43 | D112: Previdência RF Duração Livre Grau de Inv | E112: Renda Fixa Ativo | F112: XP VIDA E PREVIDÊNCIA S.A. | G112: Própria | H112: 0.9 | I112: 100 | J112: 1 | K112: Em Funcionamento Normal | L112: Site (navegador)
A113: XP Investimentos | B113: Solis Antares XP Seg Prev FIC FIRF CP | C113: 41.866.372/0001-82 | D113: Previdência RF Duração Livre Crédito Liv | E113: Crédito High Yield | F113: XP VIDA E PREVIDÊNCIA S.A. | G113: Própria | H113: 0.9 | I113: 100 | J113: 1 | K113: Em Funcionamento Normal | L113: Site (navegador)
A114: XP Investimentos | B114: Legacy Crédito Prev Advisory XP Seg FIC FIRF CP | C114: 42.195.844/0001-85 | D114: Previdência RF Duração Livre Crédito Liv | E114: Crédito Híbrido | F114: LEGACY CAPITAL GESTORA DE RECURSOS LTDA. | G114: Terceiros | H114: 1 | I114: 100 | J114: 1 | K114: Em Funcionamento Normal | L114: Site (navegador)
A115: XP Investimentos | B115: Genoa Capital Cruise Prev XP Seg FIC FIM | C115: 42.535.297/0001-30 | D115: Previdência Multimercado Livre | E115: Macro Alta Vol | F115: GENOA CAPITAL GESTORA DE RECURSOS LTDA | G115: Terceiros | H115: 2 | I115: 100 | J115: 2 | K115: Em Funcionamento Normal | L115: Site (navegador)
A116: XP Investimentos | B116: Vinland Macro Advisory 2 Xp Seg Prev Fic Fim Rl | C116: 42.718.410/0001-12 | D116: Previdência Multimercado Livre | E116: Macro Alta Vol | F116: XP VIDA E PREVIDÊNCIA S.A. | G116: Própria | H116: 2 | I116: 100 | J116: 3 | K116: Em Funcionamento Normal | L116: Site (navegador)
A117: XP Investimentos | B117: Arca Grão XP Seg Prev Advisory FIC FIM | C117: 42.794.534/0001-87 | D117: Previdência Multimercado Livre | E117: Multiestratégia | F117: GRÃO GESTÃO DE RECURSOS LTDA. | G117: Terceiros | H117: 0.59 | I117: 100 | J117: 2 | K117: Em Funcionamento Normal | L117: Site (navegador)
A118: XP Investimentos | B118: Kapitalo Kappa Prev Xp Seg Ficfim Rl | C118: 42.847.502/0001-00 | D118: Previdência Multimercado Livre | E118: Macro Alta Vol | F118: XP VIDA E PREVIDÊNCIA S.A. | G118: Própria | H118: 2 | I118: 100 | J118: 2 | K118: Em Funcionamento Normal | L118: Site (navegador)
... A130: XP Investimentos | B130: Whg Rf Dinâmico Xp Seg Prev Ficfim Cp Rl | C130: 43.860.077/0001-44 | D130: Previdência Multimercado Livre | E130: Macro Baixa Vol | F130: XP VIDA E PREVIDÊNCIA S.A. | G130: Própria | H130: 1 | I130: 100 | J130: 1 | K130: Em Funcionamento Normal | L130: Site (navegador)
A131: XP Investimentos | B131: Lis 70 Xp Seg Prev Ficfim Rl | C131: 43.860.692/0001-50 | E131: Renda Variável Small/Mid Caps | F131: XP Vida e Previdência | G131: Própria | H131: 2 | I131: 100 | J131: 2 | L131: Site (navegador)
A132: XP Investimentos | B132: Reach Total Return Xp Seg Fic Fim | C132: 44.157.016/0001-88 | D132: Previdência Multimercado Livre | E132: Renda Variável Long Biased | F132: XP VIDA E PREVIDÊNCIA S.A. | G132: Própria | H132: 2 | I132: 100 | J132: 2 | K132: Em Funcionamento Normal | L132: Site (navegador)
A133: XP Investimentos | B133: Vinci Crédito Prev Advisory Firf Cp Rl | C133: 44.230.868/0001-53 | D133: Previdência RF Duração Baixa Grau de Inv | E133: Crédito High Grade | F133: VINCI GESTORA DE RECURSOS LTDA | G133: Terceiros | H133: 0.9 | I133: 100 | J133: 1 | K133: Em Funcionamento Normal | L133: Site (navegador)
A134: XP Investimentos | B134: A1 Hedge Prev Xp Seg Prev Ficfim Rl | C134: 44.409.267/0001-02 | D134: Previdência Multimercado Livre | E134: Macro Alta Vol | F134: XP VIDA E PREVIDÊNCIA S.A. | G134: Própria | H134: 2.1 | I134: 100 | J134: 2 | K134: Em Funcionamento Normal | L134: Site (navegador)
A135: XP Investimentos | B135: Guepardo 70 Xp Seg Prev Ficfim | C135: 44.409.327/0001-97 | D135: Previdência Multimercado Livre | E135: Renda Variável Long Only | F135: XP VIDA E PREVIDÊNCIA S.A. | G135: Própria | H135: 1.5 | I135: 100 | J135: 2 | K135: Em Funcionamento Normal | L135: Site (navegador)
A136: XP Investimentos | B136: Ibiuna Credit Xp Seg Prev Ficfim Cp Rl | C136: 44.409.353/0001-15 | D136: Previdência Multimercado Livre | E136: Crédito High Grade | F136: XP VIDA E PREVIDÊNCIA S.A. | G136: Própria | H136: 0.8 | I136: 100 | J136: 1 | K136: Em Funcionamento Normal | L136: Site (navegador)
A137: XP Investimentos | B137: Távola Equity Hedge Prev XP LS FIC FIM RL | C137: 44.409.412/0001-55 | D137: Previdência Multimercado Livre | E137: Long Short Direcional | F137: TÁVOLA CAPITAL GESTÃO DE RECURSOS LTDA. | G137: Terceiros | H137: 1.92 | I137: 100 | J137: 2 | K137: Em Funcionamento Normal | L137: Site (navegador)
A138: XP Investimentos | B138: Ibiuna ST XP Seg Prev FIC FIM CP | C138: 44.409.430/0001-37 | D138: Previdência Multimercado Livre | E138: Macro Alta Vol | F138: XP VIDA E PREVIDÊNCIA S.A. | G138: Própria | H138: 2 | I138: 100 | J138: 1 | K138: Em Funcionamento Normal | L138: Site (navegador)
A139: XP Investimentos | B139: Kad Ima-B Xp Seg Prev Ficfim Rl | C139: 44.434.888/0001-46 | D139: Previdência Multimercado Livre | E139: Renda Fixa Inflação | F139: XP VIDA E PREVIDÊNCIA S.A. | G139: Própria | H139: 0.8 | I139: 100 | J139: 1 | K139: Em Funcionamento Normal | L139: Site (navegador)
A140: XP Investimentos | B140: Vista Macro Xp Seg Prev Ficfim Cp Rl | C140: 44.748.957/0001-96 | D140: Previdência Multimercado Livre | E140: Macro Alta Vol | F140: XP VIDA E PREVIDÊNCIA S.A. | G140: Própria | H140: 2 | I140: 100 | J140: 2 | K140: Em Funcionamento Normal | L140: Site (navegador)
A141: XP Investimentos | B141: Suno Ações Xp Seg Prev Fic Fim Rl | C141: 44.814.968/0001-27 | D141: Previdência Multimercado Livre | E141: Renda Variável Long Only | F141: XP VIDA E PREVIDÊNCIA S.A. | G141: Própria | H141: 2 | I141: 100 | J141: 2 | K141: Em Funcionamento Normal | L141: Site (navegador)
A142: XP Investimentos | B142: Sparta Inflação Prev Advisory XP Seg FIC FIRF CP | C142: 44.843.813/0001-19 | D142: Previdência RF Duração Média Crédito Liv | E142: Renda Fixa Inflação | F142: XP VIDA E PREVIDÊNCIA S.A. | G142: Própria | H142: 1.1 | I142: 100 | J142: 1 | K142: Em Funcionamento Normal | L142: Site (navegador)
A143: XP Investimentos | B143: Porto CP Prev XP Seg FICFIM RL | C143: 45.089.750/0001-10 | D143: Previdência Multimercado Livre | E143: Crédito High Grade | F143: XP VIDA E PREVIDÊNCIA S.A. | G143: Própria | H143: 0.9 | I143: 100 | J143: 1 | K143: Em Funcionamento Normal | L143: Site (navegador)
... A187: XP Investimentos | B187: Jive Soul 45 Xp Seg Prev Fic Multimercado Cp Rl | C187: 53.990.872/0001-00 | D187: Previdência Multimercado Livre | E187: Crédito Privado High Yield | F187: JIVE HIGH YIELD GESTÃO DE RECURSOS LTDA. | G187: Terceiros | H187: 1.5 | I187: 100 | J187: 2 | K187: Em Funcionamento Normal | L187: Site (navegador)
A188: XP Investimentos | B188: Tivio Alt Light XP Seg Prev FI FIM CP RL | C188: 53.991.177/0001-63 | D188: Previdência Multimercado Livre | F188: TIVIO CAPITAL DISTRIBUIDORA DE TITULOS E VALORES MOBILIARIOS S.A. | G188: Terceiros | H188: 1.15 | I188: 100 | J188: 2 | K188: Em Funcionamento Normal | L188: Site (navegador)
A189: XP Investimentos | B189: Tríade Prev Fic Fim Cp Rl | C189: 53.991.216/0001-22 | D189: Previdência Multimercado Livre | E189: Crédito Privado High Grade | F189: PARAMIS BR INVESTIMENTOS LTDA | G189: Terceiros | H189: 1.05 | I189: 100 | J189: 2 | K189: Em Funcionamento Normal | L189: Site (navegador)
A190: XP Investimentos | B190: V8 Speedway Vega LS XP Seg Prev FIC Multi RL | C190: 53.991.515/0001-67 | D190: Previdência Multimercado Livre | E190: Long Short Neutro | F190: V8 CAPITAL GESTÃO DE INVESTIMENTOS LTDA. | G190: Terceiros | H190: 2 | I190: 100 | J190: 2 | K190: Em Funcionamento Normal | L190: Site (navegador)
A191: XP Investimentos | B191: Mapfre Confianza XP Seg FIC FIF RF RL | C191: 56.385.272/0001-01 | D191: Previdência RF Duração Média Grau de Inv | E191: Crédito Liquidez | F191: MAPFRE INVESTIMENTOS LTDA. | G191: Terceiros | H191: 0.45 | I191: 100 | J191: 0 | K191: Em Funcionamento Normal | L191: Site (navegador)
A192: XP Investimentos | B192: Real Investor Xp Seg Prev Fif Multimercado Rl | C192: 57.446.923/0001-99 | D192: Multimercados Livre | E192: Crédito High Grade | F192: REAL INVESTOR ASSET MANAGEMENT LTDA | G192: Terceiros | H192: 1.7 | I192: 100 | J192: 2 | K192: Em Funcionamento Normal | L192: Site (navegador)
A193: XP Investimentos | B193: Safra Prev Vitesse Plus Advisory FIC RF CP Prev RL | C193: 57.850.204/0001-39 | D193: Previdência RF Duração Livre Crédito Liv | E193: Crédito High Grade | F193: TURMALINA GESTÃO E ADMINISTRAÇÃO DE RECURSOS S.A. | G193: Terceiros | H193: 0.8 | I193: 100 | J193: 1 | K193: Em Funcionamento Normal | L193: Site (navegador)
A194: XP Investimentos | B194: Mag Cash Xp Seg Prev Ficfirf Rl | C194: 58.543.779/0001-71 | D194: Previdência RF Duração Livre Crédito Liv | E194: Crédito Liquidez | F194: MONGERAL AEGON INVESTIMENTOS LTDA | G194: Terceiros | H194: 0.8 | I194: 100 | J194: 1 | K194: Em Funcionamento Normal | L194: Site (navegador)
A195: XP Investimentos | B195: Kapitalo Zeta XP Seg Prev FIF CIC Multimercado RL | C195: 58.841.072/0001-41 | D195: Multimercados Macro | E195: Macro Alta Vol | F195: KAPITALO INVESTIMENTOS LTDA. | G195: Terceiros | H195: 2 | I195: 100 | J195: 2 | K195: Em Funcionamento Normal | L195: Site (navegador)
A196: XP Investimentos | B196: Augme Xp Seg Prev Hy Fif Multimercado Cp Rl | C196: 60.749.195/0001-07 | D196: Previdência Multimercado Livre | E196: Crédito High Yield | F196: AUGME CAPITAL GESTÃO DE RECURSOS LTDA. | G196: Terceiros | H196: 1.5 | I196: 100 | J196: 1 | K196: Em Funcionamento Normal | L196: Site (navegador)
A197: XP Investimentos | B197: Novus Crédito Previdência Xp Fif Em Cotas Fim Cp Rl | C197: 60.818.157/0001-50 | D197: Previdência Multimercado Livre | E197: Crédito High Grade | F197: NOVUS CREDITO GESTAO DE RECURSOS LTDA | G197: Terceiros | H197: 0.9 | I197: 100 | J197: 1 | K197: Em Funcionamento Normal | L197: Site (navegador)
A198: XP Investimentos | B198: Sulamérica Crédito Esg Xp Seg Prev Fic Rf Cp Is Rl | C198: 61.038.314/0001-78 | D198: Previdência RF Duração Livre Crédito Liv | E198: Crédito High Grade | F198: Sul América Gestão de Investimentos S.A. | G198: Terceiros | H198: 0.9 | I198: 100 | J198: 1 | K198: Em Funcionamento Normal | L198: Site (navegador)
A199: XP Investimentos | B199: Kinea Prev Mont Blanc Xp Fif Cotas Rf Cp Rl | C199: 61.182.246/0001-16 | D199: Renda Fixa Duração Livre Crédito Livre | E199: Crédito High Grade | F199: KINEA INVESTIMENTOS LTDA. | G199: Terceiros | H199: 1.2 | I199: 100 | J199: 1 | K199: Em Funcionamento Normal | L199: Site (navegador)
A200: XP Investimentos | B200: Absolute Pace Xp Seg Prev Fif Em Ações Rl | C200: 61.201.512/0001-00 | D200: Previdência Ações Ativo | E200: Renda Variável Long Biased | F200: ABSOLUTE GESTAO DE INVESTIMENTOS LTDA | G200: Terceiros | H200: 2 | I200: 100 | J200: 2 | K200: Em Funcionamento Normal | L200: Site (navegador)
... A209: XP Investimentos | B209: JGP Strategy XP Seg Prev Qualificado FIC FIM RL | C209: 62.403.552/0001-06 | D209: Previdência Multimercado Livre | E209: Macro Média Vol | F209: JGP GESTÃO DE RECURSOS LTDA | G209: Terceiros | H209: 2 | I209: 100 | J209: 1 | K209: Em Funcionamento Normal | L209: Site (navegador)
A210: XP Investimentos | B210: Root Capital Hg Prev Plus Xp Seg Fic De Fif Multi Cp Rl | C210: 62.669.471/0001-44 | D210: Previdência RF Duração Livre Grau de Inv | F210: ROOT CAPITAL - GESTÃO DE RECURSOS LTDA | G210: Terceiros | H210: 1.1 | I210: 100 | J210: 1 | K210: Em Funcionamento Normal | L210: Site (navegador)
A211: XP Investimentos | B211: Drys Shelter Prev XP FIRF CP RL | C211: 63.285.329/0001-66 | D211: Previdência RF Duração Baixa Grau de Inv | E211: Crédito Liquidez | F211: DRYS CAPITAL LTDA | G211: Terceiros | H211: 0.8 | I211: 100 | J211: 1 | K211: Em Funcionamento Normal | L211: Site (navegador)
A212: XP Investimentos | B212: A1 High Grade Prev XP Seg FIC FIRF CP RL | C212: 63.573.988/0001-06 | D212: Previdência RF Duração Livre Crédito Liv | E212: Crédito Liquidez | F212: ASSET1 INVESTIMENTOS S/A | G212: Terceiros | H212: 0.85 | I212: 100 | J212: 2 | K212: Em Funcionamento Normal | L212: Site (navegador)
A213: XP Investimentos | B213: Occam Liquidez XP Seg Prev FIC FIRF CP RL | C213: 63.799.359/0001-90 | D213: Previdência RF Duração Livre Crédito Liv | E213: Crédito Liquidez | F213: NOVA OCCAM BRASIL GESTAO DE RECURSOS LTDA. | G213: Terceiros | H213: 0.8 | I213: 100 | J213: 1 | K213: Em Funcionamento Normal | L213: Site (navegador)
A214: XP Investimentos | B214: Genoa Capital Sagres XP Seg Prev FIF CIC Multi RL | C214: 64.195.667/0001-70 | D214: Previdência Multimercado Livre | E214: Quantitativo | F214: GENOA CAPITAL GESTORA DE RECURSOS LTDA | G214: Terceiros | H214: 2 | I214: 100 | J214: 2 | K214: Em Funcionamento Normal | L214: Site (navegador)
A215: XP Investimentos | B215: Ibiuna RF Ativo XP Seg Prev FIE I FIF CI RF RL | C215: 65.536.263/0001-65 | D215: Previdência RF Duração Livre Crédito Liv | E215: Renda Fixa Ativo | F215: IBIUNA PREVIDÊNCIA GESTÃO DE RECURSOS LTDA. | G215: Terceiros | H215: 0.8 | I215: 100 | J215: 1 | K215: Em Funcionamento Normal | L215: Site (navegador)
A216: XP Investimentos | B216: Trend B60 XP Seg Prev RF RL | C216: 65.912.212/0001-90 | D216: Previdência RF Data Alvo | E216: Renda Fixa Inflação | F216: XP ALLOCATION ASSET MANAGEMENT LTDA | G216: Própria | H216: 0.3 | I216: 100 | J216: 1 | K216: Em Funcionamento Normal | L216: Site (navegador)
A217: XP Investimentos | B217: Western Asset Total Credit XP Seg Prev FIF RF CP RL | C217: 67.654.705/0001-01 | D217: Previdência RF Duração Livre Crédito Liv | E217: Crédito Estruturado | F217: Franklin Templeton Brasil Ltda. | G217: Terceiros | H217: 0.75 | I217: 100 | J217: 1 | K217: Em Funcionamento Normal | L217: Site (navegador)
A218: XP Investimentos | B218: Investo Renda Fixa SELIC Global BRL XP Seg Prev FIRF RL | C218: 68.007.229/0001-91 | D218: Renda Fixa Duração Livre Crédito Livre | E218: Crédito Híbrido | F218: INVESTO GESTÃO DE RECURSOS LTDA. | G218: Terceiros | H218: 0.6 | I218: 100 | J218: 1 | K218: Em Funcionamento Normal | L218: Site (navegador)
A219: XP Investimentos | B219: Itaú Dual Advanced XP Seg I FIF CIC Multi CP RL | C219: 68.097.895/0001-68 | D219: Previdência Multimercado Livre | E219: Crédito High Grade | F219: ITAU UNIBANCO ASSET MANAGEMENT LTDA. | G219: Terceiros | H219: 0.7 | I219: 100 | J219: 2 | K219: Em Funcionamento Normal | L219: Site (navegador)
A220: BTG Pactual | B220: ARX Income Icatu Prev FIM RL | C220: 03.879.361/0001-48 | D220: Previdência Multimercado Livre | E220: Renda Variável | F220: ARX INVESTIMENTOS LTDA | G220: Terceiros | H220: 1.9 | I220: 1000 | J220: 2 | K220: Em Funcionamento Normal | L220: API interna
A221: BTG Pactual | B221: Icatu SEG Vanguarda FICFIRF Plus Prev RL | C221: 04.223.291/0001-38 | D221: Previdência RF Duração Média Grau de Inv | E221: Renda Fixa | F221: ICATU VANGUARDA GESTÃO DE RECURSOS LTDA | G221: Terceiros | H221: 0.45 | I221: 3000 | J221: 2 | K221: Em Funcionamento Normal | L221: API interna
A222: BTG Pactual | B222: Icatu Vanguarda FICFIRF Inflacao Longa Prev RL | C222: 04.228.716/0001-00 | D222: Previdência RF Indexados | E222: Renda Fixa | F222: ICATU VANGUARDA GESTÃO DE RECURSOS LTDA | G222: Terceiros | H222: 1.5 | I222: 1000 | J222: 1 | K222: Em Funcionamento Normal | L222: API interna
... A249: BTG Pactual | B249: Icatu SEG Global Equity Income 10 FIM Prev RL | C249: 28.557.951/0001-85 | D249: Previdência Multimercado Livre | E249: Multimercado | F249: ICATU VANGUARDA GESTÃO DE RECURSOS LTDA | G249: Terceiros | H249: 0.88 | I249: 1000 | J249: 3 | K249: Em Funcionamento Normal | L249: API interna
A250: BTG Pactual | B250: Butia Excellence Prev FICFIM RL | C250: 28.819.628/0001-32 | D250: Previdência Multimercado Livre | E250: Alocação | F250: BUTIÁ GESTÃO DE INVESTIMENTOS LTDA. | G250: Terceiros | I250: 0 | J250: 3 | K250: Em Funcionamento Normal | L250: API interna
A251: BTG Pactual | B251: BTG Pactual Tesouro Selic Prev FIRF Ref. DI RL | C251: 29.078.039/0001-03 | D251: Previdência RF Duração Livre Soberano | E251: Renda Fixa | F251: BTG PACTUAL ASSET MANAGEMENT S/A DTVM | G251: Própria | H251: 0 | I251: 1000 | J251: 1 | K251: Em Funcionamento Normal | L251: API interna
...

Sheet Restritos (auxiliar)
A1: Plataforma | B1: Fundo | C1: CNPJ | D1: Motivo | E1: Classe oficial | F1: Gestora | G1: Na vitrine | H1: Fontes
A2: XP Investimentos | B2: Alaska Black 100 Advisory XP Seg Prev FIC FIM sem pfee | C2: 32.757.743/0001-05 | D2: público-alvo profissional (segundo a casa) | E2: Previdência Multimercado Livre | F2: ALASKA INVESTIMENTOS LTDA. | G2: Sim | H2: Site (navegador)
A3: XP Investimentos | B3: Alaska Black 70 Advisory XP Seg Prev FIC FIM sem pfee | C3: 32.761.323/0001-94 | D3: público-alvo profissional (segundo a casa) | E3: Previdência Multimercado Livre | F3: ALASKA INVESTIMENTOS LTDA. | G3: Sim | H3: Site (navegador)
A4: XP Investimentos | B4: Legacy Capital Prev Advisory XP Seg FIC FIM | C4: 34.287.126/0001-00 | D4: público-alvo profissional (segundo a casa) | E4: Previdência Multimercado Livre | F4: LEGACY CAPITAL GESTORA DE RECURSOS LTDA. | G4: Sim | H4: Site (navegador)
A5: XP Investimentos | B5: Velt Advisory XP Seg Prev FIC FIA | C5: 36.352.636/0001-40 | D5: público-alvo profissional (segundo a casa) | E5: Previdência Ações Ativo | F5: VELT PARTNERS INVESTIMENTOS LTDA | G5: Sim | H5: Site (navegador)
A6: XP Investimentos | B6: Xp Long Biased Ii Seg Fic Fim | C6: 34.430.623/0001-16 | D6: público-alvo profissional (segundo a casa) | E6: Previdência Multimercado Livre | F6: XP VIDA E PREVIDÊNCIA S.A. | G6: Sim | H6: Site (navegador)

Sheet Movimentos
A1: Plataforma | B1: Movimento | C1: Fundo | D1: CNPJ | E1: Na vitrine | F1: Detalhe
A2: BTG Pactual | B2: alteração | C2: Finacap BP Prev 70 FIF MM | D2: 67.671.091/0001-68 | F2: closed_for_investment: True -> False

Sheet XP Investimentos
A1: Plataforma | B1: Fundo | C1: CNPJ | D1: Gestora | E1: CNPJ da gestora | F1: Administrador | G1: Classe | H1: Categoria na origem | I1: Aplicação mínima (R$) | J1: Taxa adm (%) | K1: Taxa perf (%) | L1: Benchmark | M1: Cotização resgate (D+) | N1: Líquidação resgate (D+) | O1: Carência (dias) | P1: Tributação | Q1: Fechado p/ captação | R1: Fontes | S1: Nº de fontes | T1: Open Finance | U1: Prateleira (site) | V1: Área logada | W1: Link
A2: XP Investimentos | B2: A1 Hedge Prev Xp Seg Prev Ficfim Rl | C2: 44.409.267/0001-02 | D2: XP VIDA E PREVIDÊNCIA S.A. | E2: 29.408.732/0001-05 | F2: XP Investimentos | G2: Multimercado | H2: Macro Alta Vol | I2: 100 | J2: 2.1 | M2: 22 | N2: 2 | Q2: Não | R2: Site (navegador) | S2: 1 | T2: Não | U2: Sim | V2: Não
A3: XP Investimentos | B3: A1 High Grade Prev XP Seg FIC FIRF CP RL | C3: 63.573.988/0001-06 | D3: ASSET1 INVESTIMENTOS S/A | E3: 35.185.577/0001-08 | F3: Intrag DTVM | G3: Renda Fixa | H3: Crédito Liquidez | I3: 100 | J3: 0.85 | M3: 0 | N3: 2 | Q3: Não | R3: Site (navegador) | S3: 1 | T3: Não | U3: Sim | V3: Não
A4: XP Investimentos | B4: A1 Renda Fixa Ativa Xp Seguros Firf | C4: 52.955.280/0001-95 | D4: ASSET1 INVESTIMENTOS S/A | E4: 35.185.577/0001-08 | F4: XP Investimentos | G4: Multimercado | H4: Renda Fixa Ativo | I4: 100 | J4: 0.9 | M4: 0 | N4: 1 | Q4: Não | R4: Site (navegador) | S4: 1 | T4: Não | U4: Sim | V4: Não
A5: XP Investimentos | B5: ARX Income 100 XP Seg Prev FIC FIA | C5: 34.461.754/0001-60 | D5: XP VIDA E PREVIDÊNCIA S.A. | E5: 29.408.732/0001-05 | F5: BNY Mellon DTVM | G5: Ações | H5: Renda Variável Dividendos | I5: 100 | J5: 2 | M5: 6 | N5: 2 | Q5: Não | R5: Site (navegador) | S5: 1 | T5: Não | U5: Sim | V5: Não
A6: XP Investimentos | B6: AZ Quest Inflação Ativo Prev FIE FIRF | C6: 34.442.059/0001-51 | D6: AZ Quest Prev Ltda. | E6: 59.312.965/0001-62 | F6: BNY Mellon DTVM | G6: Renda Fixa | H6: Renda Fixa Inflação | I6: 500 | J6: 1.1 | M6: 0 | N6: 1 | Q6: Sim | R6: Site (navegador) | S6: 1 | T6: Não | U6: Sim | V6: Não
A7: XP Investimentos | B7: AZ Quest Luce Advisory Prev XP Seg FICFIRF CP | C7: 32.847.001/0001-62 | D7: XP VIDA E PREVIDÊNCIA S.A. | E7: 29.408.732/0001-05 | F7: XPI Administradora - Modal | G7: Renda Fixa | H7: Crédito Liquidez | I7: 100 | J7: 1 | M7: 1 | N7: 2 | Q7: Não | R7: Site (navegador) | S7: 1 | T7: Não | U7: Sim | V7: Não
A8: XP Investimentos | B8: Absolute Atenas Xp Seg Prev Fie I Fic Firf Cp Rl | C8: 62.213.987/0001-80 | D8: ABSOLUTE CRÉDITO GESTÃO DE INVESTIMENTOS LTDA. | E8: 47.243.769/0001-02 | F8: BTG Pactual DTVM | G8: Renda Fixa | H8: Crédito Liquidez | I8: 100 | J8: 0.98 | M8: 6 | N8: 2 | Q8: Não | R8: Site (navegador) | S8: 1 | T8: Não | U8: Sim | V8: Não
A9: XP Investimentos | B9: Absolute Delfos Xp Seg Prev Fie I Fic Rf Cp Rl | C9: 61.904.092/0001-29 | D9: ABSOLUTE CRÉDITO GESTÃO DE INVESTIMENTOS LTDA. | E9: 47.243.769/0001-02 | F9: Intrag DTVM | G9: Renda Fixa | H9: Crédito High Grade | I9: 100 | J9: 0.88 | M9: 20 | N9: 2 | Q9: Não | R9: Site (navegador) | S9: 1 | T9: Não | U9: Sim | V9: Não
A10: XP Investimentos | B10: Absolute Endurance XP Seg FICFIA Prev | C10: 37.355.605/0001-05 | D10: ABSOLUTE GESTAO DE INVESTIMENTOS LTDA | E10: 17.285.755/0001-82 | F10: BNY Mellon DTVM | G10: Ações | H10: Renda Variável Long Only | I10: 100 | J10: 2 | M10: 21 | N10: 2 | Q10: Não | R10: Site (navegador) | S10: 1 | T10: Não | U10: Sim | V10: Não
A11: XP Investimentos | B11: Absolute Pace Xp Seg Prev Fif Em Ações Rl | C11: 61.201.512/0001-00 | D11: ABSOLUTE GESTAO DE INVESTIMENTOS LTDA | E11: 17.285.755/0001-82 | F11: BTG Pactual DTVM | G11: Ações | H11: Renda Variável Long Biased | I11: 100 | J11: 2 | M11: 22 | N11: 2 | Q11: Sim | R11: Site (navegador) | S11: 1 | T11: Não | U11: Sim | V11: Não
A12: XP Investimentos | B12: Absolute Vertex XP Seg Prev FIC FIM | C12: 40.882.496/0001-99 | D12: XP VIDA E PREVIDÊNCIA S.A. | E12: 29.408.732/0001-05 | F12: XPI Administradora - Modal | G12: Multimercado | H12: Macro Alta Vol | I12: 100 | J12: 2 | M12: 21 | N12: 1 | Q12: Não | R12: Site (navegador) | S12: 1 | T12: Não | U12: Sim | V12: Não
A13: XP Investimentos | B13: Ace Capital Prev Iq Xp Seg Fic Fim | C13: 37.541.379/0001-57 | D13: ACE CAPITAL GESTORA DE RECURSOS LTDA. | E13: 33.411.393/0001-85 | F13: Intrag DTVM | G13: Multimercado | H13: Macro Média Vol | I13: 100 | J13: 2 | M13: 6 | N13: 1 | Q13: Não | R13: Site (navegador) | S13: 1 | T13: Não | U13: Sim | V13: Não
... A39: XP Investimentos | B39: Capitânia Reit Prev Adv XP Seg FIE I FIC FIM CP | C39: 35.955.948/0001-85 | D39: CAPITANIA PREV S.A. | E39: 41.777.833/0001-40 | F39: BNY Mellon DTVM | G39: Multimercado | H39: Crédito Híbrido | I39: 100 | J39: 1.25 | M39: 59 | N39: 1 | Q39: Não | R39: Site (navegador) | S39: 1 | T39: Não | U39: Sim | V39: Não
A40: XP Investimentos | B40: Claritas Total Return XP Seg Prev FIE FIC FIM | C40: 37.396.828/0001-10 | D40: Claritas Investimentos (OLD) | F40: BNY Mellon DTVM | G40: Multimercado | H40: Macro Alta Vol | I40: 100 | J40: 2 | M40: 22 | N40: 2 | Q40: Sim | R40: Site (navegador) | S40: 1 | T40: Não | U40: Sim | V40: Não
A41: XP Investimentos | B41: Constellation XP Seg 100 Prev FIC FIM | C41: 35.651.477/0001-11 | D41: CONSTELLATION INVESTIMENTOS E PARTICIPAÇÕES LTDA | E41: 06.182.127/0001-55 | F41: XP Investimentos | G41: Multimercado | H41: Renda Variável Long Only | I41: 1000 | J41: 2 | M41: 40 | N41: 2 | Q41: Não | R41: Site (navegador) | S41: 1 | T41: Não | U41: Sim | V41: Não
A42: XP Investimentos | B42: DNA Energy Prev XP Seg FIM | C42: 35.420.731/0001-70 | D42: XP ADVISORY GESTAO DE RECURSOS LTDA | E42: 15.289.957/0001-77 | F42: XP Investimentos | G42: Multimercado | H42: Multiestratégia | I42: 100 | J42: 0.8 | M42: 6 | N42: 3 | Q42: Não | R42: Site (navegador) | S42: 1 | T42: Não | U42: Sim | V42: Não
A43: XP Investimentos | B43: Dahlia 100 Advisory XP Seg Prev FIC FIM | C43: 36.327.214/0001-14 | D43: DAHLIA CAPITAL GESTÃO DE RECURSOS LTDA. | E43: 09.551.766/0001-39 | F43: BNY Mellon DTVM | G43: Multimercado | H43: Renda Variável Long Only | I43: 100 | J43: 2 | M43: 10 | N43: 2 | Q43: Não | R43: Site (navegador) | S43: 1 | T43: Não | U43: Sim | V43: Não
A44: XP Investimentos | B44: Dahlia 70 Advisory Xp Seg Ii Prev Fic Fim | C44: 43.761.805/0001-60 | D44: XP VIDA E PREVIDÊNCIA S.A. | E44: 29.408.732/0001-05 | F44: XPI Administradora - Modal | G44: Multimercado | H44: Renda Variável Long Only | I44: 100 | J44: 1.5 | M44: 7 | N44: 2 | Q44: Não | R44: Site (navegador) | S44: 1 | T44: Não | U44: Sim | V44: Não
A45: XP Investimentos | B45: Dahlia Global 50 Advisory XP Seg Prev FIC FIM | C45: 37.645.515/0001-59 | D45: DAHLIA CAPITAL GESTÃO DE RECURSOS LTDA. | E45: 09.551.766/0001-39 | F45: BNY Mellon DTVM | G45: Multimercado | H45: Internacional Multimercado Não Hedgeado | I45: 100 | J45: 1.25 | M45: 7 | N45: 2 | Q45: Não | R45: Site (navegador) | S45: 1 | T45: Não | U45: Sim | V45: Não
A46: XP Investimentos | B46: Daycoval Classic Xp Seg Prev Fif Rf Cp Rl | C46: 61.941.773/0001-67 | D46: DAYCOVAL ASSET MANAGEMENT ADMINISTRACAO DE RECURSOS LTDA | E46: 72.027.832/0001-02 | F46: Banco Daycoval | G46: Renda Fixa | H46: Crédito Liquidez | I46: 100 | J46: 0.82 | M46: 0 | N46: 1 | Q46: Não | R46: Site (navegador) | S46: 1 | T46: Não | U46: Sim | V46: Não
A47: XP Investimentos | B47: Drys Shelter Prev XP FIRF CP RL | C47: 63.285.329/0001-66 | D47: DRYS CAPITAL LTDA | E47: 08.204.817/0001-93 | F47: BNY Mellon DTVM | G47: Renda Fixa | H47: Crédito Liquidez | I47: 100 | J47: 0.8 | M47: 5 | N47: 1 | Q47: Não | R47: Site (navegador) | S47: 1 | T47: Não | U47: Sim | V47: Não
A48: XP Investimentos | B48: Encore Long Biased 100 Xp Seg Prev Ficfim Rl | C48: 41.866.111/0001-62 | D48: XP VIDA E PREVIDÊNCIA S.A. | E48: 29.408.732/0001-05 | F48: XPI Administradora - Modal | G48: Multimercado | H48: Renda Variável Long Biased | I48: 100 | J48: 2 | M48: 20 | N48: 2 | Q48: Não | R48: Site (navegador) | S48: 1 | T48: Não | U48: Sim | V48: Não
A49: XP Investimentos | B49: Encore Long Biased 70 XP Seg Prev FIC FIM | C49: 41.802.178/0001-33 | D49: XP VIDA E PREVIDÊNCIA S.A. | E49: 29.408.732/0001-05 | F49: XPI Administradora - Modal | G49: Multimercado | H49: Renda Variável Long Biased | I49: 100 | J49: 1.5 | M49: 7 | N49: 2 | Q49: Não | R49: Site (navegador) | S49: 1 | T49: Não | U49: Sim | V49: Não
A50: XP Investimentos | B50: Forpus 100 XP Seg Prev FICFIA | C50: 40.212.923/0001-21 | D50: FORPUS CAPITAL GESTÃO DE RECURSOS LTDA. | E50: 21.018.289/0001-46 | F50: BNY Mellon DTVM | G50: Ações | H50: Renda Variável Long Only | I50: 100 | J50: 2 | M50: 8 | N50: 2 | Q50: Não | R50: Site (navegador) | S50: 1 | T50: Não | U50: Sim | V50: Não
A51: XP Investimentos | B51: Forpus 70 XP Seg Prev FIM | C51: 42.870.699/0001-90 | D51: FORPUS CAPITAL GESTÃO DE RECURSOS LTDA. | E51: 21.018.289/0001-46 | F51: BNY Mellon DTVM | G51: Multimercado | H51: Renda Variável Long Only | I51: 100 | J51: 2 | M51: 7 | N51: 2 | Q51: Não | R51: Site (navegador) | S51: 1 | T51: Não | U51: Sim | V51: Não
A52: XP Investimentos | B52: Franklin Valor e Liquidez 70 XP Seg FIM | C52: 32.319.047/0001-09 | D52: Franklin Templeton Brasil Ltda. | E52: 07.437.241/0001-41 | F52: BNY Mellon DTVM | G52: Multimercado | H52: Renda Variável Long Only | I52: 100 | J52: 2 | M52: 2 | N52: 2 | Q52: Não | R52: Site (navegador) | S52: 1 | T52: Não | U52: Sim | V52: Não
... A113: XP Investimentos | B113: Lis 100 Prev Xp Seguros Ficfim Rl | C113: 47.033.051/0001-83 | D113: XP VIDA E PREVIDÊNCIA S.A. | E113: 29.408.732/0001-05 | F113: XP Investimentos | G113: Multimercado | H113: Renda Variável Small/Mid Caps | I113: 100 | J113: 2 | M113: 30 | N113: 2 | Q113: Não | R113: Site (navegador) | S113: 1 | T113: Não | U113: Sim | V113: Não
A114: XP Investimentos | B114: Lis 70 Xp Seg Prev Ficfim Rl | C114: 43.860.692/0001-50 | D114: XP Vida e Previdência | F114: XP Investimentos | G114: Multimercado | H114: Renda Variável Small/Mid Caps | I114: 100 | J114: 2 | M114: 7 | N114: 2 | Q114: Sim | R114: Site (navegador) | S114: 1 | T114: Não | U114: Sim | V114: Não
A115: XP Investimentos | B115: M Global 40 Xp Seg Prev Fic Fim Rl | C115: 40.682.081/0001-71 | D115: XP ALLOCATION ASSET MANAGEMENT LTDA | E115: 37.918.829/0001-88 | F115: XP Investimentos | G115: Multimercado | H115: Internacional Ações Não Hedgeado | I115: 100 | J115: 0.94 | M115: 3 | N115: 3 | Q115: Não | R115: Site (navegador) | S115: 1 | T115: Não | U115: Sim | V115: Não
A116: XP Investimentos | B116: M8 Capital XP Seg Previdência FIC FIRF CP RL | C116: 61.539.506/0001-68 | D116: M8 PARTNERS GESTORA DE RECURSOS LTDA. | E116: 18.038.439/0001-79 | F116: BTG Pactual DTVM | G116: Renda Fixa | H116: Crédito High Yield | I116: 100 | J116: 1 | M116: 7 | N116: 2 | Q116: Não | R116: Site (navegador) | S116: 1 | T116: Não | U116: Sim | V116: Não
A117: XP Investimentos | B117: MAG Prev XP Seg Advisory FIRF CP | C117: 32.385.140/0001-11 | D117: MONGERAL AEGON INVESTIMENTOS LTDA | E117: 16.500.294/0001-50 | F117: BNY Mellon DTVM | G117: Renda Fixa | H117: Crédito High Grade | I117: 100 | J117: 0.95 | M117: 1 | N117: 1 | Q117: Não | R117: Site (navegador) | S117: 1 | T117: Não | U117: Sim | V117: Não
A118: XP Investimentos | B118: Mag Cash Xp Seg Prev Ficfirf Rl | C118: 58.543.779/0001-71 | D118: MONGERAL AEGON INVESTIMENTOS LTDA | E118: 16.500.294/0001-50 | F118: BNY Mellon DTVM | G118: Renda Fixa | H118: Crédito Liquidez | I118: 100 | J118: 0.8 | M118: 0 | N118: 1 | Q118: Sim | R118: Site (navegador) | S118: 1 | T118: Não | U118: Sim | V118: Não
A119: XP Investimentos | B119: Mag Prev Rf Fic Fim | C119: 45.645.112/0001-38 | D119: XP VIDA E PREVIDÊNCIA S.A. | E119: 29.408.732/0001-05 | F119: XPI Administradora - Modal | G119: Multimercado | H119: Renda Fixa Ativo | I119: 100 | J119: 0.7 | M119: 0 | N119: 1 | Q119: Não | R119: Site (navegador) | S119: 1 | T119: Não | U119: Sim | V119: Não
A120: XP Investimentos | B120: Mantaro LB Prev Advisory XP Seg FIC FIM | C120: 36.327.253/0001-11 | D120: MANTARO CAPITAL LTDA | E120: 43.353.050/0001-65 | F120: BTG Pactual DTVM | G120: Multimercado | H120: Renda Variável Long Biased | I120: 100 | J120: 2 | M120: 15 | N120: 2 | Q120: Não | R120: Site (navegador) | S120: 1 | T120: Não | U120: Sim | V120: Não
A121: XP Investimentos | B121: Mapfre Confianza XP Seg FIC FIF RF RL | C121: 56.385.272/0001-01 | D121: MAPFRE INVESTIMENTOS LTDA. | E121: 04.160.039/0001-27 | F121: BNY Mellon DTVM | G121: Renda Fixa | H121: Crédito Liquidez | I121: 100 | J121: 0.45 | M121: 0 | N121: 0 | Q121: Não | R121: Site (navegador) | S121: 1 | T121: Não | U121: Sim | V121: Não
A122: XP Investimentos | B122: Miles Virtus Advisory XP Seg Prev FIC FIA | C122: 34.475.121/0001-01 | D122: Miles Capital | F122: BNY Mellon DTVM | G122: Ações | H122: Renda Variável Long Only | I122: 100 | J122: 2 | M122: 2 | N122: 2 | Q122: Sim | R122: Site (navegador) | S122: 1 | T122: Não | U122: Sim | V122: Não
A123: XP Investimentos | B123: Moat Prev XP Seg FICFIA | C123: 37.037.432/0001-87 | D123: MOAT CAPITAL GESTÃO DE RECURSOS LTDA | E123: 18.730.786/0001-68 | F123: Intrag DTVM | G123: Ações | H123: Renda Variável Long Only | I123: 100 | J123: 2 | M123: 15 | N123: 2 | Q123: Não | R123: Site (navegador) | S123: 1 | T123: Não | U123: Sim | V123: Não
A124: XP Investimentos | B124: Neo Navitas Prev XP Seg FICFIA | C124: 41.081.187/0001-82 | D124: NEO Investimentos | F124: Intrag DTVM | G124: Ações | H124: Renda Variável Long Only | I124: 100 | J124: 2 | M124: 22 | N124: 2 | Q124: Sim | R124: Site (navegador) | S124: 1 | T124: Não | U124: Sim | V124: Não
A125: XP Investimentos | B125: Novus Bolsa Macro Global Prev Xp Seg Ficfia | C125: 38.035.023/0001-04 | D125: NOVUS CAPITAL GESTORA DE RECURSOS LTDA. | E125: 15.388.425/0001-97 | F125: Intrag DTVM | G125: Ações | H125: Renda Variável Long Biased | I125: 100 | J125: 2 | M125: 21 | N125: 2 | Q125: Sim | R125: Site (navegador) | S125: 1 | T125: Não | U125: Sim | V125: Não
A126: XP Investimentos | B126: Novus Crédito Previdência Xp Fif Em Cotas Fim Cp Rl | C126: 60.818.157/0001-50 | D126: NOVUS CREDITO GESTAO DE RECURSOS LTDA | E126: 42.524.344/0001-40 | F126: BTG Pactual DTVM | G126: Multimercado | H126: Crédito High Grade | I126: 100 | J126: 0.9 | M126: 22 | N126: 1 | Q126: Sim | R126: Site (navegador) | S126: 1 | T126: Não | U126: Sim | V126: Não
A127: XP Investimentos | B127: Occam Liquidez Prev Xp Seg Fic Fim | C127: 40.780.979/0001-82 | D127: XP VIDA E PREVIDÊNCIA S.A. | E127: 29.408.732/0001-05 | F127: XPI Administradora | G127: Multimercado | H127: Macro Baixa Vol | I127: 100 | J127: 1.15 | M127: 0 | N127: 1 | Q127: Não | R127: Site (navegador) | S127: 1 | T127: Não | U127: Sim | V127: Não
A128: XP Investimentos | B128: Occam Liquidez XP Seg Prev FIC FIRF CP RL | C128: 63.799.359/0001-90 | D128: NOVA OCCAM BRASIL GESTAO DE RECURSOS LTDA. | E128: 43.228.545/0001-62 | F128: BNY Mellon DTVM | G128: Renda Fixa | H128: Crédito Liquidez | I128: 100 | J128: 0.8 | M128: 6 | N128: 1 | Q128: Não | R128: Site (navegador) | S128: 1 | T128: Não | U128: Sim | V128: Não
A129: XP Investimentos | B129: Occam Xp Seg Prev Fic Fim Rl | C129: 32.312.361/0001-60 | D129: XP VIDA E PREVIDÊNCIA S.A. | E129: 29.408.732/0001-05 | F129: XPI Administradora - Modal | G129: Multimercado | H129: Long Short Direcional | I129: 100 | J129: 2 | M129: 1 | N129: 2 | Q129: Não | R129: Site (navegador) | S129: 1 | T129: Não | U129: Sim | V129: Não
A130: XP Investimentos | B130: Oceana Long Biased Advisory XP Seg Prev FIC FIM | C130: 38.236.291/0001-94 | D130: OCEANA INVESTIMENTOS ADMINISTRADORA DE CARTEIRA DE VALORES MOBILIÁRIOS LTDA | E130: 09.326.542/0001-23 | F130: BNY Mellon DTVM | G130: Multimercado | H130: Renda Variável Long Biased | I130: 100 | J130: 2 | M130: 21 | N130: 2 | Q130: Não | R130: Site (navegador) | S130: 1 | T130: Não | U130: Sim | V130: Não
A131: XP Investimentos | B131: Oceana Valor Advisory XP Seg Prev FICFIA | C131: 39.958.567/0001-00 | D131: XP VIDA E PREVIDÊNCIA S.A. | E131: 29.408.732/0001-05 | F131: BNY Mellon DTVM | G131: Ações | H131: Renda Variável Long Only | I131: 100 | J131: 2 | M131: 21 | N131: 2 | Q131: Não | R131: Site (navegador) | S131: 1 | T131: Não | U131: Sim | V131: Não
A132: XP Investimentos | B132: Pacifico Macro Prev Advisory Xp Seg Fic Fim | C132: 33.755.685/0001-35 | D132: BTG PACTUAL ASSET MANAGEMENT S/A DTVM | E132: 29.650.082/0001-00 | F132: BTG Pactual DTVM | G132: Multimercado | H132: Macro Alta Vol | I132: 100 | J132: 2 | M132: 1 | N132: 2 | Q132: Sim | R132: Site (navegador) | S132: 1 | T132: Não | U132: Sim | V132: Não
A133: XP Investimentos | B133: Patria Previdenciário XP Seg FIC MM CP RL | C133: 53.990.084/0001-14 | D133: PÁTRIA INVESTIMENTOS LTDA. | E133: 12.461.756/0001-17 | F133: XP Investimentos | G133: Multimercado | H133: Crédito High Yield | I133: 100 | J133: 1.59 | M133: 90 | N133: 2 | Q133: Não | R133: Site (navegador) | S133: 1 | T133: Não | U133: Sim | V133: Não
A134: XP Investimentos | B134: Persevera Prospera Xp Seg Prev Firf Cp | C134: 53.856.982/0001-84 | D134: PERSEVERA GESTÃO DE RECURSOS LTDA. | E134: 29.608.120/0001-58 | F134: Daycoval Asset | G134: Renda Fixa | H134: Renda Fixa Ativo | I134: 500 | J134: 0.9 | M134: 4 | N134: 2 | Q134: Não | R134: Site (navegador) | S134: 1 | T134: Não | U134: Sim | V134: Não
A135: XP Investimentos | B135: Polo Crédito Corporativo Prev Xp Seg Fic Rf Cp Rl | C135: 52.955.528/0001-18 | D135: POLO CAPITAL GESTÃO DE RECURSOS LTDA | E135: 05.451.668/0001-79 | F135: XP Investimentos | G135: Renda Fixa | H135: Crédito High Grade | I135: 100 | J135: 0.9 | M135: 7 | N135: 2 | Q135: Não | R135: Site (navegador) | S135: 1 | T135: Não | U135: Sim | V135: Não
A136: XP Investimentos | B136: Porto CP Prev XP Seg FICFIM RL | C136: 45.089.750/0001-10 | D136: XP VIDA E PREVIDÊNCIA S.A. | E136: 29.408.732/0001-05 | F136: XP Serviços Financeiros DTVM LTDA | G136: Multimercado | H136: Crédito High Grade | I136: 100 | J136: 0.9 | M136: 8 | N136: 1 | Q136: Sim | R136: Site (navegador) | S136: 1 | T136: Não | U136: Sim | V136: Não
... A146: XP Investimentos | B146: Root Capital Crédito HG PREV XP SEG FIC FIRF CP | C146: 48.940.997/0001-96 | D146: ROOT CAPITAL - GESTÃO DE RECURSOS LTDA | E146: 11.397.040/0001-35 | F146: BNY Mellon DTVM | G146: Renda Fixa | H146: Crédito High Yield | I146: 100 | J146: 0.9 | M146: 7 | N146: 2 | Q146: Sim | R146: Site (navegador) | S146: 1 | T146: Não | U146: Sim | V146: Não
A147: XP Investimentos | B147: Root Capital Hg Prev Plus Xp Seg Fic De Fif Multi Cp Rl | C147: 62.669.471/0001-44 | D147: ROOT CAPITAL - GESTÃO DE RECURSOS LTDA | E147: 11.397.040/0001-35 | F147: BNY Mellon DTVM | G147: Renda Fixa | I147: 100 | J147: 1.1 | M147: 23 | N147: 1 | Q147: Não | R147: Site (navegador) | S147: 1 | T147: Não | U147: Sim | V147: Não
A148: XP Investimentos | B148: Root Hy Xp Seg Prev Ficfirf Cp | C148: 52.955.482/0001-37 | D148: ROOT CAPITAL - GESTÃO DE RECURSOS LTDA | E148: 11.397.040/0001-35 | F148: XP Investimentos | G148: Renda Fixa | H148: Crédito High Yield | I148: 100 | J148: 1.45 | M148: 131 | N148: 1 | Q148: Não | R148: Site (navegador) | S148: 1 | T148: Não | U148: Sim | V148: Não
A149: XP Investimentos | B149: SPX Lancer Plus XP Seg Prev FIC FIM | C149: 41.802.098/0001-88 | D149: XP VIDA E PREVIDÊNCIA S.A. | E149: 29.408.732/0001-05 | F149: XP Investimentos | G149: Multimercado | H149: Macro Alta Vol | I149: 100 | J149: 2 | M149: 2 | N149: 3 | Q149: Não | R149: Site (navegador) | S149: 1 | T149: Não | U149: Sim | V149: Não
A150: XP Investimentos | B150: Safari Prev 100 XP Seg FIM FIE | C150: 33.378.232/0001-37 | D150: SAFARI CAPITAL GESTÃO DE RECURSOS LTDA. | E150: 21.850.329/0001-11 | F150: BNY Mellon DTVM | G150: Multimercado | H150: Renda Variável Long Biased | I150: 100 | J150: 2 | M150: 33 | N150: 2 | Q150: Sim | R150: Site (navegador) | S150: 1 | T150: Não | U150: Sim | V150: Não
A151: XP Investimentos | B151: Safra Prev Vitesse Plus Advisory FIC RF CP Prev RL | C151: 57.850.204/0001-39 | D151: TURMALINA GESTÃO E ADMINISTRAÇÃO DE RECURSOS S.A. | E151: 43.826.833/0001-19 | F151: SAFRA SERVIÇOS DE ADMINISTRAÇÃO FIDUCIÁRIA | G151: Renda Fixa | H151: Crédito High Grade | I151: 100 | J151: 0.8 | M151: 9 | N151: 1 | Q151: Não | R151: Site (navegador) | S151: 1 | T151: Não | U151: Sim | V151: Não
A152: XP Investimentos | B152: Selection Multimercado XP Seg FIC FIM | C152: 35.386.842/0001-08 | D152: XP ADVISORY GESTAO DE RECURSOS LTDA | E152: 15.289.957/0001-77 | F152: XP Investimentos | G152: Multimercado | H152: Multiestratégia | I152: 100 | J152: 0.8 | M152: 7 | N152: 2 | Q152: Não | R152: Site (navegador) | S152: 1 | T152: Não | U152: Sim | V152: Não
A153: XP Investimentos | B153: Sharp Equity Value 100 XP Seg Prev FIC FIM | C153: 35.957.156/0001-40 | D153: XP VIDA E PREVIDÊNCIA S.A. | E153: 29.408.732/0001-05 | F153: BNY Mellon DTVM | G153: Multimercado | H153: Renda Variável Long Biased | I153: 100 | J153: 2 | M153: 22 | N153: 2 | Q153: Não | R153: Site (navegador) | S153: 1 | T153: Não | U153: Sim | V153: Não
A154: XP Investimentos | B154: Solis Antares XP Seg Prev FIC FIRF CP | C154: 41.866.372/0001-82 | D154: XP VIDA E PREVIDÊNCIA S.A. | E154: 29.408.732/0001-05 | F154: XP Serviços Financeiros DTVM LTDA | G154: Renda Fixa | H154: Crédito High Yield | I154: 100 | J154: 0.9 | M154: 21 | N154: 1 | Q154: Sim | R154: Site (navegador) | S154: 1 | T154: Não | U154: Sim | V154: Não
A155: XP Investimentos | B155: Sparta Inflação Prev Advisory XP Seg FIC FIRF CP | C155: 44.843.813/0001-19 | D155: XP VIDA E PREVIDÊNCIA S.A. | E155: 29.408.732/0001-05 | F155: XP Investimentos | G155: Renda Fixa | H155: Renda Fixa Inflação | I155: 100 | J155: 1.1 | M155: 5 | N155: 1 | Q155: Não | R155: Site (navegador) | S155: 1 | T155: Não | U155: Sim | V155: Não
A156: XP Investimentos | B156: Sparta Prev Advisory Xp Seg Fic Rf Cp Rl | C156: 32.239.012/0001-60 | D156: XP VIDA E PREVIDÊNCIA S.A. | E156: 29.408.732/0001-05 | F156: XPI Administradora - Modal | G156: Renda Fixa | H156: Crédito High Grade | I156: 100 | J156: 0.8 | M156: 5 | N156: 1 | Q156: Não | R156: Site (navegador) | S156: 1 | T156: Não | U156: Sim | V156: Não
A157: XP Investimentos | B157: Spx Lancer Xp Seg Prev I Fic Fim Rl | C157: 31.569.954/0001-43 | D157: XP VIDA E PREVIDÊNCIA S.A. | E157: 29.408.732/0001-05 | F157: XP Investimentos | G157: Multimercado | H157: Macro Alta Vol | I157: 100 | J157: 2 | M157: 2 | N157: 3 | Q157: Não | R157: Site (navegador) | S157: 1 | T157: Não | U157: Sim | V157: Não
A158: XP Investimentos | B158: Spx Long Bias Xp Seguros Prev Fic Fim Rl | C158: 40.526.764/0001-30 | D158: XP VIDA E PREVIDÊNCIA S.A. | E158: 29.408.732/0001-05 | F158: XP Investimentos | G158: Multimercado | H158: Renda Variável Long Biased | I158: 100 | J158: 2 | M158: 30 | N158: 2 | Q158: Sim | R158: Site (navegador) | S158: 1 | T158: Não | U158: Sim | V158: Não
A159: XP Investimentos | B159: Spx Seahawk Plus XP Seg Prev FIC FIM CP | C159: 43.636.185/0001-38 | D159: XP VIDA E PREVIDÊNCIA S.A. | E159: 29.408.732/0001-05 | F159: XP Investimentos | G159: Multimercado | H159: Crédito Híbrido | I159: 100 | J159: 0.8 | M159: 8 | N159: 1 | Q159: Não | R159: Site (navegador) | S159: 1 | T159: Não | U159: Sim | V159: Não
... A163: XP Investimentos | B163: Suno Ações Xp Seg Prev Fic Fim Rl | C163: 44.814.968/0001-27 | D163: XP VIDA E PREVIDÊNCIA S.A. | E163: 29.408.732/0001-05 | F163: XP Investimentos | G163: Multimercado | H163: Renda Variável Long Only | I163: 100 | J163: 2 | M163: 7 | N163: 2 | Q163: Não | R163: Site (navegador) | S163: 1 | T163: Não | U163: Sim | V163: Não
A164: XP Investimentos | B164: Tivio Alt Light XP Seg Prev FI FIM CP RL | C164: 53.991.177/0001-63 | D164: TIVIO CAPITAL DISTRIBUIDORA DE TITULOS E VALORES MOBILIARIOS S.A. | E164: 03.384.738/0001-98 | F164: XP Investimentos | G164: Multimercado | I164: 100 | J164: 1.15 | M164: 50 | N164: 2 | Q164: Sim | R164: Site (navegador) | S164: 1 | T164: Não | U164: Sim | V164: Não
A165: XP Investimentos | B165: Tork Long Only XP Seg Prev FIC FIA FIE | C165: 34.432.014/0001-04 | D165: XP GESTÃO DE RECURSOS LTDA | E165: 07.625.200/0001-89 | F165: BTG Pactual DTVM | G165: Multimercado | H165: Renda Variável Long Biased | I165: 100 | J165: 2 | M165: 30 | N165: 2 | Q165: Sim | R165: Site (navegador) | S165: 1 | T165: Não | U165: Sim | V165: Não
A166: XP Investimentos | B166: Trend B26 Prev XP Seg FIC FIRF RL | C166: 24.714.864/0001-33 | D166: XP VIDA E PREVIDÊNCIA S.A. | E166: 29.408.732/0001-05 | F166: XPI Administradora | G166: Renda Fixa | H166: Renda Fixa Inflação | I166: 100 | J166: 0.3 | M166: 2 | N166: 1 | Q166: Sim | R166: Site (navegador) | S166: 1 | T166: Não | U166: Sim | V166: Não
A167: XP Investimentos | B167: Trend B29 Xp Seguros Prev Firf Rl | C167: 49.228.354/0001-87 | D167: XP ALLOCATION ASSET MANAGEMENT LTDA | E167: 37.918.829/0001-88 | F167: XP Investimentos | G167: Renda Fixa | H167: Renda Fixa Inflação | I167: 100 | J167: 0.3 | M167: 0 | N167: 1 | Q167: Não | R167: Site (navegador) | S167: 1 | T167: Não | U167: Sim | V167: Não
A168: XP Investimentos | B168: Trend B35 Prev XP Seg FIC FIRF RL | C168: 27.077.318/0001-27 | D168: XP ALLOCATION ASSET MANAGEMENT LTDA | E168: 37.918.829/0001-88 | F168: XPI Administradora - Modal | G168: Renda Fixa | H168: Renda Fixa Inflação | I168: 100 | J168: 0.3 | M168: 2 | N168: 1 | Q168: Não | R168: Site (navegador) | S168: 1 | T168: Não | U168: Sim | V168: Não
A169: XP Investimentos | B169: Trend B50 Prev Xp Seg Fic Firf | C169: 47.033.019/0001-06 | D169: XP ALLOCATION ASSET MANAGEMENT LTDA | E169: 37.918.829/0001-88 | F169: XPI Administradora - Modal | G169: Renda Fixa | H169: Renda Fixa Inflação | I169: 100 | J169: 0.3 | M169: 0 | N169: 1 | Q169: Não | R169: Site (navegador) | S169: 1 | T169: Não | U169: Sim | V169: Não
A170: XP Investimentos | B170: Trend B60 XP Seg Prev RF RL | C170: 65.912.212/0001-90 | D170: XP ALLOCATION ASSET MANAGEMENT LTDA | E170: 37.918.829/0001-88 | F170: BNP Paribas | G170: Renda Fixa | H170: Renda Fixa Inflação | I170: 100 | J170: 0.3 | M170: 0 | N170: 1 | Q170: Não | R170: Site (navegador) | S170: 1 | T170: Não | U170: Sim | V170: Não
A171: XP Investimentos | B171: Trend Bolsa Americana 40 Prev XP FIM RL | C171: 41.610.532/0001-28 | D171: XP ALLOCATION ASSET MANAGEMENT LTDA | E171: 37.918.829/0001-88 | F171: XP Investimentos | G171: Multimercado | H171: Internacional Ações Hedgeado | I171: 100 | J171: 0.33 | M171: 0 | N171: 1 | Q171: Não | R171: Site (navegador) | S171: 1 | T171: Não | U171: Sim | V171: Não
A172: XP Investimentos | B172: Trend Ibovespa 100 XP Seg Prev FIC FIA RL | C172: 33.795.343/0001-49 | D172: XP ALLOCATION ASSET MANAGEMENT LTDA | E172: 37.918.829/0001-88 | F172: BNY Mellon DTVM | G172: Ações | H172: Renda Variável Indexado | I172: 100 | J172: 0.4 | M172: 0 | N172: 2 | Q172: Não | R172: Site (navegador) | S172: 1 | T172: Não | U172: Sim | V172: Não
A173: XP Investimentos | B173: Trend Ibovespa 70 XP Seg Prev FIC FIM RL | C173: 33.784.183/0001-32 | D173: XP ALLOCATION ASSET MANAGEMENT LTDA | E173: 37.918.829/0001-88 | F173: BNY Mellon DTVM | G173: Multimercado | H173: Renda Variável Indexado | I173: 100 | J173: 0.35 | M173: 0 | N173: 2 | Q173: Não | R173: Site (navegador) | S173: 1 | T173: Não | U173: Sim | V173: Não
A174: XP Investimentos | B174: Trend Imab5+ & Bolsa Americana Dólar Xp Seg Prev Fim Rl | C174: 52.840.043/0001-89 | D174: XP ALLOCATION ASSET MANAGEMENT LTDA | E174: 37.918.829/0001-88 | F174: XP Investimentos | G174: Multimercado | H174: Multiestratégia | I174: 100 | J174: 0.5 | M174: 0 | N174: 2 | Q174: Não | R174: Site (navegador) | S174: 1 | T174: Não | U174: Sim | V174: Não
A175: XP Investimentos | B175: Trend Inflação Curta XP Seg Prev FICFI RF | C175: 32.065.041/0001-52 | D175: XP ALLOCATION ASSET MANAGEMENT LTDA | E175: 37.918.829/0001-88 | F175: XPI Administradora | G175: Renda Fixa | H175: Renda Fixa Inflação | I175: 100 | J175: 0.4 | M175: 0 | N175: 1 | Q175: Não | R175: Site (navegador) | S175: 1 | T175: Não | U175: Sim | V175: Não
A176: XP Investimentos | B176: Trend Pré-Fixado XP Seg Prev FIC FIRF RL | C176: 33.755.733/0001-95 | D176: XP ALLOCATION ASSET MANAGEMENT LTDA | E176: 37.918.829/0001-88 | F176: XP Investimentos | G176: Renda Fixa | H176: Renda Fixa Pré | I176: 100 | J176: 0.4 | M176: 0 | N176: 1 | Q176: Não | R176: Site (navegador) | S176: 1 | T176: Não | U176: Sim | V176: Não
... A219: XP Investimentos | B219: Xp Termo Xp Seg Prev Ficfim Cp | C219: 47.032.813/0001-27 | D219: XP VIDA E PREVIDÊNCIA S.A. | E219: 29.408.732/0001-05 | F219: XPI Administradora | G219: Multimercado | H219: Crédito Liquidez | I219: 100 | J219: 0.5 | M219: 5 | N219: 1 | Q219: Não | R219: Site (navegador) | S219: 1 | T219: Não | U219: Sim | V219: Não

Sheet BTG Pactual
A1: Plataforma | B1: Fundo | C1: CNPJ | D1: Gestora | E1: CNPJ da gestora | F1: Administrador | G1: Classe | H1: Categoria na origem | I1: Aplicação mínima (R$) | J1: Taxa adm (%) | K1: Taxa perf (%) | L1: Benchmark | M1: Cotização resgate (D+) | N1: Líquidação resgate (D+) | O1: Carência (dias) | P1: Tributação | Q1: Fechado p/ captação | R1: Fontes | S1: Nº de fontes | T1: Open Finance | U1: Prateleira (site) | V1: Área logada | W1: Link
A2: BTG Pactual | B2: 3R Genus Hedge Prev FIM RL | C2: 51.694.298/0001-18 | D2: 3R GESTORA DE RECURSOS LTDA | E2: 13.641.353/0001-12 | F2: BTG PACTUAL SERVICOS FINANCEIROS S.A. DISTRIBUIDOR | G2: Multimercado | H2: Renda Variável | I2: 1000 | K2: 20 | L2: - | M2: 3 | N2: 4 | P2: Curto Prazo | Q2: Sim | R2: API interna | S2: 1 | T2: Não | U2: Sim | V2: Não
A3: BTG Pactual | B3: A1 High Grade FIE I Prev BP FIC FIRF | C3: 67.124.600/0001-32 | D3: ASSET1 INVESTIMENTOS S/A | E3: 35.185.577/0001-08 | F3: BTG PACTUAL SERVICOS FINANCEIROS S.A. DISTRIBUIDOR | G3: Renda Fixa | H3: Outros | I3: 1000 | J3: 0.85 | M3: 0 | N3: 2 | P3: Longo Prazo | Q3: Não | R3: API interna | S3: 1 | T3: Não | U3: Sim | V3: Não
A4: BTG Pactual | B4: A1 RF Ativa Prev FICFIRF RL | C4: 60.356.190/0001-06 | D4: ASSET1 INVESTIMENTOS S/A | E4: 35.185.577/0001-08 | F4: BTG PACTUAL SERVICOS FINANCEIROS S.A. DISTRIBUIDOR | G4: Renda Fixa | H4: Renda Fixa | I4: 1000 | K4: 20 | L4: - | M4: 0 | N4: 1 | P4: Curto Prazo | Q4: Não | R4: API interna | S4: 1 | T4: Não | U4: Sim | V4: Não
A5: BTG Pactual | B5: ACE Capital Prev Icatu FICFIM RL | C5: 48.212.959/0001-17 | D5: ACE CAPITAL GESTORA DE RECURSOS LTDA. | E5: 33.411.393/0001-85 | F5: INTRAG DISTR DE TITULOS EVALORES MOBILIARIOS LTDA | G5: Multimercado | H5: Multimercado | I5: 1500 | J5: 2 | K5: 20 | L5: CDI | M5: 6 | N5: 7 | P5: Longo Prazo | Q5: Não | R5: API interna | S5: 1 | T5: Não | U5: Sim | V5: Não
A6: BTG Pactual | B6: ARX Denali Prev FIRF Access CrPr RL | C6: 47.564.808/0001-65 | D6: BTG PACTUAL GESTÃO E CONSULTORIA DE INVESTIMENTOS LTDA | E6: 12.695.840/0001-03 | F6: BTG PACTUAL SERVICOS FINANCEIROS S.A. DISTRIBUIDOR | G6: Renda Fixa | H6: Renda Fixa | I6: 1000 | M6: 2 | N6: 4 | P6: Curto Prazo | Q6: Não | R6: API interna | S6: 1 | T6: Não | U6: Sim | V6: Não
A7: BTG Pactual | B7: ARX Income Icatu Prev 100 FICFIA RL | C7: 37.355.672/0001-20 | D7: ARX INVESTIMENTOS LTDA | E7: 04.408.128/0001-40 | F7: BNY MELLON SERVICOS FINANCEIROS DTVM S/A | G7: Ações | H7: Renda Variável | I7: 5000 | J7: 2 | K7: 20 | L7: IBOVESPA | M7: 6 | N7: 8 | P7: Renda Variável | Q7: Não | R7: API interna | S7: 1 | T7: Não | U7: Sim | V7: Não
A8: BTG Pactual | B8: ARX Income Icatu Prev FIM RL | C8: 03.879.361/0001-48 | D8: ARX INVESTIMENTOS LTDA | E8: 04.408.128/0001-40 | F8: BNY MELLON SERVICOS FINANCEIROS DTVM S/A | G8: Multimercado | H8: Renda Variável | I8: 1000 | J8: 1.9 | M8: 1 | N8: 2 | P8: Não Aplicável | Q8: Não | R8: API interna | S8: 1 | T8: Não | U8: Sim | V8: Não
A9: BTG Pactual | B9: ARX K2 Prev FICFIM CrPr RL | C9: 33.165.244/0001-83 | D9: ARX INVESTIMENTOS LTDA | E9: 04.408.128/0001-40 | F9: BTG PACTUAL SERVICOS FINANCEIROS S.A. DISTRIBUIDOR | G9: Multimercado | H9: Renda Fixa | I9: 0 | J9: 1.1 | M9: 5 | N9: 7 | P9: Curto Prazo | Q9: Não | R9: API interna | S9: 1 | T9: Não | U9: Sim | V9: Não
A10: BTG Pactual | B10: ASA Hedge Icatu Prev FICFIM RL | C10: 26.343.792/0001-90 | D10: ASA ASSET MANAGEMENT LTDA. | E10: 19.807.960/0001-96 | F10: S3 CACEIS BRASIL DISTRIBUIDORA DE TITULOS E VALORE | G10: Multimercado | H10: Multimercado | I10: 1000 | J10: 0.95 | M10: 0 | N10: 3 | P10: Longo Prazo | Q10: Não | R10: API interna | S10: 1 | T10: Não | U10: Sim | V10: Não
A11: BTG Pactual | B11: AZ Quest Altro Prev FICFIM FIE Access CrPr RL | C11: 47.640.749/0001-67 | D11: BTG PACTUAL GESTÃO E CONSULTORIA DE INVESTIMENTOS LTDA | E11: 12.695.840/0001-03 | F11: BTG PACTUAL SERVICOS FINANCEIROS S.A. DISTRIBUIDOR | G11: Multimercado | H11: Renda Fixa | I11: 1000 | M11: 20 | N11: 21 | P11: Curto Prazo | Q11: Não | R11: API interna | S11: 1 | T11: Não | U11: Sim | V11: Não
A12: BTG Pactual | B12: AZ Quest Icatu Multi Prev FICFIM RL | C12: 18.534.967/0001-19 | D12: AZ Quest Prev Ltda. | E12: 59.312.965/0001-62 | F12: BNY MELLON SERVICOS FINANCEIROS DTVM S/A | G12: Multimercado | H12: Multimercado | I12: 1500 | J12: 2 | M12: 1 | N12: 3 | P12: Não Aplicável | Q12: Não | R12: API interna | S12: 1 | T12: Não | U12: Sim | V12: Não
A13: BTG Pactual | B13: AZ Quest Inflacao Ativo Prev FIE I FICFIRF RL | C13: 34.442.059/0001-51 | D13: AZ Quest Prev Ltda. | E13: 59.312.965/0001-62 | F13: BNY MELLON SERVICOS FINANCEIROS DTVM S/A | G13: Renda Fixa | H13: Renda Fixa | I13: 1500 | J13: 0.55 | M13: 0 | N13: 1 | P13: Longo Prazo | Q13: Não | R13: API interna | S13: 1 | T13: Não | U13: Sim | V13: Não
A14: BTG Pactual | B14: AZ Quest Prev Icatu Luce FICFIRF CrPr RL | C14: 23.883.385/0001-88 | D14: AZ Quest Prev Ltda. | E14: 59.312.965/0001-62 | F14: BNY MELLON SERVICOS FINANCEIROS DTVM S/A | G14: Renda Fixa | H14: Renda Fixa | I14: 3000 | J14: 0.55 | M14: 1 | N14: 3 | P14: Longo Prazo | Q14: Não | R14: API interna | S14: 1 | T14: Não | U14: Sim | V14: Não
A15: BTG Pactual | B15: Absolute Atenas Prev FIM Access CrPr RL | C15: 47.564.734/0001-67 | D15: BTG PACTUAL GESTÃO E CONSULTORIA DE INVESTIMENTOS LTDA | E15: 12.695.840/0001-03 | F15: BTG PACTUAL SERVICOS FINANCEIROS S.A. DISTRIBUIDOR | G15: Renda Fixa | H15: Renda Fixa | I15: 1000 | J15: 0.98 | M15: 6 | N15: 8 | P15: Curto Prazo | Q15: Não | R15: API interna | S15: 1 | T15: Não | U15: Sim | V15: Não
A16: BTG Pactual | B16: Absolute Delfos Prev FICFIRF Access CrPr RL | C16: 57.370.727/0001-88 | D16: BTG PACTUAL GESTÃO E CONSULTORIA DE INVESTIMENTOS LTDA | E16: 12.695.840/0001-03 | F16: BTG PACTUAL SERVICOS FINANCEIROS S.A. DISTRIBUIDOR | G16: Renda Fixa | H16: Renda Fixa | I16: 1000 | J16: 0.88 | M16: 20 | N16: 22 | P16: Curto Prazo | Q16: Não | R16: API interna | S16: 1 | T16: Não | U16: Sim | V16: Não
A17: BTG Pactual | B17: Absolute Hedge Prev FICFIM Access RL | C17: 61.861.454/0001-41 | D17: BTG PACTUAL GESTÃO E CONSULTORIA DE INVESTIMENTOS LTDA | E17: 12.695.840/0001-03 | F17: BTG PACTUAL SERVICOS FINANCEIROS S.A. DISTRIBUIDOR | G17: Multimercado | H17: Multimercado | I17: 1000 | J17: 2 | K17: 20 | L17: - | M17: 4 | N17: 5 | P17: Curto Prazo | Q17: Não | R17: API interna | S17: 1 | T17: Não | U17: Sim | V17: Não
A18: BTG Pactual | B18: Absolute Icatu I Prev FICFIM RL | C18: 29.242.441/0001-81 | D18: ABSOLUTE GESTAO DE INVESTIMENTOS LTDA | E18: 17.285.755/0001-82 | F18: BNY MELLON SERVICOS FINANCEIROS DTVM S/A | G18: Multimercado | H18: Multimercado | I18: 1500 | J18: 2 | K18: 20 | L18: CDI | M18: 0 | N18: 3 | P18: Longo Prazo | Q18: Não | R18: API interna | S18: 1 | T18: Não | U18: Sim | V18: Não
A19: BTG Pactual | B19: Absolute Pace Prev FICFIA Access RL | C19: 55.498.621/0001-39 | D19: BTG PACTUAL GESTÃO E CONSULTORIA DE INVESTIMENTOS LTDA | E19: 12.695.840/0001-03 | F19: BTG PACTUAL SERVICOS FINANCEIROS S.A. DISTRIBUIDOR | G19: Ações | H19: Renda Variável | I19: 0 | J19: 2 | K19: 20 | L19: - | M19: 22 | N19: 24 | P19: Curto Prazo | Q19: Sim | R19: API interna | S19: 1 | T19: Não | U19: Sim | V19: Não
A20: BTG Pactual | B20: Absolute Vertex Prev FIM Access RL | C20: 43.509.130/0001-67 | D20: BTG PACTUAL GESTÃO E CONSULTORIA DE INVESTIMENTOS LTDA | E20: 12.695.840/0001-03 | F20: BTG PACTUAL SERVICOS FINANCEIROS S.A. DISTRIBUIDOR | G20: Multimercado | H20: Multimercado | I20: 1000 | J20: 2 | K20: 20 | L20: CDI | M20: 21 | N20: 22 | P20: Curto Prazo | Q20: Não | R20: API interna | S20: 1 | T20: Não | U20: Sim | V20: Não
A21: BTG Pactual | B21: Adam BP Prev FICFIM RL | C21: 24.751.504/0001-01 | D21: ADAMCAPITAL GESTÃO DE RECURSOS LTDA. | E21: 17.905.206/0001-63 | F21: INTRAG DISTR DE TITULOS EVALORES MOBILIARIOS LTDA | G21: Multimercado | H21: Multimercado | I21: 1000 | J21: 2 | M21: 0 | N21: 2 | P21: Longo Prazo | Q21: Sim | R21: API interna | S21: 1 | T21: Não | U21: Sim | V21: Não
A22: BTG Pactual | B22: Adam Icatu RF Ativa Prev FICFIRF LP RL | C22: 52.091.995/0001-47 | D22: ADAMCAPITAL GESTÃO DE RECURSOS LTDA. | E22: 17.905.206/0001-63 | F22: INTRAG DISTR DE TITULOS EVALORES MOBILIARIOS LTDA | G22: Renda Fixa | H22: Renda Fixa | I22: 1500 | J22: 0.9 | M22: 5 | N22: 6 | P22: Longo Prazo | Q22: Não | R22: API interna | S22: 1 | T22: Não | U22: Sim | V22: Não
A23: BTG Pactual | B23: Alaska Long Only Prev 70 FICFIM RL | C23: 41.881.132/0001-57 | D23: ALASKA INVESTIMENTOS LTDA. | E23: 11.752.203/0001-50 | F23: BTG PACTUAL SERVICOS FINANCEIROS S.A. DISTRIBUIDOR | G23: Multimercado | H23: Renda Variável | I23: 1000 | J23: 1.65 | K23: 20 | L23: - | M23: 6 | N23: 8 | P23: Curto Prazo | Q23: Não | R23: API interna | S23: 1 | T23: Não | U23: Sim | V23: Não
A24: BTG Pactual | B24: Alaska Prev 100 Long Only FICFIM RL | C24: 37.313.900/0001-07 | D24: ALASKA INVESTIMENTOS LTDA. | E24: 11.752.203/0001-50 | F24: BTG PACTUAL SERVICOS FINANCEIROS S.A. DISTRIBUIDOR | G24: Multimercado | H24: Renda Variável | I24: 0 | J24: 1.5 | K24: 20 | L24: - | M24: 6 | N24: 8 | P24: Curto Prazo | Q24: Não | R24: API interna | S24: 1 | T24: Não | U24: Sim | V24: Não
A25: BTG Pactual | B25: Alphakey Prev 70 FIC FIF MM | C25: 65.655.653/0001-54 | D25: ALPHAKEY CAPITAL MANAGEMENT INVESTIMENTOS LTDA | E25: 31.340.246/0001-36 | F25: BTG PACTUAL SERVICOS FINANCEIROS S.A. DISTRIBUIDOR | G25: Multimercado | H25: Renda Variável | I25: 1000 | K25: 20 | L25: - | M25: 8 | N25: 10 | P25: Curto Prazo | Q25: Não | R25: API interna | S25: 1 | T25: Não | U25: Sim | V25: Não
A26: BTG Pactual | B26: Arca Grao Prev FICFIM Access RL | C26: 42.848.021/0001-01 | D26: GRÃO GESTÃO DE RECURSOS LTDA. | E26: 43.739.164/0001-48 | F26: S3 CACEIS BRASIL DISTRIBUIDORA DE TITULOS E VALORE | G26: Multimercado | H26: Alocação | I26: 1000 | J26: 0.59 | M26: 7 | N26: 9 | P26: Longo Prazo | Q26: Não | R26: API interna | S26: 1 | T26: Não | U26: Sim | V26: Não
A27: BTG Pactual | B27: Arca Grao Prev FICFIRF Access CrPr RL | C27: 57.445.402/0001-17 | D27: GRÃO GESTÃO DE RECURSOS LTDA. | E27: 43.739.164/0001-48 | F27: S3 CACEIS BRASIL DISTRIBUIDORA DE TITULOS E VALORE | G27: Renda Fixa | H27: Renda Fixa | I27: 1000 | J27: 0.59 | M27: 7 | N27: 9 | P27: Não Aplicável | Q27: Sim | R27: API interna | S27: 1 | T27: Não | U27: Sim | V27: Não
A28: BTG Pactual | B28: Armor Prev FIE I FIF MM | C28: 64.157.228/0001-72 | D28: ARMOR GESTORA DE RECURSOS LTDA. | E28: 34.176.302/0001-37 | F28: BTG PACTUAL SERVICOS FINANCEIROS S.A. DISTRIBUIDOR | G28: Multimercado | H28: Outros | I28: 1000 | K28: 20 | L28: - | M28: 5 | N28: 6 | P28: Longo Prazo | Q28: Não | R28: API interna | S28: 1 | T28: Não | U28: Sim | V28: Não
A29: BTG Pactual | B29: Artesanal Prev FIM RL | C29: 53.497.497/0001-61 | D29: ARTESANAL INVESTIMENTOS LTDA | E29: 03.084.098/0001-09 | F29: BTG PACTUAL SERVICOS FINANCEIROS S.A. DISTRIBUIDOR | G29: Multimercado | H29: Multimercado | I29: 100 | K29: 15 | L29: - | M29: 9 | N29: 10 | P29: Longo Prazo | Q29: Não | R29: API interna | S29: 1 | T29: Não | U29: Sim | V29: Não
A30: BTG Pactual | B30: Artica Prev FIM RL | C30: 54.347.632/0001-55 | D30: ARTICA GESTÃO DE RECURSOS LTDA | E30: 31.227.292/0001-23 | F30: BTG PACTUAL SERVICOS FINANCEIROS S.A. DISTRIBUIDOR | G30: Multimercado | H30: Renda Variável | I30: 1000 | K30: 20 | L30: IBOVESPA | M30: 88 | N30: 90 | P30: Curto Prazo | Q30: Não | R30: API interna | S30: 1 | T30: Não | U30: Sim | V30: Não
A31: BTG Pactual | B31: Atena Prev FICFIRF FIE 1 CrPr RL | C31: 53.798.822/0001-26 | D31: ATENA CAPITAL GESTÃO DE RECURSOS LTDA. | E31: 19.005.052/0001-89 | F31: BTG PACTUAL SERVICOS FINANCEIROS S.A. DISTRIBUIDOR | G31: Renda Fixa | H31: Renda Fixa | I31: 1000 | K31: 15 | L31: - | M31: 7 | N31: 9 | P31: Curto Prazo | Q31: Não | R31: API interna | S31: 1 | T31: Não | U31: Sim | V31: Não
A32: BTG Pactual | B32: Atlas ONE Icatu 70 Prev FIM RL | C32: 33.520.932/0001-14 | D32: ATLAS ONE INVESTIMENTOS GESTÃO DE RECURSOS LTDA. | E32: 36.658.682/0001-71 | F32: BEM DISTRIBUIDORA DE TITULOS E VALORES MOBILIARIOS | G32: Multimercado | H32: Renda Variável | I32: 1500 | J32: 0.55 | M32: 7 | N32: 9 | P32: Longo Prazo | Q32: Não | R32: API interna | S32: 1 | T32: Não | U32: Sim | V32: Não
A33: BTG Pactual | B33: BTG Alocacao Global Cred Prev FIM CrPr RL | C33: 52.279.451/0001-03 | D33: BTG PACTUAL ASSET MANAGEMENT S/A DTVM | E33: 29.650.082/0001-00 | F33: BTG PACTUAL SERVICOS FINANCEIROS S.A. DISTRIBUIDOR | G33: Multimercado | H33: Multimercado | I33: 1000 | M33: 7 | N33: 8 | P33: Curto Prazo | Q33: Não | R33: API interna | S33: 1 | T33: Não | U33: Sim | V33: Não
A34: BTG Pactual | B34: BTG Autoinvest Balanceado Prev FIM CrPr RL | C34: 44.672.908/0001-17 | D34: BTG PACTUAL GESTÃO E CONSULTORIA DE INVESTIMENTOS LTDA | E34: 12.695.840/0001-03 | F34: BTG PACTUAL SERVICOS FINANCEIROS S.A. DISTRIBUIDOR | G34: Multimercado | H34: Alocação | I34: 1000 | J34: 0.5 | K34: 10 | L34: CDI | M34: 7 | N34: 9 | P34: Curto Prazo | Q34: Não | R34: API interna | S34: 1 | T34: Não | U34: Sim | V34: Não
A35: BTG Pactual | B35: BTG Autoinvest Sofisticado Prev FIM CrPr RL | C35: 20.332.753/0001-01 | D35: BTG PACTUAL GESTÃO E CONSULTORIA DE INVESTIMENTOS LTDA | E35: 12.695.840/0001-03 | F35: BTG PACTUAL SERVICOS FINANCEIROS S.A. DISTRIBUIDOR | G35: Multimercado | H35: Alocação | I35: 1000 | J35: 1 | M35: 0 | N35: 2 | P35: Curto Prazo | Q35: Não | R35: API interna | S35: 1 | T35: Não | U35: Sim | V35: Não
A36: BTG Pactual | B36: BTG CDB Plus Prev FIM CrPr RL | C36: 47.564.915/0001-93 | D36: BTG PACTUAL ASSET MANAGEMENT S/A DTVM | E36: 29.650.082/0001-00 | F36: BTG PACTUAL SERVICOS FINANCEIROS S.A. DISTRIBUIDOR | G36: Multimercado | H36: Renda Fixa | I36: 1000 | M36: 0 | N36: 1 | P36: Curto Prazo | Q36: Não | R36: API interna | S36: 1 | T36: Não | U36: Sim | V36: Não
A37: BTG Pactual | B37: BTG Cred Corp OAK3 Global Prev FIE FIM CrPr RL | C37: 54.304.610/0001-08 | D37: BTG PACTUAL ASSET MANAGEMENT S/A DTVM | E37: 29.650.082/0001-00 | F37: BTG PACTUAL SERVICOS FINANCEIROS S.A. DISTRIBUIDOR | G37: Multimercado | H37: Renda Fixa | I37: 1000 | M37: 9 | N37: 12 | P37: Curto Prazo | Q37: Não | R37: API interna | S37: 1 | T37: Não | U37: Sim | V37: Não
A38: BTG Pactual | B38: BTG Icatu Vanguarda Absoluto II FIRF Prev CrPr RL | C38: 46.700.364/0001-85 | D38: ICATU VANGUARDA GESTÃO DE RECURSOS LTDA | E38: 68.622.174/0001-20 | F38: BEM DISTRIBUIDORA DE TITULOS E VALORES MOBILIARIOS | G38: Renda Fixa | H38: Renda Fixa | I38: 1000 | J38: 0.8 | K38: 20 | L38: CDI | M38: 9 | N38: 10 | P38: Longo Prazo | Q38: Não | R38: API interna | S38: 1 | T38: Não | U38: Sim | V38: Não
A39: BTG Pactual | B39: BTG Long Term Prev FIA FIE | C39: 57.976.621/0001-22 | D39: BTG PACTUAL ASSET MANAGEMENT S/A DTVM | E39: 29.650.082/0001-00 | F39: BTG PACTUAL SERVICOS FINANCEIROS S.A. DISTRIBUIDOR | G39: Ações | H39: Renda Variável | I39: 1000 | K39: 20 | L39: - | M39: 30 | N39: 32 | P39: Curto Prazo | Q39: Não | R39: API interna | S39: 1 | T39: Não | U39: Sim | V39: Não
A40: BTG Pactual | B40: BTG Multigestor Credit Plus Prev FICFIM CrPr RL | C40: 60.230.790/0001-23 | D40: BTG PACTUAL GESTÃO E CONSULTORIA DE INVESTIMENTOS LTDA | E40: 12.695.840/0001-03 | F40: BTG PACTUAL SERVICOS FINANCEIROS S.A. DISTRIBUIDOR | G40: Multimercado | H40: Renda Fixa | I40: 1000 | M40: 30 | N40: 32 | P40: Curto Prazo | Q40: Não | R40: API interna | S40: 1 | T40: Não | U40: Sim | V40: Não
A41: BTG Pactual | B41: BTG Pactual Absoluto LS Prev FICFIM RL | C41: 37.681.077/0001-84 | D41: BTG PACTUAL ASSET MANAGEMENT S/A DTVM | E41: 29.650.082/0001-00 | F41: BTG PACTUAL SERVICOS FINANCEIROS S.A. DISTRIBUIDOR | G41: Multimercado | H41: Renda Variável | I41: 1000 | J41: 2 | K41: 20 | L41: CDI | M41: 6 | N41: 8 | P41: Curto Prazo | Q41: Não | R41: API interna | S41: 1 | T41: Não | U41: Sim | V41: Não
A42: BTG Pactual | B42: BTG Pactual Absoluto Prev FICFIM CrPr RL | C42: 35.002.894/0001-33 | D42: BTG PACTUAL ASSET MANAGEMENT S/A DTVM | E42: 29.650.082/0001-00 | F42: BTG PACTUAL SERVICOS FINANCEIROS S.A. DISTRIBUIDOR | G42: Multimercado | H42: Renda Variável | I42: 0 | J42: 1.75 | K42: 20 | L42: IBOVESPA | M42: 7 | N42: 9 | P42: Curto Prazo | Q42: Não | R42: API interna | S42: 1 | T42: Não | U42: Sim | V42: Não
A43: BTG Pactual | B43: BTG Pactual Cred Corp II Prev FICFIM CrPr RL | C43: 44.025.282/0001-57 | D43: BTG PACTUAL ASSET MANAGEMENT S/A DTVM | E43: 29.650.082/0001-00 | F43: BTG PACTUAL SERVICOS FINANCEIROS S.A. DISTRIBUIDOR | G43: Multimercado | H43: Renda Fixa | I43: 0 | J43: 0.9 | K43: 20 | L43: CDI | M43: 6 | N43: 7 | P43: Curto Prazo | Q43: Não | R43: API interna | S43: 1 | T43: Não | U43: Sim | V43: Não
A44: BTG Pactual | B44: BTG Pactual Cred Corp Plus Prev FIE FICFIM CrPr RL | C44: 41.801.819/0001-35 | D44: BTG PACTUAL ASSET MANAGEMENT S/A DTVM | E44: 29.650.082/0001-00 | F44: BTG PACTUAL SERVICOS FINANCEIROS S.A. DISTRIBUIDOR | G44: Renda Fixa | H44: Renda Fixa | I44: 1000 | J44: 1.1 | K44: 20 | L44: CDI | M44: 7 | N44: 9 | P44: Curto Prazo | Q44: Não | R44: API interna | S44: 1 | T44: Não | U44: Sim | V44: Não
A45: BTG Pactual | B45: BTG Pactual Cred Corp Prev Ipca FIRF CrPr RL | C45: 43.103.846/0001-60 | D45: BTG PACTUAL ASSET MANAGEMENT S/A DTVM | E45: 29.650.082/0001-00 | F45: BTG PACTUAL SERVICOS FINANCEIROS S.A. DISTRIBUIDOR | G45: Renda Fixa | H45: Renda Fixa | I45: 5000 | J45: 0.8 | K45: 20 | L45: IMA-B | M45: 5 | N45: 7 | P45: Curto Prazo | Q45: Não | R45: API interna | S45: 1 | T45: Não | U45: Sim | V45: Não
A46: BTG Pactual | B46: BTG Pactual Discovery Prev FICFIM RL | C46: 29.178.343/0001-22 | D46: BTG PACTUAL ASSET MANAGEMENT S/A DTVM | E46: 29.650.082/0001-00 | F46: BTG PACTUAL SERVICOS FINANCEIROS S.A. DISTRIBUIDOR | G46: Multimercado | H46: Multimercado | I46: 0 | J46: 2 | M46: 6 | N46: 7 | P46: Curto Prazo | Q46: Não | R46: API interna | S46: 1 | T46: Não | U46: Sim | V46: Não
A47: BTG Pactual | B47: BTG Pactual Hedge Prev FIM CrPr RL | C47: 50.875.116/0001-42 | D47: BTG PACTUAL ASSET MANAGEMENT S/A DTVM | E47: 29.650.082/0001-00 | F47: BTG PACTUAL SERVICOS FINANCEIROS S.A. DISTRIBUIDOR | G47: Multimercado | H47: Renda Fixa | I47: 1000 | J47: 1 | K47: 20 | L47: CDI | M47: 7 | N47: 9 | P47: Curto Prazo | Q47: Não | R47: API interna | S47: 1 | T47: Não | U47: Sim | V47: Não
A48: BTG Pactual | B48: BTG Pactual Hedge Sigma Prev FIE FICFIM RL | C48: 44.025.612/0001-04 | D48: BTG PACTUAL ASSET MANAGEMENT S/A DTVM | E48: 29.650.082/0001-00 | F48: BTG PACTUAL SERVICOS FINANCEIROS S.A. DISTRIBUIDOR | G48: Multimercado | H48: Renda Fixa | I48: 1000 | J48: 1 | M48: 2 | N48: 3 | P48: Curto Prazo | Q48: Não | R48: API interna | S48: 1 | T48: Não | U48: Sim | V48: Não
A49: BTG Pactual | B49: BTG Pactual Ibovespa 100 Index Prev FIM RL | C49: 55.138.930/0001-06 | D49: BTG PACTUAL ASSET MANAGEMENT S/A DTVM | E49: 29.650.082/0001-00 | F49: BTG PACTUAL SERVICOS FINANCEIROS S.A. DISTRIBUIDOR | G49: Multimercado | H49: Renda Variável | I49: 1000 | M49: 2 | N49: 4 | P49: Curto Prazo | Q49: Não | R49: API interna | S49: 1 | T49: Não | U49: Sim | V49: Não
A50: BTG Pactual | B50: BTG Pactual Ipca Curta Prev FICFIRF CrPr RL | C50: 54.305.132/0001-50 | D50: BTG PACTUAL ASSET MANAGEMENT S/A DTVM | E50: 29.650.082/0001-00 | F50: BTG PACTUAL SERVICOS FINANCEIROS S.A. DISTRIBUIDOR | G50: Renda Fixa | H50: Renda Fixa | I50: 0 | J50: 0.35 | M50: 0 | N50: 1 | P50: Curto Prazo | Q50: Não | R50: API interna | S50: 1 | T50: Não | U50: Sim | V50: Não
A51: BTG Pactual | B51: BTG Pactual Macro HF FIE Prev FICFIM RL | C51: 43.915.616/0001-03 | D51: BTG PACTUAL ASSET MANAGEMENT S/A DTVM | E51: 29.650.082/0001-00 | F51: BTG PACTUAL SERVICOS FINANCEIROS S.A. DISTRIBUIDOR | G51: Multimercado | H51: Multimercado | I51: 1000 | J51: 2.5 | M51: 7 | N51: 9 | P51: Curto Prazo | Q51: Não | R51: API interna | S51: 1 | T51: Não | U51: Sim | V51: Não
A52: BTG Pactual | B52: BTG Pactual NTN B 2035 Yield Prev FIRF RL | C52: 42.357.379/0001-31 | D52: BTG PACTUAL ASSET MANAGEMENT S/A DTVM | E52: 29.650.082/0001-00 | F52: BTG PACTUAL SERVICOS FINANCEIROS S.A. DISTRIBUIDOR | G52: Renda Fixa | H52: Renda Fixa | I52: 1000 | J52: 0.25 | M52: 2 | N52: 3 | P52: Curto Prazo | Q52: Não | R52: API interna | S52: 1 | T52: Não | U52: Sim | V52: Não
A53: BTG Pactual | B53: BTG Pactual NTN B 2045 Yield Prev FIRF RL | C53: 54.248.765/0001-74 | D53: BTG PACTUAL ASSET MANAGEMENT S/A DTVM | E53: 29.650.082/0001-00 | F53: BTG PACTUAL SERVICOS FINANCEIROS S.A. DISTRIBUIDOR | G53: Renda Fixa | H53: Renda Fixa | I53: 1000 | M53: 2 | N53: 3 | P53: Longo Prazo | Q53: Não | R53: API interna | S53: 1 | T53: Não | U53: Sim | V53: Não
A54: BTG Pactual | B54: BTG Pactual NTN B 2055 Yield Prev FIRF RL | C54: 50.876.690/0001-15 | D54: BTG PACTUAL ASSET MANAGEMENT S/A DTVM | E54: 29.650.082/0001-00 | F54: BTG PACTUAL SERVICOS FINANCEIROS S.A. DISTRIBUIDOR | G54: Renda Fixa | H54: Renda Fixa | I54: 1000 | J54: 0.25 | M54: 2 | N54: 3 | P54: Curto Prazo | Q54: Não | R54: API interna | S54: 1 | T54: Não | U54: Sim | V54: Não
A55: BTG Pactual | B55: BTG Pactual Prev IMA B FICFIRF de Fundos de RF RL | C55: 22.187.479/0001-50 | D55: BTG PACTUAL ASSET MANAGEMENT S/A DTVM | E55: 29.650.082/0001-00 | F55: BTG PACTUAL SERVICOS FINANCEIROS S.A. DISTRIBUIDOR | G55: Renda Fixa | H55: Renda Fixa | I55: 1000 | J55: 0.5 | M55: 1 | N55: 2 | P55: Curto Prazo | Q55: Não | R55: API interna | S55: 1 | T55: Não | U55: Sim | V55: Não
A56: BTG Pactual | B56: BTG Pactual Reference S&P500 USD Prev FIM RL | C56: 44.025.397/0001-41 | D56: BTG PACTUAL ASSET MANAGEMENT S/A DTVM | E56: 29.650.082/0001-00 | F56: BTG PACTUAL SERVICOS FINANCEIROS S.A. DISTRIBUIDOR | G56: Multimercado | H56: Multimercado | I56: 1000 | M56: 1 | N56: 3 | P56: Curto Prazo | Q56: Não | R56: API interna | S56: 1 | T56: Não | U56: Sim | V56: Não
A57: BTG Pactual | B57: BTG Pactual Reference Tesouro Selic Prev FIRF RL | C57: 55.275.422/0001-61 | D57: BTG PACTUAL ASSET MANAGEMENT S/A DTVM | E57: 29.650.082/0001-00 | F57: BTG PACTUAL SERVICOS FINANCEIROS S.A. DISTRIBUIDOR | G57: Renda Fixa | H57: Renda Fixa | I57: 1000 | J57: 0.2 | M57: 0 | N57: 1 | P57: Curto Prazo | Q57: Não | R57: API interna | S57: 1 | T57: Não | U57: Sim | V57: Não
A58: BTG Pactual | B58: BTG Pactual Synergy Equity Hedge Prev FIE FIM RL | C58: 57.997.804/0001-24 | D58: BTG PACTUAL ASSET MANAGEMENT S/A DTVM | E58: 29.650.082/0001-00 | F58: BTG PACTUAL SERVICOS FINANCEIROS S.A. DISTRIBUIDOR | G58: Multimercado | H58: Renda Variável | I58: 0 | K58: 20 | L58: - | M58: 30 | N58: 32 | P58: Curto Prazo | Q58: Não | R58: API interna | S58: 1 | T58: Não | U58: Sim | V58: Não
A59: BTG Pactual | B59: BTG Pactual Synergy Long Only Prev FIE FIA RL | C59: 57.998.092/0001-68 | D59: BTG PACTUAL ASSET MANAGEMENT S/A DTVM | E59: 29.650.082/0001-00 | F59: BTG PACTUAL SERVICOS FINANCEIROS S.A. DISTRIBUIDOR | G59: Internacional | H59: Renda Variável | I59: 0 | J59: 2 | M59: 30 | N59: 32 | P59: Curto Prazo | Q59: Não | R59: API interna | S59: 1 | T59: Não | U59: Sim | V59: Não
A60: BTG Pactual | B60: BTG Pactual Tesouro Ipca Longo Prev FICFIRF de RF RL | C60: 27.762.397/0001-05 | D60: BTG PACTUAL ASSET MANAGEMENT S/A DTVM | E60: 29.650.082/0001-00 | F60: BTG PACTUAL SERVICOS FINANCEIROS S.A. DISTRIBUIDOR | G60: Renda Fixa | H60: Renda Fixa | I60: 1000 | J60: 0.75 | M60: 0 | N60: 1 | P60: Curto Prazo | Q60: Não | R60: API interna | S60: 1 | T60: Não | U60: Sim | V60: Não
A61: BTG Pactual | B61: BTG Pactual Tesouro Selic Prev FIRF Ref. DI RL | C61: 29.078.039/0001-03 | D61: BTG PACTUAL ASSET MANAGEMENT S/A DTVM | E61: 29.650.082/0001-00 | F61: BTG PACTUAL SERVICOS FINANCEIROS S.A. DISTRIBUIDOR | G61: Renda Fixa | H61: Renda Fixa | I61: 1000 | J61: 0 | M61: 0 | N61: 1 | P61: Curto Prazo | Q61: Não | R61: API interna | S61: 1 | T61: Não | U61: Sim | V61: Não
A62: BTG Pactual | B62: BTG Pactual Total Prev FICFIM RL | C62: 50.875.410/0001-54 | D62: BTG PACTUAL ASSET MANAGEMENT S/A DTVM | E62: 29.650.082/0001-00 | F62: BTG PACTUAL SERVICOS FINANCEIROS S.A. DISTRIBUIDOR | G62: Multimercado | H62: Multimercado | I62: 1000 | J62: 2 | K62: 20 | L62: CDI | M62: 7 | N62: 9 | P62: Curto Prazo | Q62: Não | R62: API interna | S62: 1 | T62: Não | U62: Sim | V62: Não
A63: BTG Pactual | B63: BTG Pactual Yield Prev FICFIM CrPr RL | C63: 20.997.959/0001-50 | D63: BTG PACTUAL ASSET MANAGEMENT S/A DTVM | E63: 29.650.082/0001-00 | F63: BTG PACTUAL SERVICOS FINANCEIROS S.A. DISTRIBUIDOR | G63: Multimercado | H63: Renda Fixa | I63: 1000 | J63: 0.55 | M63: 0 | N63: 1 | P63: Curto Prazo | Q63: Não | R63: API interna | S63: 1 | T63: Não | U63: Sim | V63: Não
A64: BTG Pactual | B64: Bradesco Maple Valor Prev FIC FIA Access | C64: 66.220.281/0001-04 | D64: BTG PACTUAL GESTÃO E CONSULTORIA DE INVESTIMENTOS LTDA | E64: 12.695.840/0001-03 | F64: BTG PACTUAL SERVICOS FINANCEIROS S.A. DISTRIBUIDOR | G64: Ações | H64: Renda Variável | I64: 0 | J64: 1.5 | K64: 20 | L64: - | M64: 3 | N64: 5 | P64: Curto Prazo | Q64: Não | R64: API interna | S64: 1 | T64: Não | U64: Sim | V64: Não
A65: BTG Pactual | B65: Bradesco Ultra Prev Access FICFIRF CrPr RL | C65: 47.564.878/0001-13 | D65: BTG PACTUAL GESTÃO E CONSULTORIA DE INVESTIMENTOS LTDA | E65: 12.695.840/0001-03 | F65: BTG PACTUAL SERVICOS FINANCEIROS S.A. DISTRIBUIDOR | G65: Renda Fixa | H65: Renda Fixa | I65: 1000 | K65: 6 | L65: CDI | M65: 5 | N65: 6 | P65: Curto Prazo | Q65: Não | R65: API interna | S65: 1 | T65: Não | U65: Sim | V65: Não
A66: BTG Pactual | B66: Brasil Capital 100 B Prev FICFIA RL | C66: 38.015.734/0001-17 | D66: BC GESTÃO DE RECURSOS LTDA | E66: 08.752.088/0001-00 | F66: BNY MELLON SERVICOS FINANCEIROS DTVM S/A | G66: Ações | H66: Renda Variável | I66: 1000 | J66: 2 | K66: 20 | L66: IBOVESPA | M66: 22 | N66: 24 | P66: Longo Prazo | Q66: Não | R66: API interna | S66: 1 | T66: Não | U66: Sim | V66: Não
A67: BTG Pactual | B67: Brasil Plural Cred Corp Icatu Prev FICFIRF CrPr RL | C67: 23.263.359/0001-57 | D67: PLURAL GESTÃO DE RECURSOS LTDA | E67: 11.397.672/0002-80 | F67: BNY MELLON SERVICOS FINANCEIROS DTVM S/A | G67: Renda Fixa | H67: Renda Fixa | I67: 3000 | J67: 0.8 | M67: 3 | N67: 4 | P67: Longo Prazo | Q67: Não | R67: API interna | S67: 1 | T67: Não | U67: Sim | V67: Não
A68: BTG Pactual | B68: Btgp Multi Acoes 100 Prev Fundo de Invstimento em Cotas de FICFIA RL | C68: 37.320.765/0001-19 | D68: BTG PACTUAL GESTÃO E CONSULTORIA DE INVESTIMENTOS LTDA | E68: 12.695.840/0001-03 | F68: BTG PACTUAL SERVICOS FINANCEIROS S.A. DISTRIBUIDOR | G68: Ações | H68: Renda Variável | I68: 1000 | J68: 0.5 | K68: 10 | L68: IPCA | M68: 60 | N68: 62 | P68: Curto Prazo | Q68: Não | R68: API interna | S68: 1 | T68: Não | U68: Sim | V68: Não
A69: BTG Pactual | B69: Btgp Multigestor Total Return Prev FICFIM CrPr RL | C69: 41.884.249/0001-94 | D69: BTG PACTUAL GESTÃO E CONSULTORIA DE INVESTIMENTOS LTDA | E69: 12.695.840/0001-03 | F69: BTG PACTUAL SERVICOS FINANCEIROS S.A. DISTRIBUIDOR | G69: Multimercado | H69: Multimercado | I69: 10000 | J69: 0.5 | K69: 10 | L69: CDI | M69: 30 | N69: 31 | P69: Curto Prazo | Q69: Não | R69: API interna | S69: 1 | T69: Não | U69: Sim | V69: Não
A70: BTG Pactual | B70: Butia Excellence Prev FICFIM RL | C70: 28.819.628/0001-32 | D70: BUTIÁ GESTÃO DE INVESTIMENTOS LTDA. | E70: 22.899.452/0001-90 | F70: BTG PACTUAL SERVICOS FINANCEIROS S.A. DISTRIBUIDOR | G70: Multimercado | H70: Alocação | I70: 0 | M70: 0 | N70: 3 | P70: Curto Prazo | Q70: Não | R70: API interna | S70: 1 | T70: Não | U70: Sim | V70: Não
A71: BTG Pactual | B71: Butia TOP Icatu SEG Prev FIRF CrPr RL | C71: 30.507.510/0001-10 | D71: BUTIÁ GESTÃO DE INVESTIMENTOS LTDA. | E71: 22.899.452/0001-90 | F71: BEM DISTRIBUIDORA DE TITULOS E VALORES MOBILIARIOS | G71: Renda Fixa | H71: Renda Fixa | I71: 3000 | J71: 0.5 | M71: 5 | N71: 7 | P71: Longo Prazo | Q71: Não | R71: API interna | S71: 1 | T71: Não | U71: Sim | V71: Não
A72: BTG Pactual | B72: Canvas Icatu Prev FICFIM Prev RL | C72: 24.405.282/0001-75 | D72: CANVAS CAPITAL S.A. | E72: 15.377.863/0001-50 | F72: INTRAG DISTR DE TITULOS EVALORES MOBILIARIOS LTDA | G72: Multimercado | H72: Multimercado | I72: 1500 | J72: 2 | M72: 0 | N72: 3 | P72: Não Aplicável | Q72: Não | R72: API interna | S72: 1 | T72: Não | U72: Sim | V72: Não
A73: BTG Pactual | B73: Capitania Prev BP FIRF CrPr RL | C73: 34.270.943/0001-56 | D73: CAPITANIA PREV S.A. | E73: 41.777.833/0001-40 | F73: BTG PACTUAL SERVICOS FINANCEIROS S.A. DISTRIBUIDOR | G73: Renda Fixa | H73: Renda Fixa | I73: 0 | M73: 5 | N73: 6 | P73: Curto Prazo | Q73: Não | R73: API interna | S73: 1 | T73: Não | U73: Sim | V73: Não
A74: BTG Pactual | B74: Clave Flex Prev FIE I FICFIM Access RL | C74: 54.494.538/0001-29 | D74: BTG PACTUAL GESTÃO E CONSULTORIA DE INVESTIMENTOS LTDA | E74: 12.695.840/0001-03 | F74: BTG PACTUAL SERVICOS FINANCEIROS S.A. DISTRIBUIDOR | G74: Multimercado | H74: Multimercado | I74: 0 | K74: 20 | L74: - | M74: 22 | N74: 24 | P74: Curto Prazo | Q74: Não | R74: API interna | S74: 1 | T74: Não | U74: Sim | V74: Não
A75: BTG Pactual | B75: Constellation 70 Prev FIM RL | C75: 29.550.612/0001-30 | D75: CONSTELLATION INVESTIMENTOS E PARTICIPAÇÕES LTDA | E75: 06.182.127/0001-55 | F75: BTG PACTUAL SERVICOS FINANCEIROS S.A. DISTRIBUIDOR | G75: Multimercado | H75: Renda Variável | I75: 5000 | K75: 20 | L75: CDI | M75: 6 | N75: 8 | P75: Curto Prazo | Q75: Não | R75: API interna | S75: 1 | T75: Não | U75: Sim | V75: Não
A76: BTG Pactual | B76: Constellation BP 100 Prev FICFIA | C76: 43.619.032/0001-82 | D76: CONSTELLATION INVESTIMENTOS E PARTICIPAÇÕES LTDA | E76: 06.182.127/0001-55 | F76: BTG PACTUAL SERVICOS FINANCEIROS S.A. DISTRIBUIDOR | G76: Ações | H76: Renda Variável | I76: 0 | M76: 40 | N76: 42 | P76: Renda Variável | Q76: Não | R76: API interna | S76: 1 | T76: Não | U76: Sim | V76: Não
A77: BTG Pactual | B77: Daemon Ethos Icatu Prev IQ FIE FICFIM | C77: 50.698.062/0001-97 | D77: DAEMON INVESTIMENTOS LTDA. | E77: 10.865.161/0001-00 | F77: BNY MELLON SERVICOS FINANCEIROS DISTRIBUIDORA DE T | G77: Multimercado | H77: Multimercado | I77: 5000 | J77: 1.5 | K77: 20 | L77: - | M77: 7 | N77: 10 | P77: Longo Prazo | Q77: Sim | R77: API interna | S77: 1 | T77: Não | U77: Sim | V77: Não
A78: BTG Pactual | B78: Dahlia 100 Prev FICFIM RL | C78: 37.128.109/0001-19 | D78: DAHLIA CAPITAL GESTÃO DE RECURSOS LTDA. | E78: 09.551.766/0001-39 | F78: BNY MELLON SERVICOS FINANCEIROS DTVM S/A | G78: Multimercado | H78: Renda Variável | I78: 0 | J78: 1.85 | K78: 20 | L78: IBX | M78: 10 | N78: 12 | P78: Longo Prazo | Q78: Não | R78: API interna | S78: 1 | T78: Não | U78: Sim | V78: Não
A79: BTG Pactual | B79: Dahlia BP Prev Total Return 70 FICFIM RL | C79: 47.212.505/0001-83 | D79: DAHLIA CAPITAL GESTÃO DE RECURSOS LTDA. | E79: 09.551.766/0001-39 | F79: INTRAG DISTR DE TITULOS EVALORES MOBILIARIOS LTDA | G79: Multimercado | H79: Renda Variável | I79: 1000 | J79: 1.65 | K79: 20 | L79: - | M79: 7 | N79: 9 | P79: Longo Prazo | Q79: Não | R79: API interna | S79: 1 | T79: Não | U79: Sim | V79: Não
A80: BTG Pactual | B80: Dahlia Global 50 Prev FICFIM RL | C80: 37.626.895/0001-84 | D80: DAHLIA CAPITAL GESTÃO DE RECURSOS LTDA. | E80: 09.551.766/0001-39 | F80: BNY MELLON SERVICOS FINANCEIROS DTVM S/A | G80: Multimercado | H80: Multimercado | I80: 0 | J80: 1.1 | K80: 15 | L80: CDI | M80: 7 | N80: 9 | P80: Longo Prazo | Q80: Não | R80: API interna | S80: 1 | T80: Não | U80: Sim | V80: Não
A81: BTG Pactual | B81: Dahlia Total Return BP Prev FICFIM RL | C81: 53.675.501/0001-34 | D81: DAHLIA CAPITAL GESTÃO DE RECURSOS LTDA. | E81: 09.551.766/0001-39 | F81: BTG PACTUAL SERVICOS FINANCEIROS S.A. DISTRIBUIDOR | G81: Multimercado | H81: Renda Variável | I81: 1000 | J81: 0.75 | M81: 7 | N81: 9 | P81: Curto Prazo | Q81: Não | R81: API interna | S81: 1 | T81: Não | U81: Sim | V81: Não
A82: BTG Pactual | B82: Empiricus Cripto Prev 20 FIM RL | C82: 44.027.398/0001-25 | D82: BTG PACTUAL ASSET MANAGEMENT S/A DTVM | E82: 29.650.082/0001-00 | F82: BTG PACTUAL SERVICOS FINANCEIROS S.A. DISTRIBUIDOR | G82: Multimercado | H82: Alternativos | I82: 1000 | M82: 7 | N82: 9 | P82: Curto Prazo | Q82: Não | R82: API interna | S82: 1 | T82: Não | U82: Sim | V82: Não
A83: BTG Pactual | B83: Empiricus FoF Nova Superprevidencia Prev FIM RL | C83: 44.027.199/0001-17 | D83: BTG PACTUAL GESTÃO E CONSULTORIA DE INVESTIMENTOS LTDA | E83: 12.695.840/0001-03 | F83: BTG PACTUAL SERVICOS FINANCEIROS S.A. DISTRIBUIDOR | G83: Multimercado | H83: Alocação | I83: 1000 | J83: 0.75 | M83: 5 | N83: 7 | P83: Curto Prazo | Q83: Não | R83: API interna | S83: 1 | T83: Não | U83: Sim | V83: Não
A84: BTG Pactual | B84: Empiricus FoF Super Prev Yield FIM CrPr RL | C84: 55.169.143/0001-13 | D84: BTG PACTUAL GESTÃO E CONSULTORIA DE INVESTIMENTOS LTDA | E84: 12.695.840/0001-03 | F84: BTG PACTUAL SERVICOS FINANCEIROS S.A. DISTRIBUIDOR | G84: Multimercado | H84: Alocação | I84: 1000 | J84: 0.3 | K84: 10 | L84: - | M84: 8 | N84: 10 | P84: Curto Prazo | Q84: Não | R84: API interna | S84: 1 | T84: Não | U84: Sim | V84: Não
A85: BTG Pactual | B85: Empiricus FoF Superprevidencia Acoes Icatu FIA RL | C85: 35.844.969/0001-23 | D85: BTG PACTUAL GESTÃO E CONSULTORIA DE INVESTIMENTOS LTDA | E85: 12.695.840/0001-03 | F85: BEM DISTRIBUIDORA DE TITULOS E VALORES MOBILIARIOS | G85: Multimercado | H85: Renda Variável | I85: 1000 | J85: 0.75 | K85: 10 | L85: IBOVESPA | M85: 42 | N85: 43 | P85: Longo Prazo | Q85: Não | R85: API interna | S85: 1 | T85: Não | U85: Sim | V85: Não
A86: BTG Pactual | B86: Empiricus FoF Superprevidencia Arrojado Icatu Prev FIM RL | C86: 33.269.222/0001-63 | D86: BTG PACTUAL GESTÃO E CONSULTORIA DE INVESTIMENTOS LTDA | E86: 12.695.840/0001-03 | F86: BTG PACTUAL SERVICOS FINANCEIROS S.A. DISTRIBUIDOR | G86: Multimercado | H86: Renda Variável | I86: 1000 | J86: 0.75 | M86: 5 | N86: 7 | P86: Curto Prazo | Q86: Não | R86: API interna | S86: 1 | T86: Não | U86: Sim | V86: Não
A87: BTG Pactual | B87: Empiricus FoF Superprevidencia Conservador Icatu FIRF Prev RL | C87: 33.884.185/0001-01 | D87: BTG PACTUAL GESTÃO E CONSULTORIA DE INVESTIMENTOS LTDA | E87: 12.695.840/0001-03 | F87: BTG PACTUAL SERVICOS FINANCEIROS S.A. DISTRIBUIDOR | G87: Renda Fixa | H87: Renda Fixa | I87: 1000 | J87: 0.3 | M87: 5 | N87: 7 | P87: Curto Prazo | Q87: Não | R87: API interna | S87: 1 | T87: Não | U87: Sim | V87: Não
A88: BTG Pactual | B88: Empiricus FoF Superprevidencia Multimercados Icatu Prev FIM RL | C88: 47.350.604/0001-21 | D88: BTG PACTUAL GESTÃO E CONSULTORIA DE INVESTIMENTOS LTDA | E88: 12.695.840/0001-03 | F88: BTG PACTUAL SERVICOS FINANCEIROS S.A. DISTRIBUIDOR | G88: Multimercado | H88: Multimercado | I88: 1000 | J88: 0.75 | K88: 10 | L88: - | M88: 5 | N88: 7 | P88: Curto Prazo | Q88: Não | R88: API interna | S88: 1 | T88: Não | U88: Sim | V88: Não
A89: BTG Pactual | B89: Empiricus Global Real Return Prev FIM RL | C89: 44.027.256/0001-68 | D89: BTG PACTUAL ASSET MANAGEMENT S/A DTVM | E89: 29.650.082/0001-00 | F89: BTG PACTUAL SERVICOS FINANCEIROS S.A. DISTRIBUIDOR | G89: Multimercado | H89: Multimercado | I89: 1000 | M89: 7 | N89: 9 | P89: Curto Prazo | Q89: Não | R89: API interna | S89: 1 | T89: Não | U89: Sim | V89: Não
A90: BTG Pactual | B90: Empiricus Icatu Carteira Universa Prev FIM CrPr RL | C90: 36.517.971/0001-50 | D90: BTG PACTUAL ASSET MANAGEMENT S/A DTVM | E90: 29.650.082/0001-00 | F90: BEM DISTRIBUIDORA DE TITULOS E VALORES MOBILIARIOS | G90: Multimercado | H90: Multimercado | I90: 1000 | J90: 1.25 | K90: 15 | L90: CDI | M90: 42 | N90: 43 | P90: Longo Prazo | Q90: Não | R90: API interna | S90: 1 | T90: Não | U90: Sim | V90: Não
A91: BTG Pactual | B91: Empiricus Oportunidades de UMA Vida Prev FIA RL | C91: 44.026.984/0001-55 | D91: BTG PACTUAL ASSET MANAGEMENT S/A DTVM | E91: 29.650.082/0001-00 | F91: BTG PACTUAL SERVICOS FINANCEIROS S.A. DISTRIBUIDOR | G91: Ações | H91: Renda Variável | I91: 1000 | J91: 1.4 | K91: 20 | L91: - | M91: 7 | N91: 9 | P91: Renda Variável | Q91: Não | R91: API interna | S91: 1 | T91: Não | U91: Sim | V91: Não
A92: BTG Pactual | B92: Encore Long Bias BTG Prev 100 Prev FICFIM Access RL | C92: 51.389.615/0001-92 | D92: BTG PACTUAL GESTÃO E CONSULTORIA DE INVESTIMENTOS LTDA | E92: 12.695.840/0001-03 | F92: BTG PACTUAL SERVICOS FINANCEIROS S.A. DISTRIBUIDOR | G92: Multimercado | H92: Renda Variável | I92: 1000 | M92: 20 | N92: 22 | P92: Curto Prazo | Q92: Não | R92: API interna | S92: 1 | T92: Não | U92: Sim | V92: Não
A93: BTG Pactual | B93: Encore Valor Dividendos 100 BP Prev FIC FIA Access | C93: 68.171.753/0001-01 | D93: BTG PACTUAL GESTÃO E CONSULTORIA DE INVESTIMENTOS LTDA | E93: 12.695.840/0001-03 | F93: BTG PACTUAL SERVICOS FINANCEIROS S.A. DISTRIBUIDOR | G93: Ações | H93: Renda Variável | I93: 1000 | J93: 2 | K93: 20 | L93: - | M93: 30 | N93: 32 | P93: Renda Variável | Q93: Não | R93: API interna | S93: 1 | T93: Não | U93: Sim | V93: Não
A94: BTG Pactual | B94: Equitas Prev II Icatu FICFIA RL | C94: 35.354.896/0001-91 | D94: DRYS CAPITAL LTDA | E94: 08.204.817/0001-93 | F94: INTRAG DISTR DE TITULOS EVALORES MOBILIARIOS LTDA | G94: Ações | H94: Renda Variável | I94: 5000 | J94: 2 | K94: 20 | L94: IBOVESPA | M94: 22 | N94: 24 | P94: Renda Variável | Q94: Não | R94: API interna | S94: 1 | T94: Não | U94: Sim | V94: Não
A95: BTG Pactual | B95: Exes Prev FIE FICFIM CrPr RL | C95: 42.730.600/0001-55 | D95: EXES GESTORA DE RECURSOS LTDA. | E95: 31.960.567/0001-33 | F95: BTG PACTUAL SERVICOS FINANCEIROS S.A. DISTRIBUIDOR | G95: Multimercado | H95: Renda Fixa | I95: 5000 | M95: 179 | N95: 180 | P95: Curto Prazo | Q95: Não | R95: API interna | S95: 1 | T95: Não | U95: Sim | V95: Não
A96: BTG Pactual | B96: Exes Prev II FIE FIM CrPr RL | C96: 60.859.486/0001-40 | D96: EXES GESTORA DE RECURSOS LTDA. | E96: 31.960.567/0001-33 | F96: BTG PACTUAL SERVICOS FINANCEIROS S.A. DISTRIBUIDOR | G96: Multimercado | H96: Renda Fixa | I96: 1000 | M96: 9 | N96: 10 | P96: Curto Prazo | Q96: Não | R96: API interna | S96: 1 | T96: Não | U96: Sim | V96: Não
A97: BTG Pactual | B97: Finacap BP Prev 70 FIF MM | C97: 67.671.091/0001-68 | D97: FINACAP INVESTIMENTOS LTDA | E97: 01.294.929/0001-33 | F97: BTG PACTUAL SERVICOS FINANCEIROS S.A. DISTRIBUIDOR | G97: Multimercado | H97: Renda Variável | I97: 1000 | M97: 3 | N97: 6 | P97: Longo Prazo | Q97: Não | R97: API interna | S97: 1 | T97: Não | U97: Sim | V97: Não
A98: BTG Pactual | B98: Forpus 100 Icatu Prev Qual FICFIA RL | C98: 38.281.397/0001-00 | D98: FORPUS CAPITAL GESTÃO DE RECURSOS LTDA. | E98: 21.018.289/0001-46 | F98: BNY MELLON SERVICOS FINANCEIROS DTVM S/A | G98: Ações | H98: Renda Variável | I98: 5000 | J98: 2 | K98: 20 | L98: IMA-B | M98: 8 | N98: 10 | P98: Indefinido | Q98: Não | R98: API interna | S98: 1 | T98: Não | U98: Sim | V98: Não
A99: BTG Pactual | B99: Forpus 70 Prev FIM RL | C99: 34.474.917/0001-40 | D99: FORPUS CAPITAL GESTÃO DE RECURSOS LTDA. | E99: 21.018.289/0001-46 | F99: BNY MELLON SERVICOS FINANCEIROS DTVM S/A | G99: Multimercado | H99: Renda Variável | I99: 1000 | J99: 2 | K99: 20 | L99: CDI | M99: 8 | N99: 10 | P99: Longo Prazo | Q99: Não | R99: API interna | S99: 1 | T99: Não | U99: Sim | V99: Não
A100: BTG Pactual | B100: Genoa Capital Cruise Prev BTG FICFIM RL | C100: 42.535.251/0001-10 | D100: GENOA CAPITAL GESTORA DE RECURSOS LTDA | E100: 34.276.448/0001-54 | F100: INTRAG DISTR DE TITULOS EVALORES MOBILIARIOS LTDA | G100: Multimercado | H100: Multimercado | I100: 1000 | J100: 2 | K100: 20 | L100: CDI | M100: 5 | N100: 7 | P100: Longo Prazo | Q100: Não | R100: API interna | S100: 1 | T100: Não | U100: Sim | V100: Não
...

Sheet Itaú Private
A1: Plataforma | B1: Fundo | C1: CNPJ | D1: Gestora | E1: CNPJ da gestora | F1: Administrador | G1: Classe | H1: Categoria na origem | I1: Aplicação mínima (R$) | J1: Taxa adm (%) | K1: Taxa perf (%) | L1: Benchmark | M1: Cotização resgate (D+) | N1: Líquidação resgate (D+) | O1: Carência (dias) | P1: Tributação | Q1: Fechado p/ captação | R1: Fontes | S1: Nº de fontes | T1: Open Finance | U1: Prateleira (site) | V1: Área logada | W1: Link
A2: Itaú Private | B2: Canvas Enduro Prev PVT MM | D2: CANVAS CAPITAL S.A. | G2: Multimercado | H2: Multimercados | J2: 2 | Q2: Não | R2: Site (HTML) | S2: 1 | T2: Não | U2: Sim | V2: Não
A3: Itaú Private | B3: Flexprev CP Ativo II | G3: Multimercado | H3: PREVIDÊNCIA - Renda Fixa | Q3: Sim | R3: Site (HTML) | S3: 1 | T3: Não | U3: Sim | V3: Não
A4: Itaú Private | B4: Flexprev Private DI | G4: Renda Fixa | H4: Juros Pós-Fixados | J4: 1 | Q4: Sim | R4: Site (HTML) | S4: 1 | T4: Não | U4: Sim | V4: Não
A5: Itaú Private | B5: Itau Private Prev Kinea Rf | D5: ITAU UNIBANCO S.A. | G5: Renda Fixa | H5: Juros Pós-Fixados | J5: 0.8 | Q5: Não | R5: Site (HTML) | S5: 1 | T5: Não | U5: Sim | V5: Não
A6: Itaú Private | B6: Itau Private Prev Kinea XTR | D6: ITAU UNIBANCO S.A. | G6: Renda Fixa | H6: Multimercados | J6: 2 | Q6: Sim | R6: Site (HTML) | S6: 1 | T6: Não | U6: Sim | V6: Não
A7: Itaú Private | B7: Itaú Prev Verde MM | D7: ITAU UNIBANCO S.A. | G7: Multimercado | H7: Multimercados | J7: 2 | Q7: Sim | R7: Site (HTML) | S7: 1 | T7: Não | U7: Sim | V7: Não
A8: Itaú Private | B8: Kinea Prev Credito Privado | G8: Renda Fixa | H8: Juros Pós-Fixados | J8: 0.6 | Q8: Sim | R8: Site (HTML) | S8: 1 | T8: Não | U8: Sim | V8: Não
A9: Itaú Private | B9: Kinea XTR II Prev PVT MM | G9: Multimercado | H9: Multimercados | J9: 1.5 | Q9: Sim | R9: Site (HTML) | S9: 1 | T9: Não | U9: Sim | V9: Não
A10: Itaú Private | B10: PRIVATE PREV TRUXT ACOES | G10: Ações | H10: Multimercados | J10: 3 | Q10: Não | R10: Site (HTML) | S10: 1 | T10: Não | U10: Sim | V10: Não
A11: Itaú Private | B11: Platinum III | D11: PLATINUM CAPITAL GESTÃO DE RECURSOS LTDA. | G11: Renda Fixa | H11: Juros Prefixados | J11: 0.6 | Q11: Não | R11: Site (HTML) | S11: 1 | T11: Não | U11: Sim | V11: Não
A12: Itaú Private | B12: Private Juro Real Target 2026 II | G12: Renda Fixa | H12: Inflação | J12: 0.5 | Q12: Não | R12: Site (HTML) | S12: 1 | T12: Não | U12: Sim | V12: Não
A13: Itaú Private | B13: Private Juro Real Target 2030 II | G13: Renda Fixa | H13: Inflação | J13: 0.5 | Q13: Não | R13: Site (HTML) | S13: 1 | T13: Não | U13: Sim | V13: Não
A14: Itaú Private | B14: Private Juro Real Target 2035 II | G14: Renda Fixa | H14: Inflação | J14: 0.5 | Q14: Não | R14: Site (HTML) | S14: 1 | T14: Não | U14: Sim | V14: Não
A15: Itaú Private | B15: Private Juro Real Target II 2024 | G15: Renda Fixa | H15: Inflação | J15: 0.5 | Q15: Não | R15: Site (HTML) | S15: 1 | T15: Não | U15: Sim | V15: Não
A16: Itaú Private | B16: Private Kinea Multimercado | G16: Multimercado | H16: Multimercados | J16: 1.5 | Q16: Sim | R16: Site (HTML) | S16: 1 | T16: Não | U16: Sim | V16: Não
A17: Itaú Private | B17: Private Prev Absolute MM | G17: Multimercado | H17: Multimercados | J17: 2 | Q17: Não | R17: Site (HTML) | S17: 1 | T17: Não | U17: Sim | V17: Não
A18: Itaú Private | B18: Private Prev Active Fix | G18: Renda Fixa | H18: Juros Pós-Fixados | J18: 0.5 | Q18: Não | R18: Site (HTML) | S18: 1 | T18: Não | U18: Sim | V18: Não
A19: Itaú Private | B19: Private Prev Adam MM VGBL | G19: Renda Fixa | H19: Multimercados | J19: 2 | Q19: Não | R19: Site (HTML) | S19: 1 | T19: Não | U19: Sim | V19: Não
A20: Itaú Private | B20: Private Prev Ativo RF | G20: Renda Fixa | H20: PREVIDÊNCIA - Renda Fixa | J20: 1.25 | Q20: Não | R20: Site (HTML) | S20: 1 | T20: Não | U20: Sim | V20: Não
A21: Itaú Private | B21: Private Prev Dinamico Crédito Privado | G21: Multimercado | H21: PREVIDÊNCIA - Renda Fixa | J21: 1 | Q21: Sim | R21: Site (HTML) | S21: 1 | T21: Não | U21: Sim | V21: Não
A22: Itaú Private | B22: Private Prev Dunamis Ações | G22: Multimercado | H22: Ações | J22: 2 | Q22: Sim | R22: Site (HTML) | S22: 1 | T22: Não | U22: Sim | V22: Não
A23: Itaú Private | B23: Private Prev High Yield | G23: Multimercado | H23: Juros Pós-Fixados | J23: 0.6 | Q23: Sim | R23: Site (HTML) | S23: 1 | T23: Não | U23: Sim | V23: Não
... A28: Itaú Private | B28: Private Prev Multigestor | G28: Multimercado | H28: Multimercados | J28: 0.75 | Q28: Não | R28: Site (HTML) | S28: 1 | T28: Não | U28: Sim | V28: Não
A29: Itaú Private | B29: Private Prev NTN-B 2024 | G29: Renda Fixa | H29: PREVIDÊNCIA - Renda Fixa | Q29: Não | R29: Site (HTML) | S29: 1 | T29: Não | U29: Sim | V29: Não
A30: Itaú Private | B30: Private Prev NTN-B 2030 | G30: Renda Fixa | H30: PREVIDÊNCIA - Renda Fixa | Q30: Não | R30: Site (HTML) | S30: 1 | T30: Não | U30: Sim | V30: Não
A31: Itaú Private | B31: Private Prev NTNB Ultra 2023 | G31: Renda Fixa | H31: Inflação | J31: 0.5 | Q31: Sim | R31: Site (HTML) | S31: 1 | T31: Não | U31: Sim | V31: Não
A32: Itaú Private | B32: Private Prev NTNB Ultra 2024 | G32: Renda Fixa | H32: Inflação | J32: 0.5 | Q32: Sim | R32: Site (HTML) | S32: 1 | T32: Não | U32: Sim | V32: Não
A33: Itaú Private | B33: Private Prev PERFIL 2 II | G33: Multimercado | H33: Multimercados | J33: 0.6 | Q33: Sim | R33: Site (HTML) | S33: 1 | T33: Não | U33: Sim | V33: Não
A34: Itaú Private | B34: Private Prev Perfil 2 | G34: Multimercado | H34: Multimercados | J34: 0.8 | Q34: Sim | R34: Site (HTML) | S34: 1 | T34: Não | U34: Sim | V34: Não
A35: Itaú Private | B35: Private Prev Perfil 3 | G35: Multimercado | H35: Multimercados | J35: 1 | Q35: Sim | R35: Site (HTML) | S35: 1 | T35: Não | U35: Sim | V35: Não
A36: Itaú Private | B36: Private Prev Premium II | G36: Renda Fixa | H36: Juros Prefixados | J36: 0.6 | Q36: Não | R36: Site (HTML) | S36: 1 | T36: Não | U36: Sim | V36: Não
A37: Itaú Private | B37: Private Prev Pré Fixado Ultra | G37: Renda Fixa | H37: Juros Prefixados | J37: 0.6 | Q37: Não | R37: Site (HTML) | S37: 1 | T37: Não | U37: Sim | V37: Não
A38: Itaú Private | B38: Private Prev RF | G38: Renda Fixa | H38: PREVIDÊNCIA - Renda Fixa | J38: 0.8 | Q38: Não | R38: Site (HTML) | S38: 1 | T38: Não | U38: Sim | V38: Não
A39: Itaú Private | B39: Private Prev Rf Vision Plus | G39: Multimercado | H39: Juros Prefixados | J39: 0.6 | Q39: Não | R39: Site (HTML) | S39: 1 | T39: Não | U39: Sim | V39: Não
A40: Itaú Private | B40: Private Prev SPX Lancer MM | G40: Multimercado | H40: Multimercados | J40: 2 | Q40: Não | R40: Site (HTML) | S40: 1 | T40: Não | U40: Sim | V40: Não
A41: Itaú Private | B41: Private Prev Ultra NTN-B 2030 | G41: Renda Fixa | H41: PREVIDÊNCIA - Renda Fixa | Q41: Não | R41: Site (HTML) | S41: 1 | T41: Não | U41: Sim | V41: Não
A42: Itaú Private | B42: Private Prev Vision Plus MM | G42: Renda Fixa | H42: Multimercados | J42: 2 | Q42: Não | R42: Site (HTML) | S42: 1 | T42: Não | U42: Sim | V42: Não

Sheet Fontes
A1: Plataforma | B1: Fonte | C1: Fundos trazidos | D1: Só nesta fonte | E1: Total da casa (união) | F1: % do total
A2: XP Investimentos | B2: Site (navegador) | C2: 223 | D2: 223 | E2: 223 | F2: =IF($E2=0,0,$C2/$E2)
A3: BTG Pactual | B3: API interna | C3: 226 | D3: 226 | E3: 226 | F3: =IF($E3=0,0,$C3/$E3)
A4: Itaú Private | B4: Site (HTML) | C4: 41 | D4: 41 | E4: 41 | F4: =IF($E4=0,0,$C4/$E4)
A6: "Fundos trazidos" é quanto aquela fonte devolveu sozinha; a soma pode passar do total
A7: da casa, porque o mesmo fundo costuma aparecer em mais de uma fonte.
A8: "Só nesta fonte" é o que se perderia desligando aquela coleta - o número que decide
A9: se manter o scraping de uma casa compensa o tempo que ele custa.

Sheet Captação por casa
A1: Captação dos fundos de vitrine - por casa
A2: Fonte | B2: Informe diário da CVM (INF_DIARIO) | C2: https://dados.cvm.gov.br/dataset/fi-doc-inf_diario
A3: Período | B3: de 01/07/2026 a 22/09/2026
A4: Competências | B4: 3 (jul/2026 a set/2026)
A5: A CVM publica fluxo por FUNDO, nunca por distribuidor: os números por casa são o fluxo dos fundos que ela exibe, no mercado inteiro. Movimento estrutural fica fora de todas as somas.
A7: Captação líquida dos fundos da vitrine de 01/07/2026 a 22/09/2026: XP Investimentos -R$ 31 mi (-0,04% do PL de início), BTG Pactual +R$ 989 mi (+1,97%). Maior captação entre as casas: BTG Pactual.
A8: Por família de ativo, a diferença entre XP Investimentos e BTG Pactual (-R$ 1,0 bi) vem de Multimercados (-R$ 878 mi) e Renda Fixa (-R$ 145 mi).
A10: De onde vem o saldo
A11: Casa | B11: Fundos na vitrine | C11: Fundos com informe | D11: Captação líquida (R$) | E11: PL de início (R$) | F11: Captação / PL de início (%)
A12: BTG Pactual | B12: 226 | C12: 226 | D12: 9.885253e+08 | E12: 5.0193947e+10 | F12: 1.969
A13: XP Investimentos | B13: 218 | C13: 214 | D13: -31209743 | E13: 7.5234026e+10 | F13: -0.041
A14: Sem o corte produto próprio x terceiros: o gestor registrado do fundo que a casa vende é a seguradora ou a asset dela, não o dono da estratégia: em 23/09, 88 dos 118 fundos que a regra chamaria de produto próprio da XP tinham como gestor a XP Vida e Previdência (Kinea, AZ Quest, Kapitalo), e os FICs de Absolute e Kapitalo no BTG, a BTG Pactual Gestão e Consultoria.
A16: Por família de ativo
A17: Família | B17: BTG Pactual (R$) | C17: XP Investimentos (R$) | D17: Todas as vitrines (R$) | E17: Fundos no universo
A18: Renda Fixa | B18: 1.1165274e+09 | C18: 9.717932e+08 | D18: 2.0889618e+09 | E18: 129
A19: Balanceados | B19: -5544864.4 | C19: 2885017.2 | D19: -2659847.2 | E19: 3
A20: Ações | B20: -12841817 | C20: -18229965 | D20: -31071782 | E20: 40
A21: Multimercados | B21: -1.0961539e+08 | C21: -9.87658e+08 | D21: -1.0972734e+09 | E21: 262
A23: Tendência dos fundos, por casa
A24: Casa | B24: acelerando | C24: desacelerando | D24: virou entrada | E24: virou saída | F24: saída persistente | G24: estável | H24: sem série | I24: Total
A25: BTG Pactual | B25: 34 | C25: 35 | D25: 38 | E25: 17 | F25: 84 | G25: 12 | H25: 1 | I25: 221
A26: XP Investimentos | B26: 27 | C26: 15 | D26: 26 | E26: 15 | F26: 111 | G26: 15 | H26: 2 | I26: 211
A28: acelerando | B28: captando mais por dia que nos meses anteriores
A29: desacelerando | B29: ainda captando, mas menos por dia que antes
A30: virou entrada | B30: estava perdendo dinheiro e passou a captar
A31: virou saída | B31: estava captando e passou a perder dinheiro
A32: saída persistente | B32: perdendo dinheiro no último mês e na média anterior
A33: estável | B33: sem mudança material no ritmo
A34: sem série | B34: competências de menos para falar em tendência

Sheet Captação por fundo
A1: Captação dos fundos de vitrine
A2: Fonte | B2: Informe diário da CVM (INF_DIARIO) | C2: https://dados.cvm.gov.br/dataset/fi-doc-inf_diario
A3: Período | B3: de 01/07/2026 a 22/09/2026
A4: Competências | B4: 3 (jul/2026 a set/2026)
A5: A CVM publica fluxo por FUNDO, nunca por distribuidor: um fundo em três vitrines entra inteiro nas três somas. Uma linha do informe é uma SUBCLASSE: PL, cotistas e fluxo somam as subclasses da classe, e a rentabilidade é a média dos retornos delas ponderada pelo PL. Rentabilidade é da cota patrimonial, ex-provento, com base no PRIMEIRO PREGÃO do período - as abas 'Rentabilidade 12 meses' e 'Rentabilidade por fundo' usam a cota do fim da competência anterior, que é a convenção de lâmina, e por isso o mesmo fundo aparece com número ligeiramente diferente nelas.
A7: Fundo | B7: CNPJ | C7: Classe | D7: Gestora | E7: Vitrines | F7: Captação bruta (R$) | G7: Resgates (R$) | H7: Captação líquida (R$) | I7: PL início (R$) | J7: PL fim (R$) | K7: Captação líquida / PL início (%) | L7: Rentabilidade no período, base no 1o pregão (%) | M7: Pregões observados | N7: Tendência | O7: Movimento estrutural
A8: BTG Pactual Cred Corp Plus Prev FIE FICFIM CrPr RL | B8: 41.801.819/0001-35 | C8: Renda Fixa | D8: BTG PACTUAL ASSET MANAGEMENT S/A DTVM | E8: btg | F8: 8.2118468e+08 | G8: 47618228 | H8: 7.7356645e+08 | I8: 4.0292593e+08 | J8: 1.1982832e+09 | K8: 191.99 | L8: 3.19 | M8: 59 | N8: desacelerando
A9: Mag Cash Xp Seg Prev Ficfirf Rl | B9: 58.543.779/0001-71 | C9: Renda Fixa | D9: MONGERAL AEGON INVESTIMENTOS LTDA | E9: xp | F9: 5.3924062e+08 | G9: 65544024 | H9: 4.7369659e+08 | I9: 1.0623736e+09 | J9: 1.5723595e+09 | K9: 44.59 | L9: 3.14 | M9: 59 | N9: estável
A10: BTG Pactual Tesouro Selic Prev FIRF Ref. DI RL | B10: 29.078.039/0001-03 | C10: Renda Fixa | D10: BTG PACTUAL ASSET MANAGEMENT S/A DTVM | E10: btg | F10: 9.9877346e+08 | G10: 6.0151784e+08 | H10: 3.9725562e+08 | I10: 6.4367286e+09 | J10: 7.034273e+09 | K10: 6.17 | L10: 3.08 | M10: 59 | N10: acelerando
A11: Trend Pós-Fixado XP Seg Prev FIC FIRF | B11: 33.784.231/0001-92 | C11: Renda Fixa | D11: XP VISTA ASSET MANAGEMENT LTDA. | E11: xp | F11: 9.4362857e+08 | G11: 5.4941899e+08 | H11: 3.9420958e+08 | I11: 6.5967033e+09 | J11: 7.1854748e+09 | K11: 5.98 | L11: 3.02 | M11: 59 | N11: desacelerando
A12: JGP Crédito Prev Advisory XP Seg FIC RF CP | B12: 32.319.225/0001-00 | C12: Renda Fixa | D12: LETO ASSET MANAGEMENT LTDA | E12: xp | F12: 4.6559002e+08 | G12: 1.5143205e+08 | H12: 3.1415797e+08 | I12: 3.3687935e+09 | J12: 3.7902701e+09 | K12: 9.33 | L12: 3.07 | M12: 59 | N12: estável
A13: Artesanal Prev FIM RL | B13: 53.497.497/0001-61 | C13: Multimercados | D13: ARTESANAL INVESTIMENTOS LTDA | E13: btg | F13: 3.126825e+08 | G13: 63404907 | H13: 2.4927759e+08 | I13: 1.0882274e+09 | J13: 1.3698032e+09 | K13: 22.91 | L13: 3.07 | M13: 59 | N13: estável
A14: Tyton Credito Prev FIM CrPr RL | B14: 53.847.333/0001-17 | C14: Multimercados | D14: TYTON CAPITAL INVESTIMENTOS LTDA. | E14: btg | F14: 2.6276965e+08 | G14: 17810858 | H14: 2.4495879e+08 | I14: 5.3320959e+08 | J14: 7.9856617e+08 | K14: 45.94 | L14: 3.29 | M14: 59 | N14: estável
A15: Icatu Vanguarda Dinâmico Cdi Xp Seg Fim Crédito Rl | B15: 53.990.541/0001-70 | C15: Multimercados | D15: ICATU VANGUARDA GESTÃO DE RECURSOS LTDA | E15: xp | F15: 1.7266809e+08 | G15: 15942793 | H15: 1.567253e+08 | I15: 4.7208894e+08 | J15: 6.4285798e+08 | K15: 33.2 | L15: 3 | M15: 59 | N15: estável
A16: XP Crédito Estruturado XP Seg Prev FIC FIRF | B16: 36.352.610/0001-00 | C16: Renda Fixa | D16: XP VIDA E PREVIDÊNCIA S.A. | E16: xp | F16: 2.1647446e+08 | G16: 71298489 | H16: 1.4517597e+08 | I16: 8.1535724e+08 | J16: 9.8341204e+08 | K16: 17.81 | L16: 2.99 | M16: 58 | N16: desacelerando
A17: Patria Previdenciário XP Seg FIC MM CP RL | B17: 53.990.084/0001-14 | C17: Multimercados | D17: PÁTRIA INVESTIMENTOS LTDA. | E17: xp | F17: 1.4272419e+08 | G17: 1739058.8 | H17: 1.4098513e+08 | I17: 2.5726906e+08 | J17: 4.0529942e+08 | K17: 54.8 | L17: 3.13 | M17: 58 | N17: estável
A18: Xp Liquidez 50 Firf Rl | B18: 52.986.302/0001-84 | C18: Renda Fixa | D18: XP VISTA ASSET MANAGEMENT LTDA. | E18: xp | F18: 2.4886442e+08 | G18: 1.1356739e+08 | H18: 1.3529703e+08 | I18: 9.2597676e+08 | J18: 1.0885912e+09 | K18: 14.61 | L18: 3.06 | M18: 59 | N18: estável
A19: BTG CDB Plus Prev FIM CrPr RL | B19: 47.564.915/0001-93 | C19: Multimercados | D19: BTG PACTUAL ASSET MANAGEMENT S/A DTVM | E19: btg | F19: 2.8290742e+08 | G19: 1.484172e+08 | H19: 1.3449023e+08 | I19: 1.9594007e+09 | J19: 2.1547077e+09 | K19: 6.86 | L19: 3.06 | M19: 59 | N19: desacelerando
... A66: ARX Denali Prev FIRF Access CrPr RL | B66: 47.564.808/0001-65 | C66: Renda Fixa | D66: BTG PACTUAL GESTÃO E CONSULTORIA DE INVESTIMENTOS LTDA | E66: btg | F66: 44712099 | G66: 33995143 | H66: 10716956 | I66: 5.4655898e+08 | J66: 5.7291259e+08 | K66: 1.96 | L66: 2.93 | M66: 59 | N66: desacelerando
A67: Patria Prev BP Seg FIC FIM CP | B67: 65.615.824/0001-11 | C67: Multimercados | D67: PÁTRIA INVESTIMENTOS LTDA. | E67: btg | F67: 10624882 | G67: 0 | H67: 10624882 | I67: 0 | J67: 10895883 | M67: 51 | N67: desacelerando
A68: Kinea Prev Ipca Dinamico II BTG Pactual FIRF RL | B68: 44.983.621/0001-08 | C68: Renda Fixa | D68: BTG PACTUAL GESTÃO E CONSULTORIA DE INVESTIMENTOS LTDA | E68: btg | F68: 22842838 | G68: 13027507 | H68: 9815330.7 | I68: 2.3613415e+08 | J68: 2.5563065e+08 | K68: 4.16 | L68: 4.22 | M68: 59 | N68: virou entrada
A69: BTG Pactual Reference S&P500 USD Prev FIM RL | B69: 44.025.397/0001-41 | C69: Multimercados | D69: BTG PACTUAL ASSET MANAGEMENT S/A DTVM | E69: btg | F69: 14950247 | G69: 5190599.8 | H69: 9759646.9 | I69: 92069574 | J69: 1.0435935e+08 | K69: 10.6 | L69: 2.62 | M69: 59 | N69: desacelerando
A70: Ibiuna Credit Prev FICFIM Access CrPr RL | B70: 44.672.703/0001-31 | C70: Multimercados | D70: BTG PACTUAL GESTÃO E CONSULTORIA DE INVESTIMENTOS LTDA | E70: btg | F70: 10075165 | G70: 1432814.8 | H70: 8642350.5 | I70: 39242337 | J70: 49118591 | K70: 22.02 | L70: 2.79 | M70: 59 | N70: desacelerando
A71: BTG Pactual Prev IMA B FICFIRF de Fundos de RF RL | B71: 22.187.479/0001-50 | C71: Renda Fixa | D71: BTG PACTUAL ASSET MANAGEMENT S/A DTVM | E71: btg | F71: 24607046 | G71: 16307287 | H71: 8299758.9 | I71: 3.3127114e+08 | J71: 3.5576942e+08 | K71: 2.51 | L71: 4.96 | M71: 59 | N71: virou entrada
A72: Root Hy Xp Seg Prev Ficfirf Cp | B72: 52.955.482/0001-37 | C72: Renda Fixa | D72: ROOT CAPITAL - GESTÃO DE RECURSOS LTDA | E72: xp | F72: 11217028 | G72: 4118537.1 | H72: 7098491.1 | I72: 1.8167016e+08 | J72: 1.9465231e+08 | K72: 3.91 | L72: 3.27 | M72: 59 | N72: desacelerando
A73: Arca Grão XP Seg Prev Advisory FIC FIM | B73: 42.794.534/0001-87 | C73: Multimercados | D73: GRÃO GESTÃO DE RECURSOS LTDA. | E73: xp | F73: 43071088 | G73: 36140093 | H73: 6930994.2 | I73: 7.7818873e+08 | J73: 8.1498466e+08 | K73: 0.89 | L73: 3.83 | M73: 59 | N73: virou saída
A74: Polo Crédito Corporativo Prev Xp Seg Fic Rf Cp Rl | B74: 52.955.528/0001-18 | C74: Renda Fixa | D74: POLO CAPITAL GESTÃO DE RECURSOS LTDA | E74: xp | F74: 23567179 | G74: 17145252 | H74: 6421927.3 | I74: 1.6848339e+08 | J74: 1.8101605e+08 | K74: 3.81 | L74: 3.14 | M74: 59 | N74: acelerando
A75: Sulamerica FIE I Credito ESG IS Prev Fundo CrPr RL | B75: 60.960.946/0001-21 | C75: Renda Fixa | D75: SUL AMÉRICA INVESTIMENTOS GESTORA DE RECURSOS S.A. | E75: btg | F75: 9136182.4 | G75: 2759537.6 | H75: 6376644.8 | I75: 50548182 | J75: 58628658 | K75: 12.61 | L75: 3.09 | M75: 59 | N75: desacelerando
A76: Polo Credito Prev I FICFIRF CrPr RL | B76: 59.065.619/0001-27 | C76: Renda Fixa | D76: POLO CAPITAL GESTÃO DE RECURSOS LTDA | E76: btg | F76: 6281042.9 | G76: 74562.63 | H76: 6206480.2 | I76: 7686383.1 | J76: 14173851 | K76: 80.75 | L76: 3.12 | M76: 59 | N76: acelerando
A77: Guardian BTG Prev FICFIRF CrPr RL | B77: 61.874.568/0001-26 | C77: Renda Fixa | D77: GUARDIAN GESTORA LTDA. | E77: btg | F77: 6857704.2 | G77: 682953.14 | H77: 6174751.1 | I77: 13615462 | J77: 20271000 | K77: 45.35 | L77: 3.1 | M77: 59 | N77: acelerando
A78: BTG Pactual Hedge Prev FIM CrPr RL | B78: 50.875.116/0001-42 | C78: Multimercados | D78: BTG PACTUAL ASSET MANAGEMENT S/A DTVM | E78: btg | F78: 7448148.2 | G78: 1494545.9 | H78: 5953602.3 | I78: 76271606 | J78: 84070658 | K78: 7.81 | L78: 2.87 | M78: 59 | N78: desacelerando
A79: MAG Prev BP FIRF CrPr RL | B79: 41.579.176/0001-27 | C79: Renda Fixa | D79: MONGERAL AEGON INVESTIMENTOS LTDA | E79: btg | F79: 9589167.5 | G79: 3856323.7 | H79: 5732843.8 | I79: 49456268 | J79: 56794789 | K79: 11.59 | L79: 3.18 | M79: 59 | N79: acelerando
... A105: Riza Lotus Prev FICFIRF CrPr RL | B105: 56.954.063/0001-31 | C105: Renda Fixa | D105: RIZA LÍQUIDOS GESTORA DE RECURSOS LTDA. | E105: btg | F105: 5636518.8 | G105: 2324849.7 | H105: 3311669.1 | I105: 26466627 | J105: 30674355 | K105: 12.51 | L105: 3.33 | M105: 59 | N105: acelerando
A106: Finacap BP Prev 70 FIF MM | B106: 67.671.091/0001-68 | C106: Multimercados | D106: FINACAP INVESTIMENTOS LTDA | E106: btg | F106: 3118789.9 | G106: 0 | H106: 3118789.9 | I106: 3000000 | J106: 3113260.5 | K106: 103.96 | L106: -0.21 | M106: 13 | N106: sem série | O106: sim
A107: Icatu Vanguarda Igarate Prev BP FICFIM CrPr RL | B107: 57.205.240/0001-40 | C107: Multimercados | D107: ICATU VANGUARDA GESTÃO DE RECURSOS LTDA | E107: btg | F107: 3135735.5 | G107: 26894.92 | H107: 3108840.6 | I107: 2678779.5 | J107: 5959791.6 | K107: 116.05 | L107: 3.17 | M107: 59 | N107: desacelerando
A108: SPX Prev Fundo Access CrPr RL | B108: 61.760.793/0001-31 | C108: Renda Fixa | D108: BTG PACTUAL GESTÃO E CONSULTORIA DE INVESTIMENTOS LTDA | E108: btg | F108: 3600008.6 | G108: 618120.34 | H108: 2981888.2 | I108: 13962014 | J108: 17403559 | K108: 21.36 | L108: 3.1 | M108: 59 | N108: desacelerando
A109: Arca Grão Xp Seguros Prev Fic Rf Cp Rl | B109: 61.304.623/0001-42 | C109: Renda Fixa | D109: GRÃO GESTÃO DE RECURSOS LTDA. | E109: xp | F109: 6224295.5 | G109: 3315922.5 | H109: 2908373 | I109: 40207102 | J109: 44203447 | K109: 7.23 | L109: 2.98 | M109: 59 | N109: virou saída
A110: Trend Ibovespa 70 XP Seg Prev FIC FIM RL | B110: 33.784.183/0001-32 | C110: Balanceados | D110: XP ALLOCATION ASSET MANAGEMENT LTDA | E110: xp | F110: 5321043.4 | G110: 2436026.2 | H110: 2885017.2 | I110: 40358895 | J110: 46287904 | K110: 7.15 | L110: 7.36 | M110: 59 | N110: desacelerando
A111: Armor Prev FIE I FIF MM | B111: 64.157.228/0001-72 | C111: Multimercados | D111: ARMOR GESTORA DE RECURSOS LTDA. | E111: btg | F111: 2833673.7 | G111: 0 | H111: 2833673.7 | I111: 1000000 | J111: 2986428.2 | K111: 283.37 | L111: 1.95 | M111: 39 | N111: estável
A112: BTG Pactual Tesouro Ipca Longo Prev FICFIRF de RF RL | B112: 27.762.397/0001-05 | C112: Renda Fixa | D112: BTG PACTUAL ASSET MANAGEMENT S/A DTVM | E112: btg | F112: 9044321.1 | G112: 6246622.3 | H112: 2797698.8 | I112: 1.3798578e+08 | J112: 1.4807197e+08 | K112: 2.03 | L112: 5.49 | M112: 59 | N112: acelerando
A113: Dahlia Total Return BP Prev FICFIM RL | B113: 53.675.501/0001-34 | C113: Multimercados | D113: DAHLIA CAPITAL GESTÃO DE RECURSOS LTDA. | E113: btg | F113: 3396652 | G113: 605962.5 | H113: 2790689.5 | I113: 12584495 | J113: 15663550 | K113: 22.18 | L113: 1.95 | M113: 59 | N113: desacelerando
A114: Kinea Prev Apolo BTG FICFIM RL | B114: 59.719.333/0001-18 | C114: Multimercados | D114: KINEA INVESTIMENTOS LTDA. | E114: btg | F114: 2908455.7 | G114: 139417.81 | H114: 2769037.9 | I114: 2736909.8 | J114: 5628033.7 | K114: 101.17 | L114: 3.1 | M114: 59 | N114: desacelerando
A115: Occam Liquidez XP Seg Prev FIC FIRF CP RL | B115: 63.799.359/0001-90 | C115: Renda Fixa | D115: NOVA OCCAM BRASIL GESTAO DE RECURSOS LTDA. | E115: xp | F115: 2782084 | G115: 141711.56 | H115: 2640372.4 | I115: 8146013.5 | J115: 10982014 | K115: 32.41 | L115: 3.15 | M115: 59 | N115: desacelerando
A116: Tríade Prev Fic Fim Cp Rl | B116: 53.991.216/0001-22 | C116: Multimercados | D116: PARAMIS BR INVESTIMENTOS LTDA | E116: xp | F116: 8521727.7 | G116: 5903147.6 | H116: 2618580.1 | I116: 1.6260627e+08 | J116: 1.7004808e+08 | K116: 1.61 | L116: 3.09 | M116: 59 | N116: virou entrada
A117: RPS Prev Absoluto BP Prev FICFIM RL | B117: 42.730.862/0001-10 | C117: Multimercados | D117: RPS CAPITAL ADMINISTRADORA DE RECURSOS LTDA | E117: btg | F117: 3715842.8 | G117: 1174722.2 | H117: 2541120.7 | I117: 14020157 | J117: 16812332 | K117: 18.12 | L117: 1.99 | M117: 59 | N117: virou entrada
A118: Guepardo Icatu Qualificado 100 Prev FIE Tipo 1 FICFIM RL | B118: 45.605.046/0001-72 | C118: Multimercados | D118: GUEPARDO INVESTIMENTOS LTDA | E118: btg | F118: 3823516.4 | G118: 1317007.4 | H118: 2506509 | I118: 52078350 | J118: 65892121 | K118: 4.81 | L118: 21.34 | M118: 59 | N118: acelerando
... A269: Absolute Endurance XP Seg FICFIA Prev | B269: 37.355.605/0001-05 | C269: Ações | D269: ABSOLUTE GESTAO DE INVESTIMENTOS LTDA | E269: xp | F269: 1296552.6 | G269: 2541331.7 | H269: -1244779 | I269: 23591232 | J269: 23442494 | K269: -5.28 | L269: 5.24 | M269: 59 | N269: virou entrada
A270: Reach Prev Moderado FIM Prev MM RL | B270: 32.398.441/0001-80 | C270: Multimercados | D270: REACH CAPITAL INVESTIMENTOS S.A | E270: btg | F270: 77783.95 | G270: 1369194 | H270: -1291410 | I270: 2054421.6 | J270: 1215999 | K270: -62.86 | L270: -1.14 | M270: 59 | N270: virou entrada | O270: sim
A271: BTG Autoinvest Balanceado Prev FIM CrPr RL | B271: 44.672.908/0001-17 | C271: Multimercados | D271: BTG PACTUAL GESTÃO E CONSULTORIA DE INVESTIMENTOS LTDA | E271: btg | F271: 46364.47 | G271: 1340037.3 | H271: -1293672.8 | I271: 3098423.5 | J271: 1910275.8 | K271: -41.75 | L271: 4.16 | M271: 59 | N271: saída persistente
A272: Tork Long Only XP Seg Prev FIC FIA FIE | B272: 34.432.014/0001-04 | C272: Multimercados | D272: XP GESTÃO DE RECURSOS LTDA | E272: xp | F272: 0 | G272: 1313564.4 | H272: -1313564.4 | I272: 5601996 | J272: 4272434.5 | K272: -23.45 | L272: 0.41 | M272: 59 | N272: saída persistente
A273: Porto Selection Prev FICFIRF FIE 1 CrPr RL | B273: 51.639.846/0001-07 | C273: Renda Fixa | D273: PORTO SEGURO INVESTIMENTOS LTDA | E273: btg | F273: 292553.91 | G273: 1672450.2 | H273: -1379896.3 | I273: 25249594 | J273: 24631562 | K273: -5.47 | L273: 3.11 | M273: 59 | N273: saída persistente
A274: ARX Income Icatu Prev FIM RL | B274: 03.879.361/0001-48 | C274: Multimercados | D274: ARX INVESTIMENTOS LTDA | E274: btg | F274: 2348862.3 | G274: 3728919.2 | H274: -1380056.9 | I274: 89353859 | J274: 94181155 | K274: -1.54 | L274: 6.55 | M274: 59 | N274: saída persistente
A275: 3R Genus Hedge Prev FIM RL | B275: 51.694.298/0001-18 | C275: Multimercados | D275: 3R GESTORA DE RECURSOS LTDA | E275: btg | F275: 0 | G275: 1480889 | H275: -1480889 | I275: 1807719.5 | J275: 333381.86 | K275: -81.92 | L275: 0.03 | M275: 59 | N275: saída persistente | O275: sim
A276: Occam Xp Seg Prev Fic Fim Rl | B276: 32.312.361/0001-60 | C276: Multimercados | D276: XP VIDA E PREVIDÊNCIA S.A. | E276: xp | F276: 31475.71 | G276: 1523150.3 | H276: -1491674.6 | I276: 16392555 | J276: 15277231 | K276: -9.1 | L276: 2.43 | M276: 59 | N276: saída persistente
A277: Sulamérica Prestige Xp Seg Prev Fif Rf Rl | B277: 46.334.681/0001-25 | C277: Renda Fixa | D277: SUL AMÉRICA INVESTIMENTOS GESTORA DE RECURSOS S.A. | E277: xp | F277: 13103558 | G277: 14694393 | H277: -1590835.5 | I277: 1.4810743e+08 | J277: 1.5136382e+08 | K277: -1.07 | L277: 2.96 | M277: 59 | N277: virou entrada
A278: Hix Xp Seg Prev Fic Fim | B278: 40.779.216/0001-11 | C278: Multimercados | D278: XP VIDA E PREVIDÊNCIA S.A. | E278: xp | F278: 1287225 | G278: 2895294.1 | H278: -1608069 | I278: 31967961 | J278: 30931233 | K278: -5.03 | L278: 1.94 | M278: 59 | N278: virou entrada
A279: Oceana Long Biased Advisory XP Seg Prev FIC FIM | B279: 38.236.291/0001-94 | C279: Multimercados | D279: OCEANA INVESTIMENTOS ADMINISTRADORA DE CARTEIRA DE VALORES MOBILIÁRIOS LTDA | E279: xp | F279: 2483328.4 | G279: 4125029.7 | H279: -1641701.3 | I279: 43634921 | J279: 44017897 | K279: -3.76 | L279: 5.05 | M279: 59 | N279: virou entrada
A280: XP Strategy III Prev FIC FIM RL | B280: 46.099.658/0001-01 | C280: Multimercados | D280: XP VIDA E PREVIDÊNCIA S.A. | E280: xp | F280: 3404.83 | G280: 1657157.1 | H280: -1653752.3 | I280: 8532568.5 | J280: 6874698.8 | K280: -19.38 | L280: -0.09 | M280: 57 | N280: saída persistente
A281: Exes Prev FIE FICFIM CrPr RL | B281: 42.730.600/0001-55 | C281: Multimercados | D281: EXES GESTORA DE RECURSOS LTDA. | E281: btg | F281: 3651526.4 | G281: 5312550.1 | H281: -1661023.8 | I281: 1.5349496e+08 | J281: 1.5554487e+08 | K281: -1.08 | L281: 2.45 | M281: 59 | N281: virou entrada
A282: HIX Prev III Prev FICFIA RL | B282: 43.507.741/0001-76 | C282: Ações | D282: HIX INVESTIMENTOS LTDA | E282: btg | F282: 255767.11 | G282: 1948365.3 | H282: -1692598.2 | I282: 7444577.2 | J282: 5784234 | K282: -22.74 | L282: 0.97 | M282: 59 | N282: virou entrada
A283: Kad Ima-B Xp Seg Prev Ficfim Rl | B283: 44.434.888/0001-46 | C283: Multimercados | D283: XP VIDA E PREVIDÊNCIA S.A. | E283: xp | F283: 517671.58 | G283: 2228520.5 | H283: -1710848.9 | I283: 32509593 | J283: 32514045 | K283: -5.26 | L283: 5.52 | M283: 59 | N283: virou entrada
A284: Itaú Janeiro XP Seg FIF CIC MM RL | B284: 61.922.156/0001-14 | C284: Multimercados | D284: ITAU UNIBANCO ASSET MANAGEMENT LTDA. | E284: xp | F284: 1073751 | G284: 2808282 | H284: -1734531 | I284: 1.3185745e+08 | J284: 1.3267008e+08 | K284: -1.32 | L284: 2.41 | M284: 59 | N284: saída persistente
A285: Xp Long Biased Advisory Xp Seg Fic Fim | B285: 35.744.196/0001-03 | C285: Multimercados | D285: XP GESTÃO DE RECURSOS LTDA | E285: xp | F285: 345173.67 | G285: 2111266.6 | H285: -1766092.9 | I285: 21995412 | J285: 19904240 | K285: -8.03 | L285: -0.33 | M285: 59 | N285: saída persistente
A286: DNA Energy Prev XP Seg FIM | B286: 35.420.731/0001-70 | C286: Multimercados | D286: XP ADVISORY GESTAO DE RECURSOS LTDA | E286: xp | F286: 80717.69 | G286: 1860352.2 | H286: -1779634.5 | I286: 20752679 | J286: 19843133 | K286: -8.58 | L286: 4.39 | M286: 53 | N286: saída persistente
A287: Legacy Crédito Prev Advisory XP Seg FIC FIRF CP | B287: 42.195.844/0001-85 | C287: Renda Fixa | D287: LEGACY CAPITAL GESTORA DE RECURSOS LTDA. | E287: xp | F287: 209559.38 | G287: 1996115.6 | H287: -1786556.2 | I287: 25435024 | J287: 24213760 | K287: -7.02 | L287: 2.7 | M287: 59 | N287: saída persistente
... A321: AZ Quest Icatu Multi Prev FICFIM RL | B321: 18.534.967/0001-19 | C321: Multimercados | D321: AZ Quest Prev Ltda. | E321: btg | F321: 1130493 | G321: 4578860 | H321: -3448367 | I321: 58267132 | J321: 56495652 | K321: -5.92 | L321: 3.02 | M321: 59 | N321: saída persistente
A322: Atlas ONE Icatu 70 Prev FIM RL | B322: 33.520.932/0001-14 | C322: Multimercados | D322: ATLAS ONE INVESTIMENTOS GESTÃO DE RECURSOS LTDA. | E322: btg | F322: 460968.78 | G322: 3994676.8 | H322: -3533708 | I322: 6139963.3 | J322: 2337272.5 | K322: -57.55 | L322: -3.22 | M322: 59 | N322: saída persistente | O322: sim
A323: Riza Icatu Prev Low Vol FIM RL | B323: 31.248.460/0001-67 | C323: Multimercados | D323: RIZA LÍQUIDOS GESTORA DE RECURSOS LTDA. | E323: btg | F323: 4935450.2 | G323: 8520022.6 | H323: -3584572.5 | I323: 1.7792928e+08 | J323: 1.7954061e+08 | K323: -2.01 | L323: 2.96 | M323: 59 | N323: saída persistente
A324: Absolute Delfos Xp Seg Prev Fie I Fic Rf Cp Rl | B324: 61.904.092/0001-29 | C324: Renda Fixa | D324: ABSOLUTE CRÉDITO GESTÃO DE INVESTIMENTOS LTDA. | E324: xp | F324: 623950.07 | G324: 4244976.4 | H324: -3621026.3 | I324: 68250769 | J324: 67236227 | K324: -5.31 | L324: 3.04 | M324: 59 | N324: virou entrada
A325: Giant Prev FIE FIC FIM | B325: 32.847.791/0001-86 | C325: Multimercados | D325: XP VIDA E PREVIDÊNCIA S.A. | E325: xp | F325: 1173102.3 | G325: 4817213.6 | H325: -3644111.3 | I325: 34179506 | J325: 31599224 | K325: -10.66 | L325: 3.02 | M325: 59 | N325: saída persistente
A326: Kinea Prev Atlas BTG Pactual FICFIM RL | B326: 37.728.756/0001-61 | C326: Multimercados | D326: BTG PACTUAL GESTÃO E CONSULTORIA DE INVESTIMENTOS LTDA | E326: btg | F326: 6554147.2 | G326: 10283706 | H326: -3729558.9 | I326: 1.252601e+08 | J326: 1.2628383e+08 | K326: -2.98 | L326: 3.98 | M326: 59 | N326: saída persistente
A327: Brasil Capital 100 B Prev FICFIA RL | B327: 38.015.734/0001-17 | C327: Ações | D327: BC GESTÃO DE RECURSOS LTDA | E327: btg | F327: 41997.86 | G327: 3843706.2 | H327: -3801708.4 | I327: 12310683 | J327: 9839807.4 | K327: -30.88 | L327: 13.48 | M327: 59 | N327: saída persistente
A328: Dahlia Global 50 Advisory XP Seg Prev FIC FIM | B328: 37.645.515/0001-59 | C328: Multimercados | D328: DAHLIA CAPITAL GESTÃO DE RECURSOS LTDA. | E328: xp | F328: 2833959.8 | G328: 6636608.6 | H328: -3802648.8 | I328: 83406033 | J328: 81449940 | K328: -4.56 | L328: 2.25 | M328: 59 | N328: virou entrada
A329: Ace Capital Prev Iq Xp Seg Fic Fim | B329: 37.541.379/0001-57 | C329: Multimercados | D329: ACE CAPITAL GESTORA DE RECURSOS LTDA. | E329: xp | F329: 1355984.8 | G329: 5233698.1 | H329: -3877713.2 | I329: 37177059 | J329: 34283151 | K329: -10.43 | L329: 2.84 | M329: 59 | N329: saída persistente
A330: Franklin Valor e Liquidez Long Bias Prev FIC FIM | B330: 40.781.467/0001-30 | C330: Multimercados | D330: XP VIDA E PREVIDÊNCIA S.A. | E330: xp | F330: 554047.46 | G330: 4681986.4 | H330: -4127938.9 | I330: 69392409 | J330: 67755275 | K330: -5.95 | L330: 3.82 | M330: 59 | N330: saída persistente
A331: JGP BP Prev FICFIM CrPr RL | B331: 38.075.290/0001-05 | C331: Multimercados | D331: JGP GESTÃO DE RECURSOS LTDA | E331: btg | F331: 507408.37 | G331: 4635648.3 | H331: -4128240 | I331: 21293731 | J331: 17329341 | K331: -19.39 | L331: 2.32 | M331: 59 | N331: saída persistente
A332: Alaska Black 100 Advisory XP Seg Prev FIC FIM | B332: 35.939.857/0001-56 | C332: Multimercados | D332: ALASKA INVESTIMENTOS LTDA. | E332: xp | F332: 821554.64 | G332: 4963180.6 | H332: -4141625.9 | I332: 40688842 | J332: 37503202 | K332: -10.18 | L332: 2.76 | M332: 59 | N332: saída persistente
A333: Icatu SEG Global Equity Income 10 FIM Prev RL | B333: 28.557.951/0001-85 | C333: Multimercados | D333: ICATU VANGUARDA GESTÃO DE RECURSOS LTDA | E333: btg | F333: 902591.9 | G333: 5159751.7 | H333: -4257159.8 | I333: 79198196 | J333: 77709991 | K333: -5.38 | L333: 3.61 | M333: 59 | N333: saída persistente
A334: Vrb Advisory Prev Fundo De Investimento Multimercado | B334: 34.507.447/0001-73 | C334: Multimercados | D334: XP ADVISORY GESTAO DE RECURSOS LTDA | E334: xp | F334: 795187.41 | G334: 5207011.7 | H334: -4411824.2 | I334: 48509815 | J334: 45902924 | K334: -9.09 | L334: 4.13 | M334: 58 | N334: saída persistente
... A422: Kinea Alpes Prev BTG Prev FICFIRF CrPr RL | B422: 55.019.754/0001-85 | C422: Renda Fixa | D422: BTG PACTUAL GESTÃO E CONSULTORIA DE INVESTIMENTOS LTDA | E422: btg | F422: 21532654 | G422: 64154833 | H422: -42622180 | I422: 4.5194096e+08 | J422: 4.2516497e+08 | K422: -9.43 | L422: 3.18 | M422: 59 | N422: saída persistente
A423: Trend B26 Prev XP Seg FIC FIRF RL | B423: 24.714.864/0001-33 | C423: Renda Fixa | D423: XP VIDA E PREVIDÊNCIA S.A. | E423: xp | F423: 276213.97 | G423: 44069615 | H423: -43793401 | I423: 58474055 | J423: 15421757 | K423: -74.89 | L423: 2.7 | M423: 59 | N423: saída persistente | O423: sim
A424: Riza Evi Prev Xp Seg Ficfim Cp Rl | B424: 43.121.014/0001-76 | C424: Multimercados | D424: XP VIDA E PREVIDÊNCIA S.A. | E424: xp | F424: 1602472.8 | G424: 45495109 | H424: -43892636 | I424: 3.6103966e+08 | J424: 3.3592918e+08 | K424: -12.16 | L424: 5.57 | M424: 59 | N424: saída persistente
A425: Icatu Vanguarda POS Fixado FIRF Prev RL | B425: 33.520.901/0001-63 | C425: Renda Fixa | D425: ICATU VANGUARDA GESTÃO DE RECURSOS LTDA | E425: btg | F425: 92355608 | G425: 1.3810824e+08 | H425: -45752628 | I425: 1.9208064e+09 | J425: 1.9293258e+09 | K425: -2.38 | L425: 2.96 | M425: 59 | N425: saída persistente
A426: Root Capital Crédito HG PREV XP SEG FIC FIRF CP | B426: 48.940.997/0001-96 | C426: Renda Fixa | D426: ROOT CAPITAL - GESTÃO DE RECURSOS LTDA | E426: xp | F426: 428505.84 | G426: 47515126 | H426: -47086620 | I426: 7.154666e+08 | J426: 6.9005839e+08 | K426: -6.58 | L426: 3.13 | M426: 59 | N426: saída persistente
A427: Absolute Vertex Prev FIM Access RL | B427: 43.509.130/0001-67 | C427: Multimercados | D427: BTG PACTUAL GESTÃO E CONSULTORIA DE INVESTIMENTOS LTDA | E427: btg | F427: 3180673.3 | G427: 50904025 | H427: -47723352 | I427: 2.7988778e+08 | J427: 2.3821802e+08 | K427: -17.05 | L427: 2.21 | M427: 59 | N427: saída persistente
A428: Itau Global Dinamico Prev BP Dist. Fundo RL | B428: 50.235.964/0001-97 | C428: Renda Fixa | D428: ITAU UNIBANCO ASSET MANAGEMENT LTDA. | E428: btg | F428: 28855330 | G428: 76915183 | H428: -48059853 | I428: 3.6077726e+08 | J428: 3.2132153e+08 | K428: -13.32 | L428: 2.57 | M428: 59 | N428: saída persistente
A429: Valora BP Prev FICFIRF CrPr RL | B429: 49.627.172/0001-89 | C429: Renda Fixa | D429: VALORA RENDA FIXA LTDA. | E429: btg | F429: 6920779.6 | G429: 55343601 | H429: -48422821 | I429: 2.2853228e+08 | J429: 1.8510102e+08 | K429: -21.19 | L429: 2.54 | M429: 59 | N429: saída persistente
A430: SUL America Prev FICFIRF CrPr RL | B430: 33.701.820/0001-60 | C430: Renda Fixa | D430: SUL AMÉRICA INVESTIMENTOS GESTORA DE RECURSOS S.A. | E430: btg | F430: 2097426.7 | G430: 53820653 | H430: -51723226 | I430: 4.8670512e+08 | J430: 4.4986078e+08 | K430: -10.63 | L430: 3.11 | M430: 59 | N430: saída persistente
A431: AZ Quest Prev Icatu Luce FICFIRF CrPr RL | B431: 23.883.385/0001-88 | C431: Renda Fixa | D431: AZ Quest Prev Ltda. | E431: btg | F431: 11528864 | G431: 66240621 | H431: -54711757 | I431: 770391426 | J431: 7.3835276e+08 | K431: -7.1 | L431: 2.98 | M431: 59 | N431: saída persistente
A432: Absolute Vertex XP Seg Prev FIC FIM | B432: 40.882.496/0001-99 | C432: Multimercados | D432: XP VIDA E PREVIDÊNCIA S.A. | E432: xp | F432: 8117140.2 | G432: 74372831 | H432: -66255690 | I432: 5.7732999e+08 | J432: 5.2382611e+08 | K432: -11.48 | L432: 2.23 | M432: 59 | N432: saída persistente
A433: Sparta Prev Advisory Xp Seg Fic Rf Cp Rl | B433: 32.239.012/0001-60 | C433: Renda Fixa | D433: XP VIDA E PREVIDÊNCIA S.A. | E433: xp | F433: 38534957 | G433: 1.058789e+08 | H433: -67343944 | I433: 2.0441515e+09 | J433: 2.0367656e+09 | K433: -3.29 | L433: 2.92 | M433: 59 | N433: saída persistente
A434: V8 Vanquish Termo Xp Seg Prev Fic Fim Cp | B434: 47.032.970/0001-32 | C434: Multimercados | D434: V8 CAPITAL GESTÃO DE INVESTIMENTOS LTDA. | E434: xp | F434: 15051516 | G434: 1.0045123e+08 | H434: -85399712 | I434: 1.0860733e+09 | J434: 1.0327239e+09 | K434: -7.86 | L434: 2.94 | M434: 59 | N434: saída persistente
A435: Xp Corporate Light Cp Xp Seg Fic Rf Rl | B435: 30.910.166/0001-06 | C435: Renda Fixa | D435: XP VISTA ASSET MANAGEMENT LTDA. | E435: xp | F435: 62902305 | G435: 1.6709404e+08 | H435: -1.0419174e+08 | I435: 3.1974605e+09 | J435: 3.1910767e+09 | K435: -3.26 | L435: 3.09 | M435: 59 | N435: saída persistente
... A446: Kinea Alpes Prev Xp Seg Mm Cp Ficfi | B446: 43.636.203/0001-81 | C446: Multimercados | D446: XP VIDA E PREVIDÊNCIA S.A. | E446: xp | F446: 1.0537456e+08 | G446: 5.2654728e+08 | H446: -4.2117272e+08 | I446: 6.5252329e+09 | J446: 6.311666e+09 | K446: -6.45 | L446: 3.15 | M446: 59 | N446: saída persistente
A448: Legenda da coluna Tendência
A449: acelerando | B449: captando mais por dia que nos meses anteriores
A450: desacelerando | B450: ainda captando, mas menos por dia que antes
A451: virou entrada | B451: estava perdendo dinheiro e passou a captar
A452: virou saída | B452: estava captando e passou a perder dinheiro
A453: saída persistente | B453: perdendo dinheiro no último mês e na média anterior
...

Sheet Tendência de captação
A1: Tendência de captação
A2: Média diária de captação líquida por competência. A média diária existe porque o mês corrente tem menos pregões que os fechados - comparar totais brutos seria comparar calendários.
A4: Por vitrine
A5: Casa | B5: 07/2026 | C5: 08/2026 | D5: 09/2026 | E5: Dias observados
A6: BTG Pactual | B6: 14862703 | C6: 13243775 | D6: 24570924 | E6: 23, 21, 15
A7: XP Investimentos | B7: 3464331.5 | C7: -3439963 | D7: -2576676.2 | E7: 23, 21, 15
A10: Fundos por tendência
A11: saída persistente | B11: 194 | C11: perdendo dinheiro no último mês e na média anterior
A12: virou entrada | B12: 64 | C12: estava perdendo dinheiro e passou a captar
A13: acelerando | B13: 61 | C13: captando mais por dia que nos meses anteriores
A14: desacelerando | B14: 50 | C14: ainda captando, mas menos por dia que antes
A15: virou saída | B15: 32 | C15: estava captando e passou a perder dinheiro
A16: estável | B16: 27 | C16: sem mudança material no ritmo
A17: sem série | B17: 3 | C17: competências de menos para falar em tendência
A20: Acelerando - captando mais por dia que antes
A21: Fundo | B21: Vitrines | C21: 07/2026 | D21: 08/2026 | E21: 09/2026 | F21: Total (R$)
A22: BTG Pactual Tesouro Selic Prev FIRF Ref. DI RL | B22: btg | C22: 1859890.6 | D22: 7928117.9 | E22: 12532511 | F22: 3.9725562e+08
A23: Bradesco Ultra Xp Seg Prev Ficfirf | B23: xp | C23: 1403204.7 | D23: 2231404.1 | E23: 2331702.3 | F23: 1.1410873e+08
A24: Augme Prev Ficfim Cp | B24: xp | C24: 935962.38 | D24: 1340740.8 | E24: 1850614 | F24: 77441901
A25: Vinci Crédito Prev Advisory Firf Cp Rl | B25: xp | C25: 460249.49 | D25: 1289806.7 | E25: 2295275 | F25: 72100804
A26: Capitânia Previdence Xp Seg Fif Rf Cp Rl | B26: xp | C26: 1160001 | D26: 526739.73 | E26: 1785424.5 | F26: 64522925
A27: Bradesco Ultra Prev Access FICFIRF CrPr RL | B27: btg | C27: 116871.82 | D27: 1459377.5 | E27: 1793165.2 | F27: 60232457
A28: Trend B35 Prev XP Seg FIC FIRF RL | B28: xp | C28: 1034780.8 | D28: 545644.62 | E28: 1081855.2 | F28: 50404468
A29: Brave Prev XP Seguros FIC FIRF CP RL | B29: xp | C29: 829718.11 | D29: 620283.38 | E29: 1161782.7 | F29: 47212642
A30: Occam BP Prev FIRF CrPr RL | B30: btg | C30: 661665.36 | D30: 549179.96 | E30: 886354.57 | F30: 40046401
A31: Jive Soul 45 Xp Seg Prev Fic Multimercado Cp Rl | B31: xp | C31: 724475.52 | D31: 412213.99 | E31: 960534.61 | F31: 38766915
A32: Mapfre Confianza XP Seg FIC FIF RF RL | B32: xp | C32: 268967.22 | D32: 905036.6 | E32: 738356.56 | F32: 36267363
A33: BTG Pactual NTN B 2035 Yield Prev FIRF RL | B33: btg | C33: 916872.85 | D33: 195816.26 | E33: 719001.7 | F33: 35985243
A36: Viraram saída - captavam e passaram a perder
A37: Fundo | B37: Vitrines | C37: 07/2026 | D37: 08/2026 | E37: 09/2026 | F37: Total (R$)
A38: Vinland Credito P Prev T1 FICFIM CrPr RL | B38: btg | C38: 1476.46 | D38: 106416.79 | E38: -446398.21 | F38: -4427261.9
A39: Occam Liquidez Prev Xp Seg Fic Fim | B39: xp | C39: 83.51 | D39: 2834.08 | E39: -73081.48 | F39: -1034785.8
A40: Tenax RFA Prev FIE I FICFIRF CrPr RL | B40: btg | C40: 0 | D40: 8751.44 | E40: -77455.81 | F40: -978056.98
A41: Kapitalo Zeta Prev FICFIM Access RL | B41: btg | C41: 40994.26 | D41: 2002.06 | E41: -119379.93 | F41: -805787.79
A42: A1 RF Ativa Prev FICFIRF RL | B42: btg | C42: -228.06 | D42: 7377.53 | E42: -62858.2 | F42: -793190.35
A43: Dahlia 100 Prev FICFIM RL | B43: btg | C43: 29036.94 | D43: -16381.73 | E43: -69545.47 | F43: -719348.69
A44: Mantaro LB Prev Advisory XP Seg FIC FIM | B44: xp | C44: 22.86 | D44: 25.04 | E44: -28509.08 | F44: -426584.53
A45: Gauss Panorama Xp Seg Iq Prev Ficfim Cp Rl | B45: xp | C45: 0 | D45: 4691.46 | E45: -15891.52 | F45: -128652.05
A46: Santander Prev Icatu Lark I RF Cred Privado FICFIF RL | B46: btg | C46: 10.87 | D46: 11.9 | E46: -6094.94 | F46: -90924.14
A47: Santander Prev Icatu Strix Mult FIF RL | B47: btg | C47: 274.69 | D47: 252.09 | E47: -4540.55 | F47: -56496.44
A48: ARX Income 100 XP Seg Prev FIC FIA | B48: xp | C48: 15962.61 | D48: -10183.83 | E48: -13432.08 | F48: -48201.38
A49: Patria Pioneiro Long Only 100 Icatu Qualificado Prev FIE FICFIM RL | B49: btg | C49: -1735.48 | D49: 3540.76 | E49: -4351.66 | F49: -30835.13

Sheet Rentabilidade 12 meses
A1: Rentabilidade da vitrine em 12 meses
A2: Fonte | B2: Cota patrimonial do informe diário da CVM (INF_DIARIO) | C2: https://dados.cvm.gov.br/dataset/fi-doc-inf_diario
A3: Janela | B3: 12 meses, base na cota do fechamento de set/2025
A4: Período | B4: de 30/09/2025 a 23/09/2026
A5: Pregões | B5: 246
A6: Competências | B6: 12 (out/2025 a set/2026)
A7: Base na cota do FECHAMENTO da competência anterior à janela, a convenção de lâmina - a mesma da coluna '12 meses' da aba 'Rentabilidade por fundo'. A aba 'Rentabilidade 3 meses' parte do primeiro pregão do período. Janela longa separa quem ficou para trás: em três meses dominados pelo CDI, quase tudo fica a centésimos da mediana da categoria. Fundo que não existia no começo da janela fica de fora, na vitrine e na mediana de referência. Referência: mediana da mesma categoria no universo oficial, no mesmo prazo (23.640 fundos, 52 categorias com amostra >= 20). É o retorno dos fundos que a casa exibe, com o peso que eles têm no MERCADO - não o retorno dos clientes dela: a CVM publica cota, PL e cotistas por fundo, somando todos os distribuidores. Cota ex-provento. ÍNDICE = share do PL nos fundos abaixo da mediana dividido pelo share de fundos abaixo: abaixo de 1, o dinheiro EVITA os piores da categoria; acima de 1, se concentra neles. Cerca de metade de qualquer universo fica abaixo da mediana por construção, então a contagem de fundos sozinha não é sinal de nada.
A8: Sem as leituras por cotistas: em previdência o cotista do fundo (FIE) é a seguradora, não o participante: 438 dos 439 fundos de vitrine com informe têm 1 cotista (XP 213 de 214, BTG 226 de 226, informe de 23/09). Contar cotistas não mede gente.
A10: Casa | B10: Fundos com série | C10: Vitrine | D10: Cobertura | E10: Mediana dos fundos (%) | F10: Ponderada por PL (%) | G10: Fundos abaixo da mediana | H10: % dos fundos | I10: % do PL | J10: Índice PL
A11: XP Investimentos | B11: 203 | C11: 218 | D11: 0.931 | E11: 12.5663 | F11: 13.1674 | G11: 109 de 198 | H11: 0.5505 | I11: 0.2489 | J11: 0.452
A12: BTG Pactual | B12: 210 | C12: 226 | D12: 0.929 | E12: 12.831 | F12: 13.3785 | G12: 108 de 204 | H12: 0.5294 | I12: 0.239 | J12: 0.451
A14: Por categoria, em 12 meses
A15: Casa | B15: Categoria | C15: Fundos | D15: Mediana dos fundos (%) | E15: Ponderada por PL (%) | F15: Mediana da categoria no mercado (%) | G15: PL (R$)
A16: BTG Pactual | B16: Previdência Multimercado Livre | C16: 122 | D16: 12.156 | E16: 13.4361 | F16: 12.8202 | G16: 2.0608716e+10
A17: BTG Pactual | B17: Previdência RF Duração Livre Crédito Liv | C17: 38 | D17: 13.5143 | E17: 13.4913 | F17: 13.3877 | G17: 1.22397e+10
A18: BTG Pactual | B18: Previdência Ações Ativo | C18: 14 | D18: 9.3945 | E18: 10.129 | F18: 10.8339 | G18: 3.7660003e+08
A19: BTG Pactual | B19: Previdência RF Duração Livre Grau de Inv | C19: 6 | D19: 13.2255 | E19: 12.4795 | F19: 13.016 | G19: 4.8638875e+08
A20: BTG Pactual | B20: Renda Fixa Duração Livre Crédito Livre | C20: 5 | D20: 13.2172 | E20: 13.3143 | F20: 8.9461 | G20: 6.412092e+08
A21: XP Investimentos | B21: Previdência Multimercado Livre | C21: 124 | D21: 11.1891 | E21: 12.9057 | F21: 12.8202 | G21: 3.1750488e+10
A22: XP Investimentos | B22: Previdência RF Duração Livre Crédito Liv | C22: 34 | D22: 13.6502 | E22: 13.3358 | F22: 13.3877 | G22: 2.9992292e+10
A23: XP Investimentos | B23: Previdência Ações Ativo | C23: 18 | D23: 9.9662 | E23: 12.1902 | F23: 10.8339 | G23: 6.666525e+08
A24: XP Investimentos | B24: Previdência RF Duração Livre Grau de Inv | C24: 7 | D24: 13.6 | E24: 13.8539 | F24: 13.016 | G24: 8.4188038e+09

Sheet Rentabilidade 3 meses
A1: Rentabilidade da vitrine em 3 meses
A2: Fonte | B2: Cota patrimonial do informe diário da CVM (INF_DIARIO) | C2: https://dados.cvm.gov.br/dataset/fi-doc-inf_diario
A3: Janela | B3: 3 meses, base na cota do primeiro pregão do período
A4: Período | B4: de 01/07/2026 a 23/09/2026
A5: Pregões | B5: 60
A6: Competências | B6: 3 (jul/2026 a set/2026)
A7: Base na cota do PRIMEIRO PREGÃO do período - esta aba responde o retorno ENTRE DUAS DATAS. As abas 'Rentabilidade 12 meses' e 'Rentabilidade por fundo' usam o fechamento da competência anterior, que é a convenção de lâmina, e por isso o mesmo fundo sai com número ligeiramente diferente lá. Referência: mediana da mesma categoria no universo oficial, no mesmo prazo (24.420 fundos, 52 categorias com amostra >= 20). É o retorno dos fundos que a casa exibe, com o peso que eles têm no MERCADO - não o retorno dos clientes dela: a CVM publica cota, PL e cotistas por fundo, somando todos os distribuidores. Cota ex-provento. ÍNDICE = share do PL nos fundos abaixo da mediana dividido pelo share de fundos abaixo: abaixo de 1, o dinheiro EVITA os piores da categoria; acima de 1, se concentra neles. Cerca de metade de qualquer universo fica abaixo da mediana por construção, então a contagem de fundos sozinha não é sinal de nada.
A8: Sem as leituras por cotistas: em previdência o cotista do fundo (FIE) é a seguradora, não o participante: 438 dos 439 fundos de vitrine com informe têm 1 cotista (XP 213 de 214, BTG 226 de 226, informe de 23/09). Contar cotistas não mede gente.
A10: Casa | B10: Fundos com série | C10: Vitrine | D10: Cobertura | E10: Mediana dos fundos (%) | F10: Ponderada por PL (%) | G10: Fundos abaixo da mediana | H10: % dos fundos | I10: % do PL | J10: Índice PL
A11: XP Investimentos | B11: 208 | C11: 218 | D11: 0.954 | E11: 3.0927 | F11: 3.4642 | G11: 125 de 203 | H11: 0.6158 | I11: 0.7395 | J11: 1.201
A12: BTG Pactual | B12: 219 | C12: 226 | D12: 0.969 | E12: 3.0992 | F12: 3.3647 | G12: 133 de 213 | H12: 0.6244 | I12: 0.8 | J12: 1.281
A14: Por categoria, em 3 meses
A15: Casa | B15: Categoria | C15: Fundos | D15: Mediana dos fundos (%) | E15: Ponderada por PL (%) | F15: Mediana da categoria no mercado (%) | G15: PL (R$)
A16: BTG Pactual | B16: Previdência Multimercado Livre | C16: 126 | D16: 3.0494 | E16: 3.4993 | F16: 3.289 | G16: 2.0706605e+10
A17: BTG Pactual | B17: Previdência RF Duração Livre Crédito Liv | C17: 40 | D17: 3.0937 | E17: 3.1675 | F17: 3.1248 | G17: 1.2312018e+10
A18: BTG Pactual | B18: Previdência Ações Ativo | C18: 15 | D18: 5.1873 | E18: 3.6967 | F18: 6.078 | G18: 3.7774978e+08
A19: BTG Pactual | B19: Previdência RF Duração Livre Grau de Inv | C19: 6 | D19: 3.0054 | E19: 4.0373 | F19: 3.0704 | G19: 4.8638875e+08
A20: BTG Pactual | B20: Renda Fixa Duração Livre Crédito Livre | C20: 5 | D20: 3.1155 | E20: 3.1145 | F20: 3.0667 | G20: 6.412092e+08
A21: XP Investimentos | B21: Previdência Multimercado Livre | C21: 127 | D21: 3.0285 | E21: 3.7759 | F21: 3.289 | G21: 3.1891373e+10
A22: XP Investimentos | B22: Previdência RF Duração Livre Crédito Liv | C22: 35 | D22: 3.0612 | E22: 3.0986 | F22: 3.1248 | G22: 3.0003274e+10
A23: XP Investimentos | B23: Previdência Ações Ativo | C23: 18 | D23: 5.0591 | E23: 6.3088 | F23: 6.078 | G23: 6.666525e+08
A24: XP Investimentos | B24: Previdência RF Duração Livre Grau de Inv | C24: 8 | D24: 3.062 | E24: 3.0238 | F24: 3.0704 | G24: 8.4274858e+09

Sheet Mandato declarado
A1: Mandato declarado
A2: Fonte | B2: Extrato de informações da CVM (EXTRATO) - política de investimento | C2: https://dados.cvm.gov.br/dataset/fi-doc-extrato
A3: Período | B3: Não se aplica: mandato é condição vigente do regulamento, não medida de um intervalo.
A4: Mandato AUTORIZADO pelo regulamento, nunca exposição carregada. Medir o que a carteira de fato tem exigiria a CDA, fora do escopo.
A6: Casa | B6: Dimensão | C6: Share da vitrine | D6: Share das concorrentes | E6: Índice | F6: Aposta | G6: Teto mediano (%)
A7: BTG Pactual | B7: Exposição acima do patrimônio autorizada | C7: 0.0136 | D7: 0.0074 | E7: 1.84 | F7: acima | G7: 15
A8: BTG Pactual | B8: Crédito privado autorizado | C8: 0.8 | D8: 0.6815 | E8: 1.17 | F8: na média | G8: 50
A9: BTG Pactual | B9: Derivativos autorizados | C9: 0.8318 | D9: 0.7407 | E9: 1.12 | F9: na média
A10: BTG Pactual | B10: Fundo espelho | C10: 0.1212 | D10: 0.156 | E10: 0.78 | F10: na média
A11: BTG Pactual | B11: Ativo no exterior autorizado | C11: 0.7773 | D11: 0.763 | E11: 1.02 | F11: na média | G11: 20
A12: XP Investimentos | B12: Exposição acima do patrimônio autorizada | C12: 0.0074 | D12: 0.0136 | E12: 0.54 | F12: abaixo | G12: 100
A13: XP Investimentos | B13: Crédito privado autorizado | C13: 0.6815 | D13: 0.8 | E13: 0.85 | F13: na média | G13: 50
A14: XP Investimentos | B14: Derivativos autorizados | C14: 0.7407 | D14: 0.8318 | E14: 0.89 | F14: na média
A15: XP Investimentos | B15: Fundo espelho | C15: 0.156 | D15: 0.1212 | E15: 1.29 | F15: na média
A16: XP Investimentos | B16: Ativo no exterior autorizado | C16: 0.763 | D16: 0.7773 | E16: 0.98 | F16: na média | G16: 20

Sheet Coleta
A1: Fonte | B1: Status | C1: Fontes consultadas | D1: Fundos | E1: Observação
A2: XP Investimentos | B2: ok | C2: Site (navegador) | D2: 223
A3: BTG Pactual | B3: ok | C3: API interna | D3: 226
A4: Itaú Private | B4: ok | C4: Site (HTML) | D4: 41

Sheet Metodologia
A1: Metodologia e proveniência
A3: Gerado em | B3: 24/09/2026 12:36
A5: Fontes
A6: Fonte | B6: O que entra | C6: Endereço para consulta | D6: Arquivos que o monitor lê
A7: Vitrine - XP Investimentos | B7: fundos que a casa exibe ao cliente e as condições publicadas | C7: https://institucional.xpi.com.br/previdencia-privada/lista-de-fundos/#/
A8: Vitrine - BTG Pactual | B8: fundos que a casa exibe ao cliente e as condições publicadas | C8: https://investimentos.btgpactual.com/previdencia-privada/produtos
A9: Vitrine - Itaú Private | B9: fundos que a casa exibe ao cliente e as condições publicadas | C9: https://ww15.itau.com.br/privatebank/hotsite/catalogofundos2/tabela_rentabilidade/default.aspx
A10: Cadastro de fundos da CVM | B10: classificação ANBIMA, gestora, situação e o radar de registros | C10: https://dados.cvm.gov.br/dataset/fi-cad | D10: https://dados.cvm.gov.br/dados/FI/CAD/DADOS/
A11: Informe diário de fundos da CVM | B11: captação, resgates, patrimônio, cotistas e cota (rentabilidade) | C11: https://dados.cvm.gov.br/dataset/fi-doc-inf_diario | D11: https://dados.cvm.gov.br/dados/FI/DOC/INF_DIARIO/DADOS/
A12: Extrato de informações de fundos da CVM | B12: taxa de administração, mandato e condições de resgate | C12: https://dados.cvm.gov.br/dataset/fi-doc-extrato | D12: https://dados.cvm.gov.br/dados/FI/DOC/EXTRATO/DADOS/
A14: Período de cada aba
A15: Aba | B15: Fonte e período
A16: Captação por casa | B16: Informe diário da CVM (INF_DIARIO) - de 01/07/2026 a 22/09/2026 (3 competências: jul/2026, ago/2026, set/2026)
A17: Captação por fundo | B17: Informe diário da CVM (INF_DIARIO) - de 01/07/2026 a 22/09/2026 (3 competências: jul/2026, ago/2026, set/2026)
A18: Tendência de captação | B18: Informe diário da CVM (INF_DIARIO) - de 01/07/2026 a 22/09/2026 (3 competências: jul/2026, ago/2026, set/2026)
A19: Rentabilidade 12 meses | B19: Cota patrimonial do INF_DIARIO, base na cota do fechamento de set/2025 - de 30/09/2025 a 23/09/2026 (246 pregões)
A20: Rentabilidade 3 meses | B20: Cota patrimonial do INF_DIARIO, base na cota do primeiro pregão do período - de 01/07/2026 a 23/09/2026 (60 pregões)
A21: Mandato declarado | B21: Extrato de informações da CVM (EXTRATO) - Não se aplica: condição vigente do regulamento, não medida de período
A23: Vitrine (definição) | B23: Fundo presente no canal da própria casa: site público, API do portal ou área logada. Open Finance NÃO conta como vitrine - é o catálogo regulatório (tudo que a casa administra), usado aqui para enriquecer campos e medir o catálogo.
A24: Perfil de varejo | B24: Fundos exclusivos/restritos (registro CVM, público profissional, flag da casa ou nome) ficam FORA das abas de análise e moram na aba 'Restritos (auxiliar)' com o motivo. Qualificado não é motivo de corte.
A25: Gaps e exclusivos por CNPJ | B25: Não se aplica a este monitor: cada seguradora distribui pelo próprio veículo (FIE), então o mesmo gestor e a mesma estratégia têm CNPJ diferente em cada casa - em 23/09 as vitrines de XP e BTG dividiam 1 CNPJ (217 só na XP, 225 só no BTG). Gap e exclusividade por CNPJ medem a seguradora, não a oferta; a comparação que vale é por gestora e categoria. Por isso não há abas de gaps nem de oportunidade de grade, e nenhuma coluna 'Só nesta vitrine' ou 'Exclusivo'.
A26: Cotistas | B26: Não se aplica a este monitor: em previdência o cotista do fundo (FIE) é a seguradora, não o participante: 438 dos 439 fundos de vitrine com informe têm 1 cotista (XP 213 de 214, BTG 226 de 226, informe de 23/09). Contar cotistas não mede gente. Por isso não há aba 'Onde está a gente' nem colunas de cotistas.
A27: Precedência de fontes | B27: Open Finance > área logada > API do portal > navegador > HTML. Quando duas fontes discordam de um campo, vence a de maior confiança; as demais preenchem lacunas.
... A30: Gestora | B30: Vem do registro da CVM sempre que o fundo casa com a base (445 fundos nesta geração) - é o que faz a mesma gestora ter um nome só nas cinco casas. O nome publicado pela casa, quando diverge, fica em gestor_casa. Sem match, 5 gestoras foram inferidas pelo prefixo do nome do fundo e vão marcadas como inferidas.
A32: Coleta por casa
A33: XP Investimentos | B33: 24/09/2026 08:55 - status=ok | fontes: playwright=223 | vitrine=223 de 223
A34: BTG Pactual | B34: 24/09/2026 08:56 - status=ok | fontes: api-json=226 | vitrine=226 de 226
A35: Itaú Private | B35: 24/09/2026 08:56 - status=ok | fontes: html-scrape=41 | vitrine=41 de 41
